Workbook
Name Slicer_Customer_Type: #N/A
Name Slicer_Fuel_Type: #N/A
Name Slicer_Month: #N/A
Name Slicer_Region: #N/A
Name Slicer_Year: #N/A

Sheet Pivot 1
A1: Count of Order_ID | C1: Sum of Price(in lakh) | E1: Average of Discount% | G1: Average of Price(in lakh) | I1: Average of Rating_1_to_5 | K1: Row Labels | L1: Sum of Price(in lakh) | N1: Row Labels | O1: Count of Order_ID
A2: 1000 | C2: 9370.91 | E2: 0.018917686 | G2: 9.37091 | I2: 3.8537549 | K2: Pune | L2: 638.88 | N2: Audi | O2: 1
K3: Ludhiana | L3: 568.27 | N3: Honda | O3: 54
A4: Row Labels | B4: Count of Order_ID | D4: Row Labels | E4: Sum of Price(in lakh) | G4: Row Labels | H4: Count of Order_ID | I4: Average of Delivery_time | K4: Bhubaneswar | L4: 525.85 | N4: Hyundai | O4: 182
A5: Cancelled | B5: 51 | D5: Hyundai | E5: 1748.02 | F5: =GETPIVOTDATA("Price(in lakh)",$D$4,"Brand","Hyundai")/GETPIVOTDATA("Price(in lakh)",$D$4) -> 0.22931288 | G5: i10 Nios | H5: 33 | I5: 19.186966 | K5: Guwahati | L5: 447.9 | N5: Kia | O5: 64
A6: Delivered | B6: 936 | D6: Kia | E6: 713.53 | F6: =GETPIVOTDATA("Price(in lakh)",$D$4,"Brand","Kia")/GETPIVOTDATA("Price(in lakh)",$D$4) -> 0.093603975 | G6: Creta | H6: 34 | K6: Surat | L6: 436.28 | N6: Mahindra | O6: 86
A7: Pending Delivery | B7: 13 | D7: Mahindra | E7: 1010.6 | F7: =GETPIVOTDATA("Price(in lakh)",$D$4,"Brand","Mahindra")/GETPIVOTDATA("Price(in lakh)",$D$4) -> 0.13257491 | G7: i20 | H7: 41 | K7: Bhopal | L7: 429.37 | N7: Maruti Suzuki | O7: 360
A8: Grand Total | B8: 1000 | D8: Maruti Suzuki | E8: 2718.05 | F8: =GETPIVOTDATA("Price(in lakh)",$D$4,"Brand","Maruti Suzuki")/GETPIVOTDATA("Price(in lakh)",$D$4) -> 0.35656565 | G8: Punch | H8: 47 | K8: Mysuru | L8: 425.6 | N8: Mercedes-Benz | O8: 1
A9: Cancellation Rate | B9: =GETPIVOTDATA("Order_ID",$A$4,"Order_Status","Cancelled")/GETPIVOTDATA("Order_ID",$A$4) -> 0.051 | D9: Tata | E9: 1432.66 | F9: =GETPIVOTDATA("Price(in lakh)",$D$4,"Brand","Tata")/GETPIVOTDATA("Price(in lakh)",$D$4) -> 0.18794258 | G9: Nexon | H9: 50 | K9: Chandigarh | L9: 406.46 | N9: MG | O9: 23
D10: Grand Total | E10: 7622.86 | G10: Brezza | H10: 53 | K10: Ahmedabad | L10: 405.85 | N10: Renault | O10: 25
G11: Ertiga | H11: 56 | K11: Panipat | L11: 401.81 | N11: Skoda | O11: 16
A12: Sum of Price(in lakh) | B12: Column Labels | G12: Swift | H12: 57 | K12: Grand Total | L12: 4686.27 | N12: Tata | O12: 163
A13: Row Labels | B13: 2024 | C13: 2025 | D13: 2026 | E13: Grand Total | G13: Baleno | H13: 70 | N13: Toyota | O13: 12
A14: Jan | B14: 245.25 | C14: 159.71 | D14: 264.5 | E14: 669.46 | G14: Dzire | H14: 76 | K14: Row Labels | L14: Sum of Price(in lakh) | N14: Volkswagen | O14: 13
A15: Feb | B15: 184.66 | C15: 226.36 | D15: 237.22 | E15: 648.24 | G15: Grand Total | H15: 517 | K15: Hatchback | L15: 1737.9 | N15: Grand Total | O15: 1000
A16: Mar | B16: 240.19 | C16: 367.68 | D16: 361.21 | E16: 969.08 | K16: Luxury Sedan | L16: 62
A17: Apr | B17: 338.24 | C17: 308.57 | D17: 407.79 | E17: 1054.6 | K17: Luxury SUV | L17: 54 | N17: Row Labels | O17: Sum of Price(in lakh)
A18: May | B18: 218.58 | C18: 236.05 | D18: 173.2 | E18: 627.83 | K18: MPV | L18: 847.22 | N18: Harsh Nair | O18: 342.86
A19: Jun | B19: 198.21 | C19: 310.15 | D19: 275.1 | E19: 783.46 | K19: Sedan | L19: 1789.07 | N19: Gaurav Shah | O19: 270.58
A20: Jul | B20: 228.46 | C20: 245.15 | D20: 261.99 | E20: 735.6 | G20: Row Labels | H20: Count of Order_ID | I20: Sum of Price(in lakh) | K20: SUV | L20: 4880.72 | N20: Arjun Reddy | O20: 241.02
A21: Aug | B21: 231.96 | C21: 284.84 | D21: 364.77 | E21: 881.57 | G21: North | H21: 289 | I21: 2763.74 | K21: Grand Total | L21: 9370.91 | N21: Akash Verma | O21: 239.07
A22: Sep | B22: 205.31 | C22: 268.62 | D22: 349.71 | E22: 823.64 | G22: West | H22: 228 | I22: 2089.29 | N22: Varun Yadav | O22: 232.36
A23: Oct | B23: 353.8 | C23: 494.05 | E23: 847.85 | G23: South | H23: 230 | I23: 2088.76 | K23: Row Labels | L23: Sum of Price(in lakh) | N23: Akash Jain | O23: 216.32
A24: Nov | B24: 323.53 | C24: 360.72 | E24: 684.25 | G24: East | H24: 176 | I24: 1674.73 | K24: Patna Autoplex | L24: 520.79 | N24: Yash Sharma | O24: 215.35
A25: Dec | B25: 283.96 | C25: 361.37 | E25: 645.33 | G25: Central | H25: 77 | I25: 754.39 | K25: Ludhiana Wheels | L25: 519.46 | N25: Tarun Sharma | O25: 207.57
A26: Grand Total | B26: 3052.15 | C26: 3623.27 | D26: 2695.49 | E26: 9370.91 | G26: Grand Total | H26: 1000 | I26: 9370.91 | K26: Bengaluru Auto Hub | L26: 494.96 | N26: Nitin Pillai | O26: 207.14
K27: Pune Autoplex | L27: 477.79 | N27: Akash Pillai | O27: 203.07
G28: Row Labels | H28: Count of Order_ID | K28: Bhubaneswar Motors | L28: 472.53 | N28: Grand Total | O28: 2375.34
A29: Row Labels | B29: Count of Order_ID | D29: Row Labels | E29: Count of Order_ID | G29: Business Owner | H29: 183 | K29: Indore Wheels | L29: 464.54
A30: Social Media | B30: 157 | D30: After-Sales Support | E30: 24 | G30: Doctor | H30: 43 | K30: Surat Autoplex | L30: 454.99
A31: Referral | B31: 151 | D31: Delivery Delay | E31: 31 | G31: Engineer | H31: 101 | K31: Guwahati Automobiles | L31: 423.22
A32: Corporate Tie-up | B32: 143 | D32: Pricing | E32: 24 | G32: Farmer | H32: 49 | K32: Noida Car World | L32: 413.82
A33: Online Website | B33: 142 | D33: Sales Experience | E33: 22 | G33: Retired | H33: 47 | K33: Nagpur Motors | L33: 407.8
A34: Auto Expo/Event | B34: 140 | D34: Vehicle Quality | E34: 31 | G34: Salaried - Government | H34: 111 | K34: Grand Total | L34: 4649.9
A35: Walk-in | B35: 138 | D35: Grand Total | E35: 132 | G35: Salaried - Private | H35: 296
A36: Test Drive Campaign | B36: 129 | G36: Self-Employed Professional | H36: 99
A37: Grand Total | B37: 1000 | G37: Student/Other | H37: 13
G38: Teacher | H38: 58
G39: Grand Total | H39: 1000
A42: Count of Target Achieved | B42: Column Labels | G42: Row Labels | H42: Sum of Price(in lakh)
A43: Row Labels | B43: False | C43: True | D43: Grand Total | G43: Jan | H43: 669.46
A44: Akash Jain | C44: 25 | D44: 25 | G44: Feb | H44: 648.24
A45: Akash Khanna | C45: 11 | D45: 11 | G45: Mar | H45: 969.08
A46: Akash Pillai | C46: 15 | D46: 15 | G46: Apr | H46: 1054.6
A47: Akash Verma | C47: 25 | D47: 25 | G47: May | H47: 627.83
A48: Anjali Joshi | C48: 16 | D48: 16 | G48: Jun | H48: 783.46
A49: Ankit Malhotra | C49: 7 | D49: 7 | G49: Jul | H49: 735.6
A50: Ankit Rao | C50: 9 | D50: 9 | G50: Aug | H50: 881.57
A51: Ankit Verma | C51: 13 | D51: 13 | G51: Sep | H51: 823.64
A52: Arjun Pillai | C52: 13 | D52: 13 | G52: Oct | H52: 847.85
A53: Arjun Reddy | C53: 25 | D53: 25 | G53: Nov | H53: 684.25
A54: Arjun Verma | C54: 14 | D54: 14 | G54: Dec | H54: 645.33
A55: Ayesha Rao | B55: 5 | D55: 5 | G55: Grand Total | H55: 9370.91
A56: Divya Jain | C56: 10 | D56: 10
A57: Divya Kapoor | C57: 15 | D57: 15
A58: Faisal Shah | C58: 11 | D58: 11
A59: Gaurav Shah | C59: 32 | D59: 32
A60: Harsh Nair | C60: 38 | D60: 38
A61: Imran Das | C61: 9 | D61: 9
A62: Imran Joshi | C62: 15 | D62: 15
A63: Imran Patel | C63: 9 | D63: 9
A64: Imran Verma | C64: 20 | D64: 20
A65: Jatin Chauhan | C65: 12 | D65: 12
A66: Jatin Jain | C66: 9 | D66: 9
A67: Jatin Kapoor | C67: 16 | D67: 16
... A75: Lokesh Iyer | C75: 9 | D75: 9
A76: Lokesh Nair | B76: 5 | D76: 5
A77: Meera Saini | C77: 13 | D77: 13
A78: Mohit Bose | C78: 6 | D78: 6
A79: Mohit Mehta | C79: 10 | D79: 10
A80: Mohit Nair | C80: 8 | D80: 8
A81: Mohit Patel | C81: 18 | D81: 18
A82: Mohit Yadav | C82: 13 | D82: 13
A83: Nisha Iyer | C83: 12 | D83: 12
A84: Nisha Khanna | B84: 6 | D84: 6
A85: Nitin Das | C85: 9 | D85: 9
A86: Nitin Pillai | C86: 24 | D86: 24
A87: Priya Joshi | C87: 13 | D87: 13
A88: Priya Mishra | B88: 5 | D88: 5
A89: Priya Saini | C89: 14 | D89: 14
A90: Priya Singh | C90: 13 | D90: 13
A91: Rahul Kapoor | C91: 12 | D91: 12
A92: Rahul Rao | C92: 11 | D92: 11
A93: Shweta Malhotra | C93: 7 | D93: 7
A94: Shweta Mishra | C94: 10 | D94: 10
A95: Siddharth Joshi | C95: 18 | D95: 18
A96: Sneha Iyer | C96: 8 | D96: 8
A97: Tanvi Chauhan | C97: 9 | D97: 9
A98: Tanvi Reddy | C98: 15 | D98: 15
A99: Tanvi Shah | C99: 9 | D99: 9
A100: Tarun Mehta | C100: 22 | D100: 22
... A106: Varun Malhotra | C106: 23 | D106: 23
A107: Varun Saini | B107: 6 | D107: 6
A108: Varun Yadav | C108: 25 | D108: 25
A109: Vivek Das | B109: 8 | D109: 8
A110: Vivek Iyer | C110: 10 | D110: 10
A111: Vivek Mehta | C111: 21 | D111: 21
A112: Yash Bose | C112: 13 | D112: 13
A113: Yash Rao | C113: 12 | D113: 12
A114: Yash Shah | C114: 20 | D114: 20
...

Sheet Executive

Sheet Insights

Sheet Key Findings

Sheet Sales
A1: Order_ID | B1: Order_Date | C1: Month | D1: Year | E1: Delivery_Date | F1: Order_Status | G1: Delivery_time | H1: Customer_ID | I1: Customer_Name | J1: Gender | K1: Age | L1: City | M1: State | N1: Occupation | O1: Annual_Income_INR | P1: Customer_Type | Q1: Car_ID | R1: Brand | S1: Model | T1: Segment | U1: Fuel_Type | V1: Transmission | W1: Ex_Showroom_Price_INR | X1: Launch_Year | Y1: Warranty_Years | Z1: Dealer_ID | AA1: Region | AB1: Dealer_Name | AC1: Established_Year | AD1: Showroom_Area_SqFt | AE1: Dealer_Rating | AF1: Salesperson_ID | AG1: Salesperson_Name | AH1: Monthly_Target_Units | AI1: Target Achieved | AJ1: Color | AK1: Discount% | AL1: Discount_INR | AM1: Price | AN1: Price(in lakh) | AO1: Payment_Mode | AP1: Finance_Provider | AQ1: Lead_Source | AR1: Insurance_Bundled | AS1: Feedback_ID | AT1: Rating_1_to_5 | AU1: Recommend_Score_0_to_10 | AV1: Feedback_Channel | AW1: Complaint_Category
A2: ORD00001 | B2: 45294 | C2: =TEXT(B2,"mmm") -> Jan | D2: =TEXT(B2,"yyyy") -> 2024 | E2: 45309 | F2: Delivered | G2: =IF(E2=0,"",E2-B2) -> 15 | H2: CU0692 | I2: =VLOOKUP($H2,Customers!$A$1:$I$721,2,FALSE) -> Sachin Pillai | J2: =VLOOKUP($H2,Customers!$A$1:$I$721,3,FALSE) -> Male | K2: =VLOOKUP($H2,Customers!$A$1:$I$721,4,FALSE) -> 41 | L2: =VLOOKUP($H2,Customers!$A$1:$I$721,5,FALSE) -> Chandigarh | M2: =VLOOKUP($H2,Customers!$A$1:$I$721,6,FALSE) -> Chandigarh | N2: =VLOOKUP($H2,Customers!$A$1:$I$721,7,FALSE) -> Salaried - Government | O2: =VLOOKUP($H2,Customers!$A$1:$I$721,8,FALSE) -> 1020000 | P2: =VLOOKUP($H2,Customers!$A$1:$I$721,9,FALSE) -> Individual | Q2: C024 | R2: {=VLOOKUP($Q2,Cars[],{2,3,4,5,6,7,8,9},FALSE)} -> Mahindra | S2: Bolero | T2: SUV | U2: Diesel | V2: Manual | W2: 1000000 | X2: 2019 | Y2: 3 | Z2: D004 | AA2: =VLOOKUP(Z2,Dealers[],5,FALSE) -> North | AB2: {=VLOOKUP($Z2,Dealers[],{2,7,8,9},FALSE)} -> Chandigarh Car World | AC2: 2018 | AD2: 4500 | AE2: 4 | AF2: S012 | AG2: =VLOOKUP($AF2,SalesPerson[],2,FALSE) -> Tarun Sharma | AH2: =_xlfn.XLOOKUP(AG2,Salespersons!$B:$B,Salespersons!$G:$G,,0) -> 7 | AI2: =_xlfn.XLOOKUP(AG2,Salespersons!$B:$B,Salespersons!$I:$I,,0) -> True | AJ2: Blue | AK2: =AL2/W2 -> 0 | AL2: 0 | AM2: =W2-AL2 -> 1000000 | AN2: =AM2/100000 -> 10 | AO2: Cash | AP2: N/A | AQ2: Online Website | AR2: No
A3: ORD00002 | B3: 45294 | C3: =TEXT(B3,"mmm") -> Jan | D3: =TEXT(B3,"yyyy") -> 2024 | E3: 45324 | F3: Delivered | G3: =IF(E3=0,"",E3-B3) -> 30 | H3: CU0522 | I3: =VLOOKUP($H3,Customers!$A$1:$I$721,2,FALSE) -> Ashok Pillai | J3: =VLOOKUP($H3,Customers!$A$1:$I$721,3,FALSE) -> Male | K3: =VLOOKUP($H3,Customers!$A$1:$I$721,4,FALSE) -> 25 | L3: =VLOOKUP($H3,Customers!$A$1:$I$721,5,FALSE) -> Ludhiana | M3: =VLOOKUP($H3,Customers!$A$1:$I$721,6,FALSE) -> Punjab | N3: =VLOOKUP($H3,Customers!$A$1:$I$721,7,FALSE) -> Salaried - Private | O3: =VLOOKUP($H3,Customers!$A$1:$I$721,8,FALSE) -> 990000 | P3: =VLOOKUP($H3,Customers!$A$1:$I$721,9,FALSE) -> Individual | Q3: C005 | R3: {=VLOOKUP($Q3,Cars[],{2,3,4,5,6,7,8,9},FALSE)} -> Maruti Suzuki | S3: Brezza | T3: SUV | U3: Petrol | V3: Automatic | W3: 900000 | X3: 2022 | Y3: 3 | Z3: D005 | AA3: =VLOOKUP(Z3,Dealers[],5,FALSE) -> North | AB3: {=VLOOKUP($Z3,Dealers[],{2,7,8,9},FALSE)} -> Ludhiana Wheels | AC3: 2010 | AD3: 12000 | AE3: 4 | AF3: S014 | AG3: =VLOOKUP($AF3,SalesPerson[],2,FALSE) -> Harsh Nair | AH3: =_xlfn.XLOOKUP(AG3,Salespersons!$B:$B,Salespersons!$G:$G,,0) -> 8 | AI3: =_xlfn.XLOOKUP(AG3,Salespersons!$B:$B,Salespersons!$I:$I,,0) -> True | AJ3: Silver | AK3: =AL3/W3 -> 0 | AL3: 0 | AM3: =W3-AL3 -> 900000 | AN3: =AM3/100000 -> 9 | AO3: Loan/Finance | AP3: HDFC Bank | AQ3: Corporate Tie-up | AR3: No | AS3: {=VLOOKUP($A3,Feedback[],{2,4,5,6,7},FALSE)} -> FB0001 | AT3: 4 | AU3: 8 | AV3: Dealer Visit | AW3: None
A4: ORD00003 | B4: 45295 | C4: =TEXT(B4,"mmm") -> Jan | D4: =TEXT(B4,"yyyy") -> 2024 | E4: 45298 | F4: Delivered | G4: =IF(E4=0,"",E4-B4) -> 3 | H4: CU0319 | I4: =VLOOKUP($H4,Customers!$A$1:$I$721,2,FALSE) -> Divya Malhotra | J4: =VLOOKUP($H4,Customers!$A$1:$I$721,3,FALSE) -> Female | K4: =VLOOKUP($H4,Customers!$A$1:$I$721,4,FALSE) -> 27 | L4: =VLOOKUP($H4,Customers!$A$1:$I$721,5,FALSE) -> Delhi | M4: =VLOOKUP($H4,Customers!$A$1:$I$721,6,FALSE) -> Delhi | N4: =VLOOKUP($H4,Customers!$A$1:$I$721,7,FALSE) -> Salaried - Government | O4: =VLOOKUP($H4,Customers!$A$1:$I$721,8,FALSE) -> 1360000 | P4: =VLOOKUP($H4,Customers!$A$1:$I$721,9,FALSE) -> Individual | Q4: C015 | R4: {=VLOOKUP($Q4,Cars[],{2,3,4,5,6,7,8,9},FALSE)} -> Tata | S4: Punch | T4: SUV | U4: Petrol | V4: Manual | W4: 650000 | X4: 2021 | Y4: 3 | Z4: D001 | AA4: =VLOOKUP(Z4,Dealers[],5,FALSE) -> North | AB4: {=VLOOKUP($Z4,Dealers[],{2,7,8,9},FALSE)} -> Delhi Autoplex | AC4: 2013 | AD4: 4500 | AE4: 3.7 | AF4: S002 | AG4: =VLOOKUP($AF4,SalesPerson[],2,FALSE) -> Nisha Iyer | AH4: =_xlfn.XLOOKUP(AG4,Salespersons!$B:$B,Salespersons!$G:$G,,0) -> 4 | AI4: =_xlfn.XLOOKUP(AG4,Salespersons!$B:$B,Salespersons!$I:$I,,0) -> True | AJ4: Silver | AK4: =AL4/W4 -> 0.016923077 | AL4: 11000 | AM4: =W4-AL4 -> 639000 | AN4: =AM4/100000 -> 6.39 | AO4: Loan/Finance | AP4: ICICI Bank | AQ4: Corporate Tie-up | AR4: No | AS4: {=VLOOKUP($A4,Feedback[],{2,4,5,6,7},FALSE)} -> FB0002 | AT4: 5 | AU4: 10 | AV4: Phone | AW4: None
A5: ORD00004 | B5: 45297 | C5: =TEXT(B5,"mmm") -> Jan | D5: =TEXT(B5,"yyyy") -> 2024 | E5: 45312 | F5: Delivered | G5: =IF(E5=0,"",E5-B5) -> 15 | H5: CU0149 | I5: =VLOOKUP($H5,Customers!$A$1:$I$721,2,FALSE) -> Jatin Saini | J5: =VLOOKUP($H5,Customers!$A$1:$I$721,3,FALSE) -> Male | K5: =VLOOKUP($H5,Customers!$A$1:$I$721,4,FALSE) -> 33 | L5: =VLOOKUP($H5,Customers!$A$1:$I$721,5,FALSE) -> Pune | M5: =VLOOKUP($H5,Customers!$A$1:$I$721,6,FALSE) -> Maharashtra | N5: =VLOOKUP($H5,Customers!$A$1:$I$721,7,FALSE) -> Business Owner | O5: =VLOOKUP($H5,Customers!$A$1:$I$721,8,FALSE) -> 2200000 | P5: =VLOOKUP($H5,Customers!$A$1:$I$721,9,FALSE) -> Individual | Q5: C002 | R5: {=VLOOKUP($Q5,Cars[],{2,3,4,5,6,7,8,9},FALSE)} -> Maruti Suzuki | S5: Swift | T5: Hatchback | U5: Petrol | V5: Manual | W5: 650000 | X5: 2024 | Y5: 3 | Z5: D011 | AA5: =VLOOKUP(Z5,Dealers[],5,FALSE) -> West | AB5: {=VLOOKUP($Z5,Dealers[],{2,7,8,9},FALSE)} -> Nagpur Motors | AC5: 2019 | AD5: 12000 | AE5: 4.6 | AF5: S034 | AG5: =VLOOKUP($AF5,SalesPerson[],2,FALSE) -> Arjun Reddy | AH5: =_xlfn.XLOOKUP(AG5,Salespersons!$B:$B,Salespersons!$G:$G,,0) -> 5 | AI5: =_xlfn.XLOOKUP(AG5,Salespersons!$B:$B,Salespersons!$I:$I,,0) -> True | AJ5: Red | AK5: =AL5/W5 -> 0.016923077 | AL5: 11000 | AM5: =W5-AL5 -> 639000 | AN5: =AM5/100000 -> 6.39 | AO5: Cash | AP5: N/A | AQ5: Referral | AR5: Yes | AS5: {=VLOOKUP($A5,Feedback[],{2,4,5,6,7},FALSE)} -> FB0003 | AT5: 3 | AU5: 4 | AV5: Dealer Visit | AW5: Vehicle Quality
A6: ORD00005 | B6: 45297 | C6: =TEXT(B6,"mmm") -> Jan | D6: =TEXT(B6,"yyyy") -> 2024 | E6: 45321 | F6: Delivered | G6: =IF(E6=0,"",E6-B6) -> 24 | H6: CU0684 | I6: =VLOOKUP($H6,Customers!$A$1:$I$721,2,FALSE) -> Ravi Verma | J6: =VLOOKUP($H6,Customers!$A$1:$I$721,3,FALSE) -> Male | K6: =VLOOKUP($H6,Customers!$A$1:$I$721,4,FALSE) -> 21 | L6: =VLOOKUP($H6,Customers!$A$1:$I$721,5,FALSE) -> Panipat | M6: =VLOOKUP($H6,Customers!$A$1:$I$721,6,FALSE) -> Haryana | N6: =VLOOKUP($H6,Customers!$A$1:$I$721,7,FALSE) -> Salaried - Government | O6: =VLOOKUP($H6,Customers!$A$1:$I$721,8,FALSE) -> 490000 | P6: =VLOOKUP($H6,Customers!$A$1:$I$721,9,FALSE) -> Individual | Q6: C010 | R6: {=VLOOKUP($Q6,Cars[],{2,3,4,5,6,7,8,9},FALSE)} -> Hyundai | S6: Venue | T6: SUV | U6: Petrol | V6: Manual | W6: 800000 | X6: 2022 | Y6: 3 | Z6: D003 | AA6: =VLOOKUP(Z6,Dealers[],5,FALSE) -> North | AB6: {=VLOOKUP($Z6,Dealers[],{2,7,8,9},FALSE)} -> Panipat Motors | AC6: 2012 | AD6: 10000 | AE6: 4.2 | AF6: S011 | AG6: =VLOOKUP($AF6,SalesPerson[],2,FALSE) -> Yash Bose | AH6: =_xlfn.XLOOKUP(AG6,Salespersons!$B:$B,Salespersons!$G:$G,,0) -> 7 | AI6: =_xlfn.XLOOKUP(AG6,Salespersons!$B:$B,Salespersons!$I:$I,,0) -> True | AJ6: Silver | AK6: =AL6/W6 -> 0.035 | AL6: 28000 | AM6: =W6-AL6 -> 772000 | AN6: =AM6/100000 -> 7.72 | AO6: Cash | AP6: N/A | AQ6: Social Media | AR6: No | AS6: {=VLOOKUP($A6,Feedback[],{2,4,5,6,7},FALSE)} -> FB0004 | AT6: 5 | AU6: 10 | AV6: Email | AW6: None
A7: ORD00006 | B7: 45298 | C7: =TEXT(B7,"mmm") -> Jan | D7: =TEXT(B7,"yyyy") -> 2024 | E7: 45330 | F7: Delivered | G7: =IF(E7=0,"",E7-B7) -> 32 | H7: CU0167 | I7: =VLOOKUP($H7,Customers!$A$1:$I$721,2,FALSE) -> Komal Patel | J7: =VLOOKUP($H7,Customers!$A$1:$I$721,3,FALSE) -> Female | K7: =VLOOKUP($H7,Customers!$A$1:$I$721,4,FALSE) -> 25 | L7: =VLOOKUP($H7,Customers!$A$1:$I$721,5,FALSE) -> Coimbatore | M7: =VLOOKUP($H7,Customers!$A$1:$I$721,6,FALSE) -> Tamil Nadu | N7: =VLOOKUP($H7,Customers!$A$1:$I$721,7,FALSE) -> Business Owner | O7: =VLOOKUP($H7,Customers!$A$1:$I$721,8,FALSE) -> 2650000 | P7: =VLOOKUP($H7,Customers!$A$1:$I$721,9,FALSE) -> Individual | Q7: C003 | R7: {=VLOOKUP($Q7,Cars[],{2,3,4,5,6,7,8,9},FALSE)} -> Maruti Suzuki | S7: Baleno | T7: Hatchback | U7: Petrol | V7: Automatic | W7: 760000 | X7: 2022 | Y7: 2 | Z7: D002 | AA7: =VLOOKUP(Z7,Dealers[],5,FALSE) -> North | AB7: {=VLOOKUP($Z7,Dealers[],{2,7,8,9},FALSE)} -> Gurugram Autoplex | AC7: 2007 | AD7: 10000 | AE7: 4 | AF7: S008 | AG7: =VLOOKUP($AF7,SalesPerson[],2,FALSE) -> Mohit Nair | AH7: =_xlfn.XLOOKUP(AG7,Salespersons!$B:$B,Salespersons!$G:$G,,0) -> 5 | AI7: =_xlfn.XLOOKUP(AG7,Salespersons!$B:$B,Salespersons!$I:$I,,0) -> True | AJ7: Grey | AK7: =AL7/W7 -> 0 | AL7: 0 | AM7: =W7-AL7 -> 760000 | AN7: =AM7/100000 -> 7.6 | AO7: Cash | AP7: N/A | AQ7: Online Website | AR7: No | AS7: {=VLOOKUP($A7,Feedback[],{2,4,5,6,7},FALSE)} -> FB0005 | AT7: 4 | AU7: 9 | AV7: Dealer Visit | AW7: None
A8: ORD00007 | B8: 45298 | C8: =TEXT(B8,"mmm") -> Jan | D8: =TEXT(B8,"yyyy") -> 2024 | E8: 45302 | F8: Delivered | G8: =IF(E8=0,"",E8-B8) -> 4 | H8: CU0340 | I8: =VLOOKUP($H8,Customers!$A$1:$I$721,2,FALSE) -> Siddharth Khanna | J8: =VLOOKUP($H8,Customers!$A$1:$I$721,3,FALSE) -> Male | K8: =VLOOKUP($H8,Customers!$A$1:$I$721,4,FALSE) -> 21 | L8: =VLOOKUP($H8,Customers!$A$1:$I$721,5,FALSE) -> Bhubaneswar | M8: =VLOOKUP($H8,Customers!$A$1:$I$721,6,FALSE) -> Odisha | N8: =VLOOKUP($H8,Customers!$A$1:$I$721,7,FALSE) -> Salaried - Private | O8: =VLOOKUP($H8,Customers!$A$1:$I$721,8,FALSE) -> 1070000 | P8: =VLOOKUP($H8,Customers!$A$1:$I$721,9,FALSE) -> Individual | Q8: C028 | R8: {=VLOOKUP($Q8,Cars[],{2,3,4,5,6,7,8,9},FALSE)} -> Honda | S8: City | T8: Sedan | U8: Petrol | V8: Automatic | W8: 1250000 | X8: 2023 | Y8: 4 | Z8: D021 | AA8: =VLOOKUP(Z8,Dealers[],5,FALSE) -> East | AB8: {=VLOOKUP($Z8,Dealers[],{2,7,8,9},FALSE)} -> Bhubaneswar Motors | AC8: 2008 | AD8: 4500 | AE8: 4.3 | AF8: S062 | AG8: =VLOOKUP($AF8,SalesPerson[],2,FALSE) -> Akash Jain | AH8: =_xlfn.XLOOKUP(AG8,Salespersons!$B:$B,Salespersons!$G:$G,,0) -> 5 | AI8: =_xlfn.XLOOKUP(AG8,Salespersons!$B:$B,Salespersons!$I:$I,,0) -> True | AJ8: Silver | AK8: =AL8/W8 -> 0.0496 | AL8: 62000 | AM8: =W8-AL8 -> 1188000 | AN8: =AM8/100000 -> 11.88 | AO8: Loan/Finance | AP8: HDFC Bank | AQ8: Online Website | AR8: No | AS8: {=VLOOKUP($A8,Feedback[],{2,4,5,6,7},FALSE)} -> FB0006 | AT8: 5 | AU8: 10 | AV8: Email | AW8: None
A9: ORD00008 | B9: 45300 | C9: =TEXT(B9,"mmm") -> Jan | D9: =TEXT(B9,"yyyy") -> 2024 | E9: 45319 | F9: Delivered | G9: =IF(E9=0,"",E9-B9) -> 19 | H9: CU0451 | I9: =VLOOKUP($H9,Customers!$A$1:$I$721,2,FALSE) -> Ravi Reddy | J9: =VLOOKUP($H9,Customers!$A$1:$I$721,3,FALSE) -> Male | K9: =VLOOKUP($H9,Customers!$A$1:$I$721,4,FALSE) -> 37 | L9: =VLOOKUP($H9,Customers!$A$1:$I$721,5,FALSE) -> Hyderabad | M9: =VLOOKUP($H9,Customers!$A$1:$I$721,6,FALSE) -> Telangana | N9: =VLOOKUP($H9,Customers!$A$1:$I$721,7,FALSE) -> Retired | O9: =VLOOKUP($H9,Customers!$A$1:$I$721,8,FALSE) -> 520000 | P9: =VLOOKUP($H9,Customers!$A$1:$I$721,9,FALSE) -> Individual | Q9: C004 | R9: {=VLOOKUP($Q9,Cars[],{2,3,4,5,6,7,8,9},FALSE)} -> Maruti Suzuki | S9: Dzire | T9: Sedan | U9: Petrol | V9: Manual | W9: 690000 | X9: 2024 | Y9: 3 | Z9: D018 | AA9: =VLOOKUP(Z9,Dealers[],5,FALSE) -> South | AB9: {=VLOOKUP($Z9,Dealers[],{2,7,8,9},FALSE)} -> Hyderabad Automobiles | AC9: 2019 | AD9: 4500 | AE9: 3.8 | AF9: S053 | AG9: =VLOOKUP($AF9,SalesPerson[],2,FALSE) -> Mohit Patel | AH9: =_xlfn.XLOOKUP(AG9,Salespersons!$B:$B,Salespersons!$G:$G,,0) -> 7 | AI9: =_xlfn.XLOOKUP(AG9,Salespersons!$B:$B,Salespersons!$I:$I,,0) -> True | AJ9: Grey | AK9: =AL9/W9 -> 0 | AL9: 0 | AM9: =W9-AL9 -> 690000 | AN9: =AM9/100000 -> 6.9 | AO9: Loan/Finance | AP9: SBI | AQ9: Referral | AR9: No | AS9: {=VLOOKUP($A9,Feedback[],{2,4,5,6,7},FALSE)} -> FB0007 | AT9: 4 | AU9: 9 | AV9: Phone | AW9: None
A10: ORD00009 | B10: 45300 | C10: =TEXT(B10,"mmm") -> Jan | D10: =TEXT(B10,"yyyy") -> 2024 | E10: 45310 | F10: Delivered | G10: =IF(E10=0,"",E10-B10) -> 10 | H10: CU0252 | I10: =VLOOKUP($H10,Customers!$A$1:$I$721,2,FALSE) -> Mohit Agarwal | J10: =VLOOKUP($H10,Customers!$A$1:$I$721,3,FALSE) -> Male | K10: =VLOOKUP($H10,Customers!$A$1:$I$721,4,FALSE) -> 47 | L10: =VLOOKUP($H10,Customers!$A$1:$I$721,5,FALSE) -> Bhopal | M10: =VLOOKUP($H10,Customers!$A$1:$I$721,6,FALSE) -> Madhya Pradesh | N10: =VLOOKUP($H10,Customers!$A$1:$I$721,7,FALSE) -> Salaried - Government | O10: =VLOOKUP($H10,Customers!$A$1:$I$721,8,FALSE) -> 1480000 | P10: =VLOOKUP($H10,Customers!$A$1:$I$721,9,FALSE) -> Individual | Q10: C004 | R10: {=VLOOKUP($Q10,Cars[],{2,3,4,5,6,7,8,9},FALSE)} -> Maruti Suzuki | S10: Dzire | T10: Sedan | U10: Petrol | V10: Manual | W10: 690000 | X10: 2024 | Y10: 3 | Z10: D025 | AA10: =VLOOKUP(Z10,Dealers[],5,FALSE) -> Central | AB10: {=VLOOKUP($Z10,Dealers[],{2,7,8,9},FALSE)} -> Indore Wheels | AC10: 2019 | AD10: 3000 | AE10: 4.7 | AF10: S074 | AG10: =VLOOKUP($AF10,SalesPerson[],2,FALSE) -> Kunal Shah | AH10: =_xlfn.XLOOKUP(AG10,Salespersons!$B:$B,Salespersons!$G:$G,,0) -> 8 | AI10: =_xlfn.XLOOKUP(AG10,Salespersons!$B:$B,Salespersons!$I:$I,,0) -> True | AJ10: Black | AK10: =AL10/W10 -> 0 | AL10: 0 | AM10: =W10-AL10 -> 690000 | AN10: =AM10/100000 -> 6.9 | AO10: Cash | AP10: N/A | AQ10: Online Website | AR10: No | AS10: {=VLOOKUP($A10,Feedback[],{2,4,5,6,7},FALSE)} -> FB0008 | AT10: 5 | AU10: 10 | AV10: Phone | AW10: None
A11: ORD00010 | B11: 45301 | C11: =TEXT(B11,"mmm") -> Jan | D11: =TEXT(B11,"yyyy") -> 2024 | E11: 45308 | F11: Delivered | G11: =IF(E11=0,"",E11-B11) -> 7 | H11: CU0468 | I11: =VLOOKUP($H11,Customers!$A$1:$I$721,2,FALSE) -> Gaurav Das | J11: =VLOOKUP($H11,Customers!$A$1:$I$721,3,FALSE) -> Male | K11: =VLOOKUP($H11,Customers!$A$1:$I$721,4,FALSE) -> 27 | L11: =VLOOKUP($H11,Customers!$A$1:$I$721,5,FALSE) -> Pune | M11: =VLOOKUP($H11,Customers!$A$1:$I$721,6,FALSE) -> Maharashtra | N11: =VLOOKUP($H11,Customers!$A$1:$I$721,7,FALSE) -> Salaried - Government | O11: =VLOOKUP($H11,Customers!$A$1:$I$721,8,FALSE) -> 750000 | P11: =VLOOKUP($H11,Customers!$A$1:$I$721,9,FALSE) -> Individual | Q11: C005 | R11: {=VLOOKUP($Q11,Cars[],{2,3,4,5,6,7,8,9},FALSE)} -> Maruti Suzuki | S11: Brezza | T11: SUV | U11: Petrol | V11: Automatic | W11: 900000 | X11: 2022 | Y11: 3 | Z11: D011 | AA11: =VLOOKUP(Z11,Dealers[],5,FALSE) -> West | AB11: {=VLOOKUP($Z11,Dealers[],{2,7,8,9},FALSE)} -> Nagpur Motors | AC11: 2019 | AD11: 12000 | AE11: 4.6 | AF11: S034 | AG11: =VLOOKUP($AF11,SalesPerson[],2,FALSE) -> Arjun Reddy | AH11: =_xlfn.XLOOKUP(AG11,Salespersons!$B:$B,Salespersons!$G:$G,,0) -> 5 | AI11: =_xlfn.XLOOKUP(AG11,Salespersons!$B:$B,Salespersons!$I:$I,,0) -> True | AJ11: White | AK11: =AL11/W11 -> 0.03 | AL11: 27000 | AM11: =W11-AL11 -> 873000 | AN11: =AM11/100000 -> 8.73 | AO11: Cash | AP11: N/A | AQ11: Online Website | AR11: Yes | AS11: {=VLOOKUP($A11,Feedback[],{2,4,5,6,7},FALSE)} -> FB0009 | AT11: 4 | AU11: 9 | AV11: Email | AW11: None
A12: ORD00011 | B12: 45303 | C12: =TEXT(B12,"mmm") -> Jan | D12: =TEXT(B12,"yyyy") -> 2024 | E12: 45318 | F12: Delivered | G12: =IF(E12=0,"",E12-B12) -> 15 | H12: CU0197 | I12: =VLOOKUP($H12,Customers!$A$1:$I$721,2,FALSE) -> Aman Mehta | J12: =VLOOKUP($H12,Customers!$A$1:$I$721,3,FALSE) -> Male | K12: =VLOOKUP($H12,Customers!$A$1:$I$721,4,FALSE) -> 52 | L12: =VLOOKUP($H12,Customers!$A$1:$I$721,5,FALSE) -> Gurugram | M12: =VLOOKUP($H12,Customers!$A$1:$I$721,6,FALSE) -> Haryana | N12: =VLOOKUP($H12,Customers!$A$1:$I$721,7,FALSE) -> Salaried - Private | O12: =VLOOKUP($H12,Customers!$A$1:$I$721,8,FALSE) -> 1180000 | P12: =VLOOKUP($H12,Customers!$A$1:$I$721,9,FALSE) -> Individual | Q12: C014 | R12: {=VLOOKUP($Q12,Cars[],{2,3,4,5,6,7,8,9},FALSE)} -> Tata | S12: Tiago | T12: Hatchback | U12: Petrol | V12: Manual | W12: 570000 | X12: 2022 | Y12: 3 | Z12: D003 | AA12: =VLOOKUP(Z12,Dealers[],5,FALSE) -> North | AB12: {=VLOOKUP($Z12,Dealers[],{2,7,8,9},FALSE)} -> Panipat Motors | AC12: 2012 | AD12: 10000 | AE12: 4.2 | AF12: S011 | AG12: =VLOOKUP($AF12,SalesPerson[],2,FALSE) -> Yash Bose | AH12: =_xlfn.XLOOKUP(AG12,Salespersons!$B:$B,Salespersons!$G:$G,,0) -> 7 | AI12: =_xlfn.XLOOKUP(AG12,Salespersons!$B:$B,Salespersons!$I:$I,,0) -> True | AJ12: Red | AK12: =AL12/W12 -> 0.019298246 | AL12: 11000 | AM12: =W12-AL12 -> 559000 | AN12: =AM12/100000 -> 5.59 | AO12: Cash | AP12: N/A | AQ12: Referral | AR12: Yes | AS12: {=VLOOKUP($A12,Feedback[],{2,4,5,6,7},FALSE)} -> FB0010 | AT12: 4 | AU12: 8 | AV12: Phone | AW12: None
A13: ORD00012 | B13: 45303 | C13: =TEXT(B13,"mmm") -> Jan | D13: =TEXT(B13,"yyyy") -> 2024 | E13: 45319 | F13: Delivered | G13: =IF(E13=0,"",E13-B13) -> 16 | H13: CU0336 | I13: =VLOOKUP($H13,Customers!$A$1:$I$721,2,FALSE) -> Kunal Bansal | J13: =VLOOKUP($H13,Customers!$A$1:$I$721,3,FALSE) -> Male | K13: =VLOOKUP($H13,Customers!$A$1:$I$721,4,FALSE) -> 57 | L13: =VLOOKUP($H13,Customers!$A$1:$I$721,5,FALSE) -> Pune | M13: =VLOOKUP($H13,Customers!$A$1:$I$721,6,FALSE) -> Maharashtra | N13: =VLOOKUP($H13,Customers!$A$1:$I$721,7,FALSE) -> Business Owner | O13: =VLOOKUP($H13,Customers!$A$1:$I$721,8,FALSE) -> 3160000 | P13: =VLOOKUP($H13,Customers!$A$1:$I$721,9,FALSE) -> Individual | Q13: C005 | R13: {=VLOOKUP($Q13,Cars[],{2,3,4,5,6,7,8,9},FALSE)} -> Maruti Suzuki | S13: Brezza | T13: SUV | U13: Petrol | V13: Automatic | W13: 900000 | X13: 2022 | Y13: 3 | Z13: D010 | AA13: =VLOOKUP(Z13,Dealers[],5,FALSE) -> West | AB13: {=VLOOKUP($Z13,Dealers[],{2,7,8,9},FALSE)} -> Pune Autoplex | AC13: 2014 | AD13: 3000 | AE13: 4.6 | AF13: S031 | AG13: =VLOOKUP($AF13,SalesPerson[],2,FALSE) -> Ankit Verma | AH13: =_xlfn.XLOOKUP(AG13,Salespersons!$B:$B,Salespersons!$G:$G,,0) -> 4 | AI13: =_xlfn.XLOOKUP(AG13,Salespersons!$B:$B,Salespersons!$I:$I,,0) -> True | AJ13: Grey | AK13: =AL13/W13 -> 0.045555556 | AL13: 41000 | AM13: =W13-AL13 -> 859000 | AN13: =AM13/100000 -> 8.59 | AO13: Cash | AP13: N/A | AQ13: Auto Expo/Event | AR13: No | AS13: No Feedback | AT13: No Feedback | AU13: No Feedback | AV13: No Feedback | AW13: No Feedback
A14: ORD00013 | B14: 45308 | C14: =TEXT(B14,"mmm") -> Jan | D14: =TEXT(B14,"yyyy") -> 2024 | E14: 45334 | F14: Delivered | G14: =IF(E14=0,"",E14-B14) -> 26 | H14: CU0680 | I14: =VLOOKUP($H14,Customers!$A$1:$I$721,2,FALSE) -> Ankit Gupta | J14: =VLOOKUP($H14,Customers!$A$1:$I$721,3,FALSE) -> Male | K14: =VLOOKUP($H14,Customers!$A$1:$I$721,4,FALSE) -> 26 | L14: =VLOOKUP($H14,Customers!$A$1:$I$721,5,FALSE) -> Ludhiana | M14: =VLOOKUP($H14,Customers!$A$1:$I$721,6,FALSE) -> Punjab | N14: =VLOOKUP($H14,Customers!$A$1:$I$721,7,FALSE) -> Farmer | O14: =VLOOKUP($H14,Customers!$A$1:$I$721,8,FALSE) -> 550000 | P14: =VLOOKUP($H14,Customers!$A$1:$I$721,9,FALSE) -> Individual | Q14: C015 | R14: {=VLOOKUP($Q14,Cars[],{2,3,4,5,6,7,8,9},FALSE)} -> Tata | S14: Punch | T14: SUV | U14: Petrol | V14: Manual | W14: 650000 | X14: 2021 | Y14: 3 | Z14: D005 | AA14: =VLOOKUP(Z14,Dealers[],5,FALSE) -> North | AB14: {=VLOOKUP($Z14,Dealers[],{2,7,8,9},FALSE)} -> Ludhiana Wheels | AC14: 2010 | AD14: 12000 | AE14: 4 | AF14: S015 | AG14: =VLOOKUP($AF14,SalesPerson[],2,FALSE) -> Akash Verma | AH14: =_xlfn.XLOOKUP(AG14,Salespersons!$B:$B,Salespersons!$G:$G,,0) -> 8 | AI14: =_xlfn.XLOOKUP(AG14,Salespersons!$B:$B,Salespersons!$I:$I,,0) -> True | AJ14: Silver | AK14: =AL14/W14 -> 0.018461538 | AL14: 12000 | AM14: =W14-AL14 -> 638000 | AN14: =AM14/100000 -> 6.38 | AO14: Cash | AP14: N/A | AQ14: Social Media | AR14: No | AS14: No Feedback | AT14: No Feedback | AU14: No Feedback | AV14: No Feedback | AW14: No Feedback
A15: ORD00014 | B15: 45309 | C15: =TEXT(B15,"mmm") -> Jan | D15: =TEXT(B15,"yyyy") -> 2024 | E15: 45325 | F15: Delivered | G15: =IF(E15=0,"",E15-B15) -> 16 | H15: CU0507 | I15: =VLOOKUP($H15,Customers!$A$1:$I$721,2,FALSE) -> Ashok Das | J15: =VLOOKUP($H15,Customers!$A$1:$I$721,3,FALSE) -> Male | K15: =VLOOKUP($H15,Customers!$A$1:$I$721,4,FALSE) -> 27 | L15: =VLOOKUP($H15,Customers!$A$1:$I$721,5,FALSE) -> Indore | M15: =VLOOKUP($H15,Customers!$A$1:$I$721,6,FALSE) -> Madhya Pradesh | N15: =VLOOKUP($H15,Customers!$A$1:$I$721,7,FALSE) -> Salaried - Private | O15: =VLOOKUP($H15,Customers!$A$1:$I$721,8,FALSE) -> 880000 | P15: =VLOOKUP($H15,Customers!$A$1:$I$721,9,FALSE) -> Individual | Q15: C012 | R15: {=VLOOKUP($Q15,Cars[],{2,3,4,5,6,7,8,9},FALSE)} -> Hyundai | S15: Verna | T15: Sedan | U15: Petrol | V15: Automatic | W15: 1100000 | X15: 2023 | Y15: 2 | Z15: D024 | AA15: =VLOOKUP(Z15,Dealers[],5,FALSE) -> Central | AB15: {=VLOOKUP($Z15,Dealers[],{2,7,8,9},FALSE)} -> Bhopal Autoplex | AC15: 2013 | AD15: 12000 | AE15: 3.9 | AF15: S071 | AG15: =VLOOKUP($AF15,SalesPerson[],2,FALSE) -> Imran Verma | AH15: =_xlfn.XLOOKUP(AG15,Salespersons!$B:$B,Salespersons!$G:$G,,0) -> 5 | AI15: =_xlfn.XLOOKUP(AG15,Salespersons!$B:$B,Salespersons!$I:$I,,0) -> True | AJ15: Black | AK15: =AL15/W15 -> 0 | AL15: 0 | AM15: =W15-AL15 -> 1100000 | AN15: =AM15/100000 -> 11 | AO15: Exchange + Loan | AP15: Tata Capital | AQ15: Social Media | AR15: No | AS15: {=VLOOKUP($A15,Feedback[],{2,4,5,6,7},FALSE)} -> FB0011 | AT15: 3 | AU15: 6 | AV15: Online Survey | AW15: After-Sales Support
A16: ORD00015 | B16: 45312 | C16: =TEXT(B16,"mmm") -> Jan | D16: =TEXT(B16,"yyyy") -> 2024 | E16: 45329 | F16: Delivered | G16: =IF(E16=0,"",E16-B16) -> 17 | H16: CU0161 | I16: =VLOOKUP($H16,Customers!$A$1:$I$721,2,FALSE) -> Imran Khanna | J16: =VLOOKUP($H16,Customers!$A$1:$I$721,3,FALSE) -> Male | K16: =VLOOKUP($H16,Customers!$A$1:$I$721,4,FALSE) -> 25 | L16: =VLOOKUP($H16,Customers!$A$1:$I$721,5,FALSE) -> Pune | M16: =VLOOKUP($H16,Customers!$A$1:$I$721,6,FALSE) -> Maharashtra | N16: =VLOOKUP($H16,Customers!$A$1:$I$721,7,FALSE) -> Salaried - Private | O16: =VLOOKUP($H16,Customers!$A$1:$I$721,8,FALSE) -> 960000 | P16: =VLOOKUP($H16,Customers!$A$1:$I$721,9,FALSE) -> Individual | Q16: C034 | R16: {=VLOOKUP($Q16,Cars[],{2,3,4,5,6,7,8,9},FALSE)} -> Volkswagen | S16: Virtus | T16: Sedan | U16: Petrol | V16: Automatic | W16: 1350000 | X16: 2022 | Y16: 3 | Z16: D011 | AA16: =VLOOKUP(Z16,Dealers[],5,FALSE) -> West | AB16: {=VLOOKUP($Z16,Dealers[],{2,7,8,9},FALSE)} -> Nagpur Motors | AC16: 2019 | AD16: 12000 | AE16: 4.6 | AF16: S034 | AG16: =VLOOKUP($AF16,SalesPerson[],2,FALSE) -> Arjun Reddy | AH16: =_xlfn.XLOOKUP(AG16,Salespersons!$B:$B,Salespersons!$G:$G,,0) -> 5 | AI16: =_xlfn.XLOOKUP(AG16,Salespersons!$B:$B,Salespersons!$I:$I,,0) -> True | AJ16: Silver | AK16: =AL16/W16 -> 0 | AL16: 0 | AM16: =W16-AL16 -> 1350000 | AN16: =AM16/100000 -> 13.5 | AO16: Loan/Finance | AP16: Axis Bank | AQ16: Social Media | AR16: No | AS16: {=VLOOKUP($A16,Feedback[],{2,4,5,6,7},FALSE)} -> FB0012 | AT16: 5 | AU16: 10 | AV16: Phone | AW16: None
A17: ORD00016 | B17: 45314 | C17: =TEXT(B17,"mmm") -> Jan | D17: =TEXT(B17,"yyyy") -> 2024 | E17: 45328 | F17: Delivered | G17: =IF(E17=0,"",E17-B17) -> 14 | H17: CU0637 | I17: =VLOOKUP($H17,Customers!$A$1:$I$721,2,FALSE) -> Kunal Singh | J17: =VLOOKUP($H17,Customers!$A$1:$I$721,3,FALSE) -> Male | K17: =VLOOKUP($H17,Customers!$A$1:$I$721,4,FALSE) -> 45 | L17: =VLOOKUP($H17,Customers!$A$1:$I$721,5,FALSE) -> Bengaluru | M17: =VLOOKUP($H17,Customers!$A$1:$I$721,6,FALSE) -> Karnataka | N17: =VLOOKUP($H17,Customers!$A$1:$I$721,7,FALSE) -> Student/Other | O17: =VLOOKUP($H17,Customers!$A$1:$I$721,8,FALSE) -> 480000 | P17: =VLOOKUP($H17,Customers!$A$1:$I$721,9,FALSE) -> Individual | Q17: C006 | R17: {=VLOOKUP($Q17,Cars[],{2,3,4,5,6,7,8,9},FALSE)} -> Maruti Suzuki | S17: Ertiga | T17: MPV | U17: CNG | V17: Manual | W17: 900000 | X17: 2022 | Y17: 3 | Z17: D015 | AA17: =VLOOKUP(Z17,Dealers[],5,FALSE) -> South | AB17: {=VLOOKUP($Z17,Dealers[],{2,7,8,9},FALSE)} -> Mysuru Auto Hub | AC17: 2006 | AD17: 4500 | AE17: 4.6 | AF17: S046 | AG17: =VLOOKUP($AF17,SalesPerson[],2,FALSE) -> Tanvi Reddy | AH17: =_xlfn.XLOOKUP(AG17,Salespersons!$B:$B,Salespersons!$G:$G,,0) -> 4 | AI17: =_xlfn.XLOOKUP(AG17,Salespersons!$B:$B,Salespersons!$I:$I,,0) -> True | AJ17: Black | AK17: =AL17/W17 -> 0.01 | AL17: 9000 | AM17: =W17-AL17 -> 891000 | AN17: =AM17/100000 -> 8.91 | AO17: Loan/Finance | AP17: ICICI Bank | AQ17: Referral | AR17: No | AS17: {=VLOOKUP($A17,Feedback[],{2,4,5,6,7},FALSE)} -> FB0013 | AT17: 5 | AU17: 9 | AV17: Dealer Visit | AW17: None
A18: ORD00017 | B18: 45314 | C18: =TEXT(B18,"mmm") -> Jan | D18: =TEXT(B18,"yyyy") -> 2024 | E18: 45329 | F18: Delivered | G18: =IF(E18=0,"",E18-B18) -> 15 | H18: CU0078 | I18: =VLOOKUP($H18,Customers!$A$1:$I$721,2,FALSE) -> Karan Chauhan | J18: =VLOOKUP($H18,Customers!$A$1:$I$721,3,FALSE) -> Male | K18: =VLOOKUP($H18,Customers!$A$1:$I$721,4,FALSE) -> 38 | L18: =VLOOKUP($H18,Customers!$A$1:$I$721,5,FALSE) -> Delhi | M18: =VLOOKUP($H18,Customers!$A$1:$I$721,6,FALSE) -> Delhi | N18: =VLOOKUP($H18,Customers!$A$1:$I$721,7,FALSE) -> Business Owner | O18: =VLOOKUP($H18,Customers!$A$1:$I$721,8,FALSE) -> 1260000 | P18: =VLOOKUP($H18,Customers!$A$1:$I$721,9,FALSE) -> Individual | Q18: C008 | R18: {=VLOOKUP($Q18,Cars[],{2,3,4,5,6,7,8,9},FALSE)} -> Hyundai | S18: i10 Nios | T18: Hatchback | U18: Petrol | V18: Manual | W18: 600000 | X18: 2023 | Y18: 3 | Z18: D001 | AA18: =VLOOKUP(Z18,Dealers[],5,FALSE) -> North | AB18: {=VLOOKUP($Z18,Dealers[],{2,7,8,9},FALSE)} -> Delhi Autoplex | AC18: 2013 | AD18: 4500 | AE18: 3.7 | AF18: S003 | AG18: =VLOOKUP($AF18,SalesPerson[],2,FALSE) -> Karan Verma | AH18: =_xlfn.XLOOKUP(AG18,Salespersons!$B:$B,Salespersons!$G:$G,,0) -> 5 | AI18: =_xlfn.XLOOKUP(AG18,Salespersons!$B:$B,Salespersons!$I:$I,,0) -> True | AJ18: Black | AK18: =AL18/W18 -> 0 | AL18: 0 | AM18: =W18-AL18 -> 600000 | AN18: =AM18/100000 -> 6 | AO18: Loan/Finance | AP18: ICICI Bank | AQ18: Corporate Tie-up | AR18: No | AS18: No Feedback | AT18: No Feedback | AU18: No Feedback | AV18: No Feedback | AW18: No Feedback
A19: ORD00018 | B19: 45314 | C19: =TEXT(B19,"mmm") -> Jan | D19: =TEXT(B19,"yyyy") -> 2024 | F19: Cancelled | G19: =IF(E19=0,"",E19-B19) | H19: CU0257 | I19: =VLOOKUP($H19,Customers!$A$1:$I$721,2,FALSE) -> Arjun Mehta | J19: =VLOOKUP($H19,Customers!$A$1:$I$721,3,FALSE) -> Male | K19: =VLOOKUP($H19,Customers!$A$1:$I$721,4,FALSE) -> 41 | L19: =VLOOKUP($H19,Customers!$A$1:$I$721,5,FALSE) -> Lucknow | M19: =VLOOKUP($H19,Customers!$A$1:$I$721,6,FALSE) -> Uttar Pradesh | N19: =VLOOKUP($H19,Customers!$A$1:$I$721,7,FALSE) -> Engineer | O19: =VLOOKUP($H19,Customers!$A$1:$I$721,8,FALSE) -> 1510000 | P19: =VLOOKUP($H19,Customers!$A$1:$I$721,9,FALSE) -> Individual | Q19: C006 | R19: {=VLOOKUP($Q19,Cars[],{2,3,4,5,6,7,8,9},FALSE)} -> Maruti Suzuki | S19: Ertiga | T19: MPV | U19: CNG | V19: Manual | W19: 900000 | X19: 2022 | Y19: 3 | Z19: D008 | AA19: =VLOOKUP(Z19,Dealers[],5,FALSE) -> North | AB19: {=VLOOKUP($Z19,Dealers[],{2,7,8,9},FALSE)} -> Noida Car World | AC19: 2007 | AD19: 10000 | AE19: 3.8 | AF19: S023 | AG19: =VLOOKUP($AF19,SalesPerson[],2,FALSE) -> Kunal Jain | AH19: =_xlfn.XLOOKUP(AG19,Salespersons!$B:$B,Salespersons!$G:$G,,0) -> 8 | AI19: =_xlfn.XLOOKUP(AG19,Salespersons!$B:$B,Salespersons!$I:$I,,0) -> True | AJ19: Grey | AK19: =AL19/W19 -> 0.036666667 | AL19: 33000 | AM19: =W19-AL19 -> 867000 | AN19: =AM19/100000 -> 8.67 | AO19: Cash | AP19: N/A | AQ19: Corporate Tie-up | AR19: No | AS19: No Feedback | AT19: No Feedback | AU19: No Feedback | AV19: No Feedback | AW19: No Feedback
A20: ORD00019 | B20: 45315 | C20: =TEXT(B20,"mmm") -> Jan | D20: =TEXT(B20,"yyyy") -> 2024 | E20: 45318 | F20: Delivered | G20: =IF(E20=0,"",E20-B20) -> 3 | H20: CU0557 | I20: =VLOOKUP($H20,Customers!$A$1:$I$721,2,FALSE) -> Mahesh Malhotra | J20: =VLOOKUP($H20,Customers!$A$1:$I$721,3,FALSE) -> Male | K20: =VLOOKUP($H20,Customers!$A$1:$I$721,4,FALSE) -> 46 | L20: =VLOOKUP($H20,Customers!$A$1:$I$721,5,FALSE) -> Panipat | M20: =VLOOKUP($H20,Customers!$A$1:$I$721,6,FALSE) -> Haryana | N20: =VLOOKUP($H20,Customers!$A$1:$I$721,7,FALSE) -> Salaried - Private | O20: =VLOOKUP($H20,Customers!$A$1:$I$721,8,FALSE) -> 1690000 | P20: =VLOOKUP($H20,Customers!$A$1:$I$721,9,FALSE) -> Individual | Q20: C032 | R20: {=VLOOKUP($Q20,Cars[],{2,3,4,5,6,7,8,9},FALSE)} -> Kia | S20: Carens | T20: MPV | U20: Diesel | V20: Manual | W20: 1200000 | X20: 2022 | Y20: 3 | Z20: D003 | AA20: =VLOOKUP(Z20,Dealers[],5,FALSE) -> North | AB20: {=VLOOKUP($Z20,Dealers[],{2,7,8,9},FALSE)} -> Panipat Motors | AC20: 2012 | AD20: 10000 | AE20: 4.2 | AF20: S010 | AG20: =VLOOKUP($AF20,SalesPerson[],2,FALSE) -> Rahul Rao | AH20: =_xlfn.XLOOKUP(AG20,Salespersons!$B:$B,Salespersons!$G:$G,,0) -> 5 | AI20: =_xlfn.XLOOKUP(AG20,Salespersons!$B:$B,Salespersons!$I:$I,,0) -> True | AJ20: Silver | AK20: =AL20/W20 -> 0.043333333 | AL20: 52000 | AM20: =W20-AL20 -> 1148000 | AN20: =AM20/100000 -> 11.48 | AO20: Exchange + Loan | AP20: Axis Bank | AQ20: Test Drive Campaign | AR20: Yes | AS20: {=VLOOKUP($A20,Feedback[],{2,4,5,6,7},FALSE)} -> FB0014 | AT20: 5 | AU20: 10 | AV20: Email | AW20: None
A21: ORD00020 | B21: 45316 | C21: =TEXT(B21,"mmm") -> Jan | D21: =TEXT(B21,"yyyy") -> 2024 | E21: 45348 | F21: Delivered | G21: =IF(E21=0,"",E21-B21) -> 32 | H21: CU0408 | I21: =VLOOKUP($H21,Customers!$A$1:$I$721,2,FALSE) -> Gaurav Mehta | J21: =VLOOKUP($H21,Customers!$A$1:$I$721,3,FALSE) -> Male | K21: =VLOOKUP($H21,Customers!$A$1:$I$721,4,FALSE) -> 21 | L21: =VLOOKUP($H21,Customers!$A$1:$I$721,5,FALSE) -> Ludhiana | M21: =VLOOKUP($H21,Customers!$A$1:$I$721,6,FALSE) -> Punjab | N21: =VLOOKUP($H21,Customers!$A$1:$I$721,7,FALSE) -> Teacher | O21: =VLOOKUP($H21,Customers!$A$1:$I$721,8,FALSE) -> 470000 | P21: =VLOOKUP($H21,Customers!$A$1:$I$721,9,FALSE) -> Individual | Q21: C004 | R21: {=VLOOKUP($Q21,Cars[],{2,3,4,5,6,7,8,9},FALSE)} -> Maruti Suzuki | S21: Dzire | T21: Sedan | U21: Petrol | V21: Manual | W21: 690000 | X21: 2024 | Y21: 3 | Z21: D005 | AA21: =VLOOKUP(Z21,Dealers[],5,FALSE) -> North | AB21: {=VLOOKUP($Z21,Dealers[],{2,7,8,9},FALSE)} -> Ludhiana Wheels | AC21: 2010 | AD21: 12000 | AE21: 4 | AF21: S015 | AG21: =VLOOKUP($AF21,SalesPerson[],2,FALSE) -> Akash Verma | AH21: =_xlfn.XLOOKUP(AG21,Salespersons!$B:$B,Salespersons!$G:$G,,0) -> 8 | AI21: =_xlfn.XLOOKUP(AG21,Salespersons!$B:$B,Salespersons!$I:$I,,0) -> True | AJ21: Black | AK21: =AL21/W21 -> 0 | AL21: 0 | AM21: =W21-AL21 -> 690000 | AN21: =AM21/100000 -> 6.9 | AO21: Cash | AP21: N/A | AQ21: Walk-in | AR21: No | AS21: {=VLOOKUP($A21,Feedback[],{2,4,5,6,7},FALSE)} -> FB0015 | AT21: 4 | AU21: 7 | AV21: Phone | AW21: None
A22: ORD00021 | B22: 45317 | C22: =TEXT(B22,"mmm") -> Jan | D22: =TEXT(B22,"yyyy") -> 2024 | E22: 45328 | F22: Delivered | G22: =IF(E22=0,"",E22-B22) -> 11 | H22: CU0193 | I22: =VLOOKUP($H22,Customers!$A$1:$I$721,2,FALSE) -> Sneha Gupta | J22: =VLOOKUP($H22,Customers!$A$1:$I$721,3,FALSE) -> Female | K22: =VLOOKUP($H22,Customers!$A$1:$I$721,4,FALSE) -> 29 | L22: =VLOOKUP($H22,Customers!$A$1:$I$721,5,FALSE) -> Chandigarh | M22: =VLOOKUP($H22,Customers!$A$1:$I$721,6,FALSE) -> Chandigarh | N22: =VLOOKUP($H22,Customers!$A$1:$I$721,7,FALSE) -> Self-Employed Professional | O22: =VLOOKUP($H22,Customers!$A$1:$I$721,8,FALSE) -> 1390000 | P22: =VLOOKUP($H22,Customers!$A$1:$I$721,9,FALSE) -> Individual | Q22: C011 | R22: {=VLOOKUP($Q22,Cars[],{2,3,4,5,6,7,8,9},FALSE)} -> Hyundai | S22: Creta | T22: SUV | U22: Diesel | V22: Automatic | W22: 1250000 | X22: 2024 | Y22: 4 | Z22: D014 | AA22: =VLOOKUP(Z22,Dealers[],5,FALSE) -> South | AB22: {=VLOOKUP($Z22,Dealers[],{2,7,8,9},FALSE)} -> Bengaluru Auto Hub | AC22: 2013 | AD22: 12000 | AE22: 4.4 | AF22: S042 | AG22: =VLOOKUP($AF22,SalesPerson[],2,FALSE) -> Yash Sharma | AH22: =_xlfn.XLOOKUP(AG22,Salespersons!$B:$B,Salespersons!$G:$G,,0) -> 5 | AI22: =_xlfn.XLOOKUP(AG22,Salespersons!$B:$B,Salespersons!$I:$I,,0) -> True | AJ22: Silver | AK22: =AL22/W22 -> 0.0176 | AL22: 22000 | AM22: =W22-AL22 -> 1228000 | AN22: =AM22/100000 -> 12.28 | AO22: Cash | AP22: N/A | AQ22: Online Website | AR22: No | AS22: {=VLOOKUP($A22,Feedback[],{2,4,5,6,7},FALSE)} -> FB0016 | AT22: 5 | AU22: 10 | AV22: Email | AW22: None
A23: ORD00022 | B23: 45317 | C23: =TEXT(B23,"mmm") -> Jan | D23: =TEXT(B23,"yyyy") -> 2024 | E23: 45339 | F23: Delivered | G23: =IF(E23=0,"",E23-B23) -> 22 | H23: CU0010 | I23: =VLOOKUP($H23,Customers!$A$1:$I$721,2,FALSE) -> Nisha Mishra | J23: =VLOOKUP($H23,Customers!$A$1:$I$721,3,FALSE) -> Female | K23: =VLOOKUP($H23,Customers!$A$1:$I$721,4,FALSE) -> 21 | L23: =VLOOKUP($H23,Customers!$A$1:$I$721,5,FALSE) -> Pune | M23: =VLOOKUP($H23,Customers!$A$1:$I$721,6,FALSE) -> Maharashtra | N23: =VLOOKUP($H23,Customers!$A$1:$I$721,7,FALSE) -> Student/Other | O23: =VLOOKUP($H23,Customers!$A$1:$I$721,8,FALSE) -> 590000 | P23: =VLOOKUP($H23,Customers!$A$1:$I$721,9,FALSE) -> Individual | Q23: C012 | R23: {=VLOOKUP($Q23,Cars[],{2,3,4,5,6,7,8,9},FALSE)} -> Hyundai | S23: Verna | T23: Sedan | U23: Petrol | V23: Automatic | W23: 1100000 | X23: 2023 | Y23: 2 | Z23: D010 | AA23: =VLOOKUP(Z23,Dealers[],5,FALSE) -> West | AB23: {=VLOOKUP($Z23,Dealers[],{2,7,8,9},FALSE)} -> Pune Autoplex | AC23: 2014 | AD23: 3000 | AE23: 4.6 | AF23: S032 | AG23: =VLOOKUP($AF23,SalesPerson[],2,FALSE) -> Nitin Pillai | AH23: =_xlfn.XLOOKUP(AG23,Salespersons!$B:$B,Salespersons!$G:$G,,0) -> 6 | AI23: =_xlfn.XLOOKUP(AG23,Salespersons!$B:$B,Salespersons!$I:$I,,0) -> True | AJ23: Black | AK23: =AL23/W23 -> 0 | AL23: 0 | AM23: =W23-AL23 -> 1100000 | AN23: =AM23/100000 -> 11 | AO23: Exchange + Loan | AP23: Tata Capital | AQ23: Walk-in | AR23: No | AS23: No Feedback | AT23: No Feedback | AU23: No Feedback | AV23: No Feedback | AW23: No Feedback
A24: ORD00023 | B24: 45320 | C24: =TEXT(B24,"mmm") -> Jan | D24: =TEXT(B24,"yyyy") -> 2024 | E24: 45335 | F24: Delivered | G24: =IF(E24=0,"",E24-B24) -> 15 | H24: CU0033 | I24: =VLOOKUP($H24,Customers!$A$1:$I$721,2,FALSE) -> Suresh Nair | J24: =VLOOKUP($H24,Customers!$A$1:$I$721,3,FALSE) -> Male | K24: =VLOOKUP($H24,Customers!$A$1:$I$721,4,FALSE) -> 38 | L24: =VLOOKUP($H24,Customers!$A$1:$I$721,5,FALSE) -> Guwahati | M24: =VLOOKUP($H24,Customers!$A$1:$I$721,6,FALSE) -> Assam | N24: =VLOOKUP($H24,Customers!$A$1:$I$721,7,FALSE) -> Teacher | O24: =VLOOKUP($H24,Customers!$A$1:$I$721,8,FALSE) -> 620000 | P24: =VLOOKUP($H24,Customers!$A$1:$I$721,9,FALSE) -> Individual | Q24: C033 | R24: {=VLOOKUP($Q24,Cars[],{2,3,4,5,6,7,8,9},FALSE)} -> Skoda | S24: Slavia | T24: Sedan | U24: Petrol | V24: Automatic | W24: 1300000 | X24: 2022 | Y24: 3 | Z24: D023 | AA24: =VLOOKUP(Z24,Dealers[],5,FALSE) -> East | AB24: {=VLOOKUP($Z24,Dealers[],{2,7,8,9},FALSE)} -> Guwahati Automobiles | AC24: 2005 | AD24: 12000 | AE24: 4.4 | AF24: S070 | AG24: =VLOOKUP($AF24,SalesPerson[],2,FALSE) -> Tarun Mehta | AH24: =_xlfn.XLOOKUP(AG24,Salespersons!$B:$B,Salespersons!$G:$G,,0) -> 4 | AI24: =_xlfn.XLOOKUP(AG24,Salespersons!$B:$B,Salespersons!$I:$I,,0) -> True | AJ24: Silver | AK24: =AL24/W24 -> 0.016923077 | AL24: 22000 | AM24: =W24-AL24 -> 1278000 | AN24: =AM24/100000 -> 12.78 | AO24: Exchange + Loan | AP24: HDFC Bank | AQ24: Referral | AR24: No | AS24: {=VLOOKUP($A24,Feedback[],{2,4,5,6,7},FALSE)} -> FB0017 | AT24: 4 | AU24: 7 | AV24: Email | AW24: None
A25: ORD00024 | B25: 45320 | C25: =TEXT(B25,"mmm") -> Jan | D25: =TEXT(B25,"yyyy") -> 2024 | E25: 45354 | F25: Delivered | G25: =IF(E25=0,"",E25-B25) -> 34 | H25: CU0463 | I25: =VLOOKUP($H25,Customers!$A$1:$I$721,2,FALSE) -> Nitin Gupta | J25: =VLOOKUP($H25,Customers!$A$1:$I$721,3,FALSE) -> Male | K25: =VLOOKUP($H25,Customers!$A$1:$I$721,4,FALSE) -> 49 | L25: =VLOOKUP($H25,Customers!$A$1:$I$721,5,FALSE) -> Panipat | M25: =VLOOKUP($H25,Customers!$A$1:$I$721,6,FALSE) -> Haryana | N25: =VLOOKUP($H25,Customers!$A$1:$I$721,7,FALSE) -> Salaried - Private | O25: =VLOOKUP($H25,Customers!$A$1:$I$721,8,FALSE) -> 1440000 | P25: =VLOOKUP($H25,Customers!$A$1:$I$721,9,FALSE) -> Individual | Q25: C016 | R25: {=VLOOKUP($Q25,Cars[],{2,3,4,5,6,7,8,9},FALSE)} -> Tata | S25: Nexon | T25: SUV | U25: Diesel | V25: Manual | W25: 950000 | X25: 2023 | Y25: 3 | Z25: D002 | AA25: =VLOOKUP(Z25,Dealers[],5,FALSE) -> North | AB25: {=VLOOKUP($Z25,Dealers[],{2,7,8,9},FALSE)} -> Gurugram Autoplex | AC25: 2007 | AD25: 10000 | AE25: 4 | AF25: S005 | AG25: =VLOOKUP($AF25,SalesPerson[],2,FALSE) -> Mohit Bose | AH25: =_xlfn.XLOOKUP(AG25,Salespersons!$B:$B,Salespersons!$G:$G,,0) -> 4 | AI25: =_xlfn.XLOOKUP(AG25,Salespersons!$B:$B,Salespersons!$I:$I,,0) -> True | AJ25: White | AK25: =AL25/W25 -> 0.036842105 | AL25: 35000 | AM25: =W25-AL25 -> 915000 | AN25: =AM25/100000 -> 9.15 | AO25: Loan/Finance | AP25: Tata Capital | AQ25: Online Website | AR25: Yes | AS25: No Feedback | AT25: No Feedback | AU25: No Feedback | AV25: No Feedback | AW25: No Feedback
A26: ORD00025 | B26: 45320 | C26: =TEXT(B26,"mmm") -> Jan | D26: =TEXT(B26,"yyyy") -> 2024 | E26: 45349 | F26: Delivered | G26: =IF(E26=0,"",E26-B26) -> 29 | H26: CU0396 | I26: =VLOOKUP($H26,Customers!$A$1:$I$721,2,FALSE) -> Kamal Khanna | J26: =VLOOKUP($H26,Customers!$A$1:$I$721,3,FALSE) -> Male | K26: =VLOOKUP($H26,Customers!$A$1:$I$721,4,FALSE) -> 24 | L26: =VLOOKUP($H26,Customers!$A$1:$I$721,5,FALSE) -> Delhi | M26: =VLOOKUP($H26,Customers!$A$1:$I$721,6,FALSE) -> Delhi | N26: =VLOOKUP($H26,Customers!$A$1:$I$721,7,FALSE) -> Salaried - Government | O26: =VLOOKUP($H26,Customers!$A$1:$I$721,8,FALSE) -> 600000 | P26: =VLOOKUP($H26,Customers!$A$1:$I$721,9,FALSE) -> Individual | Q26: C006 | R26: {=VLOOKUP($Q26,Cars[],{2,3,4,5,6,7,8,9},FALSE)} -> Maruti Suzuki | S26: Ertiga | T26: MPV | U26: CNG | V26: Manual | W26: 900000 | X26: 2022 | Y26: 3 | Z26: D001 | AA26: =VLOOKUP(Z26,Dealers[],5,FALSE) -> North | AB26: {=VLOOKUP($Z26,Dealers[],{2,7,8,9},FALSE)} -> Delhi Autoplex | AC26: 2013 | AD26: 4500 | AE26: 3.7 | AF26: S004 | AG26: =VLOOKUP($AF26,SalesPerson[],2,FALSE) -> Lokesh Nair | AH26: =_xlfn.XLOOKUP(AG26,Salespersons!$B:$B,Salespersons!$G:$G,,0) -> 8 | AI26: =_xlfn.XLOOKUP(AG26,Salespersons!$B:$B,Salespersons!$I:$I,,0) -> False | AJ26: Black | AK26: =AL26/W26 -> 0 | AL26: 0 | AM26: =W26-AL26 -> 900000 | AN26: =AM26/100000 -> 9 | AO26: Loan/Finance | AP26: SBI | AQ26: Walk-in | AR26: Yes | AS26: {=VLOOKUP($A26,Feedback[],{2,4,5,6,7},FALSE)} -> FB0018 | AT26: 5 | AU26: 9 | AV26: Dealer Visit | AW26: None
A27: ORD00026 | B27: 45321 | C27: =TEXT(B27,"mmm") -> Jan | D27: =TEXT(B27,"yyyy") -> 2024 | E27: 45354 | F27: Delivered | G27: =IF(E27=0,"",E27-B27) -> 33 | H27: CU0550 | I27: =VLOOKUP($H27,Customers!$A$1:$I$721,2,FALSE) -> Sachin Bose | J27: =VLOOKUP($H27,Customers!$A$1:$I$721,3,FALSE) -> Male | K27: =VLOOKUP($H27,Customers!$A$1:$I$721,4,FALSE) -> 31 | L27: =VLOOKUP($H27,Customers!$A$1:$I$721,5,FALSE) -> Jaipur | M27: =VLOOKUP($H27,Customers!$A$1:$I$721,6,FALSE) -> Rajasthan | N27: =VLOOKUP($H27,Customers!$A$1:$I$721,7,FALSE) -> Teacher | O27: =VLOOKUP($H27,Customers!$A$1:$I$721,8,FALSE) -> 500000 | P27: =VLOOKUP($H27,Customers!$A$1:$I$721,9,FALSE) -> Individual | Q27: C009 | R27: {=VLOOKUP($Q27,Cars[],{2,3,4,5,6,7,8,9},FALSE)} -> Hyundai | S27: i20 | T27: Hatchback | U27: Petrol | V27: Automatic | W27: 780000 | X27: 2023 | Y27: 2 | Z27: D006 | AA27: =VLOOKUP(Z27,Dealers[],5,FALSE) -> North | AB27: {=VLOOKUP($Z27,Dealers[],{2,7,8,9},FALSE)} -> Jaipur Wheels | AC27: 2015 | AD27: 3000 | AE27: 3.5 | AF27: S017 | AG27: =VLOOKUP($AF27,SalesPerson[],2,FALSE) -> Mohit Yadav | AH27: =_xlfn.XLOOKUP(AG27,Salespersons!$B:$B,Salespersons!$G:$G,,0) -> 8 | AI27: =_xlfn.XLOOKUP(AG27,Salespersons!$B:$B,Salespersons!$I:$I,,0) -> True | AJ27: White | AK27: =AL27/W27 -> 0 | AL27: 0 | AM27: =W27-AL27 -> 780000 | AN27: =AM27/100000 -> 7.8 | AO27: Loan/Finance | AP27: Axis Bank | AQ27: Test Drive Campaign | AR27: No | AS27: No Feedback | AT27: No Feedback | AU27: No Feedback | AV27: No Feedback | AW27: No Feedback
A28: ORD00027 | B28: 45321 | C28: =TEXT(B28,"mmm") -> Jan | D28: =TEXT(B28,"yyyy") -> 2024 | E28: 45349 | F28: Delivered | G28: =IF(E28=0,"",E28-B28) -> 28 | H28: CU0602 | I28: =VLOOKUP($H28,Customers!$A$1:$I$721,2,FALSE) -> Siddharth Khanna | J28: =VLOOKUP($H28,Customers!$A$1:$I$721,3,FALSE) -> Male | K28: =VLOOKUP($H28,Customers!$A$1:$I$721,4,FALSE) -> 30 | L28: =VLOOKUP($H28,Customers!$A$1:$I$721,5,FALSE) -> Hyderabad | M28: =VLOOKUP($H28,Customers!$A$1:$I$721,6,FALSE) -> Telangana | N28: =VLOOKUP($H28,Customers!$A$1:$I$721,7,FALSE) -> Salaried - Private | O28: =VLOOKUP($H28,Customers!$A$1:$I$721,8,FALSE) -> 550000 | P28: =VLOOKUP($H28,Customers!$A$1:$I$721,9,FALSE) -> Individual | Q28: C004 | R28: {=VLOOKUP($Q28,Cars[],{2,3,4,5,6,7,8,9},FALSE)} -> Maruti Suzuki | S28: Dzire | T28: Sedan | U28: Petrol | V28: Manual | W28: 690000 | X28: 2024 | Y28: 3 | Z28: D018 | AA28: =VLOOKUP(Z28,Dealers[],5,FALSE) -> South | AB28: {=VLOOKUP($Z28,Dealers[],{2,7,8,9},FALSE)} -> Hyderabad Automobiles | AC28: 2019 | AD28: 4500 | AE28: 3.8 | AF28: S054 | AG28: =VLOOKUP($AF28,SalesPerson[],2,FALSE) -> Gaurav Shah | AH28: =_xlfn.XLOOKUP(AG28,Salespersons!$B:$B,Salespersons!$G:$G,,0) -> 4 | AI28: =_xlfn.XLOOKUP(AG28,Salespersons!$B:$B,Salespersons!$I:$I,,0) -> True | AJ28: Silver | AK28: =AL28/W28 -> 0 | AL28: 0 | AM28: =W28-AL28 -> 690000 | AN28: =AM28/100000 -> 6.9 | AO28: Cash | AP28: N/A | AQ28: Online Website | AR28: No | AS28: No Feedback | AT28: No Feedback | AU28: No Feedback | AV28: No Feedback | AW28: No Feedback
A29: ORD00028 | B29: 45322 | C29: =TEXT(B29,"mmm") -> Jan | D29: =TEXT(B29,"yyyy") -> 2024 | E29: 45354 | F29: Delivered | G29: =IF(E29=0,"",E29-B29) -> 32 | H29: CU0337 | I29: =VLOOKUP($H29,Customers!$A$1:$I$721,2,FALSE) -> Mohit Bose | J29: =VLOOKUP($H29,Customers!$A$1:$I$721,3,FALSE) -> Male | K29: =VLOOKUP($H29,Customers!$A$1:$I$721,4,FALSE) -> 47 | L29: =VLOOKUP($H29,Customers!$A$1:$I$721,5,FALSE) -> Gurugram | M29: =VLOOKUP($H29,Customers!$A$1:$I$721,6,FALSE) -> Haryana | N29: =VLOOKUP($H29,Customers!$A$1:$I$721,7,FALSE) -> Retired | O29: =VLOOKUP($H29,Customers!$A$1:$I$721,8,FALSE) -> 350000 | P29: =VLOOKUP($H29,Customers!$A$1:$I$721,9,FALSE) -> Individual | Q29: C029 | R29: {=VLOOKUP($Q29,Cars[],{2,3,4,5,6,7,8,9},FALSE)} -> Honda | S29: Amaze | T29: Sedan | U29: Petrol | V29: Manual | W29: 800000 | X29: 2024 | Y29: 3 | Z29: D015 | AA29: =VLOOKUP(Z29,Dealers[],5,FALSE) -> South | AB29: {=VLOOKUP($Z29,Dealers[],{2,7,8,9},FALSE)} -> Mysuru Auto Hub | AC29: 2006 | AD29: 4500 | AE29: 4.6 | AF29: S046 | AG29: =VLOOKUP($AF29,SalesPerson[],2,FALSE) -> Tanvi Reddy | AH29: =_xlfn.XLOOKUP(AG29,Salespersons!$B:$B,Salespersons!$G:$G,,0) -> 4 | AI29: =_xlfn.XLOOKUP(AG29,Salespersons!$B:$B,Salespersons!$I:$I,,0) -> True | AJ29: Black | AK29: =AL29/W29 -> 0.02375 | AL29: 19000 | AM29: =W29-AL29 -> 781000 | AN29: =AM29/100000 -> 7.81 | AO29: Loan/Finance | AP29: ICICI Bank | AQ29: Auto Expo/Event | AR29: No | AS29: {=VLOOKUP($A29,Feedback[],{2,4,5,6,7},FALSE)} -> FB0019 | AT29: 5 | AU29: 10 | AV29: Email | AW29: None
A30: ORD00029 | B30: 45325 | C30: =TEXT(B30,"mmm") -> Feb | D30: =TEXT(B30,"yyyy") -> 2024 | E30: 45357 | F30: Delivered | G30: =IF(E30=0,"",E30-B30) -> 32 | H30: CU0305 | I30: =VLOOKUP($H30,Customers!$A$1:$I$721,2,FALSE) -> Sneha Mishra | J30: =VLOOKUP($H30,Customers!$A$1:$I$721,3,FALSE) -> Female | K30: =VLOOKUP($H30,Customers!$A$1:$I$721,4,FALSE) -> 40 | L30: =VLOOKUP($H30,Customers!$A$1:$I$721,5,FALSE) -> Bengaluru | M30: =VLOOKUP($H30,Customers!$A$1:$I$721,6,FALSE) -> Karnataka | N30: =VLOOKUP($H30,Customers!$A$1:$I$721,7,FALSE) -> Salaried - Private | O30: =VLOOKUP($H30,Customers!$A$1:$I$721,8,FALSE) -> 760000 | P30: =VLOOKUP($H30,Customers!$A$1:$I$721,9,FALSE) -> Individual | Q30: C009 | R30: {=VLOOKUP($Q30,Cars[],{2,3,4,5,6,7,8,9},FALSE)} -> Hyundai | S30: i20 | T30: Hatchback | U30: Petrol | V30: Automatic | W30: 780000 | X30: 2023 | Y30: 2 | Z30: D014 | AA30: =VLOOKUP(Z30,Dealers[],5,FALSE) -> South | AB30: {=VLOOKUP($Z30,Dealers[],{2,7,8,9},FALSE)} -> Bengaluru Auto Hub | AC30: 2013 | AD30: 12000 | AE30: 4.4 | AF30: S043 | AG30: =VLOOKUP($AF30,SalesPerson[],2,FALSE) -> Yash Singh | AH30: =_xlfn.XLOOKUP(AG30,Salespersons!$B:$B,Salespersons!$G:$G,,0) -> 4 | AI30: =_xlfn.XLOOKUP(AG30,Salespersons!$B:$B,Salespersons!$I:$I,,0) -> True | AJ30: Black | AK30: =AL30/W30 -> 0 | AL30: 0 | AM30: =W30-AL30 -> 780000 | AN30: =AM30/100000 -> 7.8 | AO30: Cash | AP30: N/A | AQ30: Corporate Tie-up | AR30: Yes | AS30: No Feedback | AT30: No Feedback | AU30: No Feedback | AV30: No Feedback | AW30: No Feedback
A31: ORD00030 | B31: 45326 | C31: =TEXT(B31,"mmm") -> Feb | D31: =TEXT(B31,"yyyy") -> 2024 | E31: 45333 | F31: Delivered | G31: =IF(E31=0,"",E31-B31) -> 7 | H31: CU0716 | I31: =VLOOKUP($H31,Customers!$A$1:$I$721,2,FALSE) -> Anjali Rao | J31: =VLOOKUP($H31,Customers!$A$1:$I$721,3,FALSE) -> Female | K31: =VLOOKUP($H31,Customers!$A$1:$I$721,4,FALSE) -> 56 | L31: =VLOOKUP($H31,Customers!$A$1:$I$721,5,FALSE) -> Lucknow | M31: =VLOOKUP($H31,Customers!$A$1:$I$721,6,FALSE) -> Uttar Pradesh | N31: =VLOOKUP($H31,Customers!$A$1:$I$721,7,FALSE) -> Engineer | O31: =VLOOKUP($H31,Customers!$A$1:$I$721,8,FALSE) -> 1140000 | P31: =VLOOKUP($H31,Customers!$A$1:$I$721,9,FALSE) -> Individual | Q31: C015 | R31: {=VLOOKUP($Q31,Cars[],{2,3,4,5,6,7,8,9},FALSE)} -> Tata | S31: Punch | T31: SUV | U31: Petrol | V31: Manual | W31: 650000 | X31: 2021 | Y31: 3 | Z31: D007 | AA31: =VLOOKUP(Z31,Dealers[],5,FALSE) -> North | AB31: {=VLOOKUP($Z31,Dealers[],{2,7,8,9},FALSE)} -> Lucknow Motors | AC31: 2013 | AD31: 3000 | AE31: 4.4 | AF31: S020 | AG31: =VLOOKUP($AF31,SalesPerson[],2,FALSE) -> Tarun Patel | AH31: =_xlfn.XLOOKUP(AG31,Salespersons!$B:$B,Salespersons!$G:$G,,0) -> 4 | AI31: =_xlfn.XLOOKUP(AG31,Salespersons!$B:$B,Salespersons!$I:$I,,0) -> True | AJ31: Grey | AK31: =AL31/W31 -> 0.041538462 | AL31: 27000 | AM31: =W31-AL31 -> 623000 | AN31: =AM31/100000 -> 6.23 | AO31: Cash | AP31: N/A | AQ31: Corporate Tie-up | AR31: Yes | AS31: {=VLOOKUP($A31,Feedback[],{2,4,5,6,7},FALSE)} -> FB0020 | AT31: 4 | AU31: 8 | AV31: Dealer Visit | AW31: None
A32: ORD00031 | B32: 45326 | C32: =TEXT(B32,"mmm") -> Feb | D32: =TEXT(B32,"yyyy") -> 2024 | E32: 45349 | F32: Delivered | G32: =IF(E32=0,"",E32-B32) -> 23 | H32: CU0506 | I32: =VLOOKUP($H32,Customers!$A$1:$I$721,2,FALSE) -> Sandeep Verma | J32: =VLOOKUP($H32,Customers!$A$1:$I$721,3,FALSE) -> Male | K32: =VLOOKUP($H32,Customers!$A$1:$I$721,4,FALSE) -> 54 | L32: =VLOOKUP($H32,Customers!$A$1:$I$721,5,FALSE) -> Pune | M32: =VLOOKUP($H32,Customers!$A$1:$I$721,6,FALSE) -> Maharashtra | N32: =VLOOKUP($H32,Customers!$A$1:$I$721,7,FALSE) -> Business Owner | O32: =VLOOKUP($H32,Customers!$A$1:$I$721,8,FALSE) -> 1830000 | P32: =VLOOKUP($H32,Customers!$A$1:$I$721,9,FALSE) -> Individual | Q32: C010 | R32: {=VLOOKUP($Q32,Cars[],{2,3,4,5,6,7,8,9},FALSE)} -> Hyundai | S32: Venue | T32: SUV | U32: Petrol | V32: Manual | W32: 800000 | X32: 2022 | Y32: 3 | Z32: D009 | AA32: =VLOOKUP(Z32,Dealers[],5,FALSE) -> West | AB32: {=VLOOKUP($Z32,Dealers[],{2,7,8,9},FALSE)} -> Mumbai Autoplex | AC32: 2011 | AD32: 12000 | AE32: 3.5 | AF32: S028 | AG32: =VLOOKUP($AF32,SalesPerson[],2,FALSE) -> Ankit Rao | AH32: =_xlfn.XLOOKUP(AG32,Salespersons!$B:$B,Salespersons!$G:$G,,0) -> 7 | AI32: =_xlfn.XLOOKUP(AG32,Salespersons!$B:$B,Salespersons!$I:$I,,0) -> True | AJ32: Black | AK32: =AL32/W32 -> 0 | AL32: 0 | AM32: =W32-AL32 -> 800000 | AN32: =AM32/100000 -> 8 | AO32: Cash | AP32: N/A | AQ32: Online Website | AR32: No | AS32: {=VLOOKUP($A32,Feedback[],{2,4,5,6,7},FALSE)} -> FB0021 | AT32: 4 | AU32: 10 | AV32: Dealer Visit | AW32: None
A33: ORD00032 | B33: 45327 | C33: =TEXT(B33,"mmm") -> Feb | D33: =TEXT(B33,"yyyy") -> 2024 | E33: 45355 | F33: Delivered | G33: =IF(E33=0,"",E33-B33) -> 28 | H33: CU0213 | I33: =VLOOKUP($H33,Customers!$A$1:$I$721,2,FALSE) -> Nisha Sharma | J33: =VLOOKUP($H33,Customers!$A$1:$I$721,3,FALSE) -> Female | K33: =VLOOKUP($H33,Customers!$A$1:$I$721,4,FALSE) -> 21 | L33: =VLOOKUP($H33,Customers!$A$1:$I$721,5,FALSE) -> Bhopal | M33: =VLOOKUP($H33,Customers!$A$1:$I$721,6,FALSE) -> Madhya Pradesh | N33: =VLOOKUP($H33,Customers!$A$1:$I$721,7,FALSE) -> Business Owner | O33: =VLOOKUP($H33,Customers!$A$1:$I$721,8,FALSE) -> 1760000 | P33: =VLOOKUP($H33,Customers!$A$1:$I$721,9,FALSE) -> Individual | Q33: C013 | R33: {=VLOOKUP($Q33,Cars[],{2,3,4,5,6,7,8,9},FALSE)} -> Hyundai | S33: Alcazar | T33: SUV | U33: Diesel | V33: Automatic | W33: 1700000 | X33: 2024 | Y33: 2 | Z33: D024 | AA33: =VLOOKUP(Z33,Dealers[],5,FALSE) -> Central | AB33: {=VLOOKUP($Z33,Dealers[],{2,7,8,9},FALSE)} -> Bhopal Autoplex | AC33: 2013 | AD33: 12000 | AE33: 3.9 | AF33: S073 | AG33: =VLOOKUP($AF33,SalesPerson[],2,FALSE) -> Sneha Iyer | AH33: =_xlfn.XLOOKUP(AG33,Salespersons!$B:$B,Salespersons!$G:$G,,0) -> 4 | AI33: =_xlfn.XLOOKUP(AG33,Salespersons!$B:$B,Salespersons!$I:$I,,0) -> True | AJ33: Red | AK33: =AL33/W33 -> 0.037647059 | AL33: 64000 | AM33: =W33-AL33 -> 1636000 | AN33: =AM33/100000 -> 16.36 | AO33: Exchange + Loan | AP33: Axis Bank | AQ33: Social Media | AR33: Yes | AS33: {=VLOOKUP($A33,Feedback[],{2,4,5,6,7},FALSE)} -> FB0022 | AT33: 5 | AU33: 9 | AV33: Online Survey | AW33: None
A34: ORD00033 | B34: 45327 | C34: =TEXT(B34,"mmm") -> Feb | D34: =TEXT(B34,"yyyy") -> 2024 | E34: 45345 | F34: Delivered | G34: =IF(E34=0,"",E34-B34) -> 18 | H34: CU0011 | I34: =VLOOKUP($H34,Customers!$A$1:$I$721,2,FALSE) -> Jatin Sharma | J34: =VLOOKUP($H34,Customers!$A$1:$I$721,3,FALSE) -> Male | K34: =VLOOKUP($H34,Customers!$A$1:$I$721,4,FALSE) -> 29 | L34: =VLOOKUP($H34,Customers!$A$1:$I$721,5,FALSE) -> Guwahati | M34: =VLOOKUP($H34,Customers!$A$1:$I$721,6,FALSE) -> Assam | N34: =VLOOKUP($H34,Customers!$A$1:$I$721,7,FALSE) -> Retired | O34: =VLOOKUP($H34,Customers!$A$1:$I$721,8,FALSE) -> 660000 | P34: =VLOOKUP($H34,Customers!$A$1:$I$721,9,FALSE) -> Individual | Q34: C005 | R34: {=VLOOKUP($Q34,Cars[],{2,3,4,5,6,7,8,9},FALSE)} -> Maruti Suzuki | S34: Brezza | T34: SUV | U34: Petrol | V34: Automatic | W34: 900000 | X34: 2022 | Y34: 3 | Z34: D023 | AA34: =VLOOKUP(Z34,Dealers[],5,FALSE) -> East | AB34: {=VLOOKUP($Z34,Dealers[],{2,7,8,9},FALSE)} -> Guwahati Automobiles | AC34: 2005 | AD34: 12000 | AE34: 4.4 | AF34: S070 | AG34: =VLOOKUP($AF34,SalesPerson[],2,FALSE) -> Tarun Mehta | AH34: =_xlfn.XLOOKUP(AG34,Salespersons!$B:$B,Salespersons!$G:$G,,0) -> 4 | AI34: =_xlfn.XLOOKUP(AG34,Salespersons!$B:$B,Salespersons!$I:$I,,0) -> True | AJ34: Grey | AK34: =AL34/W34 -> 0.037777778 | AL34: 34000 | AM34: =W34-AL34 -> 866000 | AN34: =AM34/100000 -> 8.66 | AO34: Exchange + Loan | AP34: Axis Bank | AQ34: Social Media | AR34: Yes | AS34: No Feedback | AT34: No Feedback | AU34: No Feedback | AV34: No Feedback | AW34: No Feedback
A35: ORD00034 | B35: 45327 | C35: =TEXT(B35,"mmm") -> Feb | D35: =TEXT(B35,"yyyy") -> 2024 | E35: 45355 | F35: Delivered | G35: =IF(E35=0,"",E35-B35) -> 28 | H35: CU0483 | I35: =VLOOKUP($H35,Customers!$A$1:$I$721,2,FALSE) -> Ritu Reddy | J35: =VLOOKUP($H35,Customers!$A$1:$I$721,3,FALSE) -> Female | K35: =VLOOKUP($H35,Customers!$A$1:$I$721,4,FALSE) -> 50 | L35: =VLOOKUP($H35,Customers!$A$1:$I$721,5,FALSE) -> Chennai | M35: =VLOOKUP($H35,Customers!$A$1:$I$721,6,FALSE) -> Tamil Nadu | N35: =VLOOKUP($H35,Customers!$A$1:$I$721,7,FALSE) -> Farmer | O35: =VLOOKUP($H35,Customers!$A$1:$I$721,8,FALSE) -> 850000 | P35: =VLOOKUP($H35,Customers!$A$1:$I$721,9,FALSE) -> Individual | Q35: C028 | R35: {=VLOOKUP($Q35,Cars[],{2,3,4,5,6,7,8,9},FALSE)} -> Honda | S35: City | T35: Sedan | U35: Petrol | V35: Automatic | W35: 1250000 | X35: 2023 | Y35: 4 | Z35: D016 | AA35: =VLOOKUP(Z35,Dealers[],5,FALSE) -> South | AB35: {=VLOOKUP($Z35,Dealers[],{2,7,8,9},FALSE)} -> Chennai Wheels | AC35: 2007 | AD35: 4500 | AE35: 4.7 | AF35: S048 | AG35: =VLOOKUP($AF35,SalesPerson[],2,FALSE) -> Kunal Pillai | AH35: =_xlfn.XLOOKUP(AG35,Salespersons!$B:$B,Salespersons!$G:$G,,0) -> 5 | AI35: =_xlfn.XLOOKUP(AG35,Salespersons!$B:$B,Salespersons!$I:$I,,0) -> True | AJ35: White | AK35: =AL35/W35 -> 0.0248 | AL35: 31000 | AM35: =W35-AL35 -> 1219000 | AN35: =AM35/100000 -> 12.19 | AO35: Loan/Finance | AP35: HDFC Bank | AQ35: Corporate Tie-up | AR35: Yes | AS35: {=VLOOKUP($A35,Feedback[],{2,4,5,6,7},FALSE)} -> FB0023 | AT35: 3 | AU35: 5 | AV35: Dealer Visit | AW35: None
A36: ORD00035 | B36: 45332 | C36: =TEXT(B36,"mmm") -> Feb | D36: =TEXT(B36,"yyyy") -> 2024 | E36: 45338 | F36: Delivered | G36: =IF(E36=0,"",E36-B36) -> 6 | H36: CU0694 | I36: =VLOOKUP($H36,Customers!$A$1:$I$721,2,FALSE) -> Ashok Gupta | J36: =VLOOKUP($H36,Customers!$A$1:$I$721,3,FALSE) -> Male | K36: =VLOOKUP($H36,Customers!$A$1:$I$721,4,FALSE) -> 35 | L36: =VLOOKUP($H36,Customers!$A$1:$I$721,5,FALSE) -> Noida | M36: =VLOOKUP($H36,Customers!$A$1:$I$721,6,FALSE) -> Uttar Pradesh | N36: =VLOOKUP($H36,Customers!$A$1:$I$721,7,FALSE) -> Engineer | O36: =VLOOKUP($H36,Customers!$A$1:$I$721,8,FALSE) -> 1850000 | P36: =VLOOKUP($H36,Customers!$A$1:$I$721,9,FALSE) -> Individual | Q36: C006 | R36: {=VLOOKUP($Q36,Cars[],{2,3,4,5,6,7,8,9},FALSE)} -> Maruti Suzuki | S36: Ertiga | T36: MPV | U36: CNG | V36: Manual | W36: 900000 | X36: 2022 | Y36: 3 | Z36: D007 | AA36: =VLOOKUP(Z36,Dealers[],5,FALSE) -> North | AB36: {=VLOOKUP($Z36,Dealers[],{2,7,8,9},FALSE)} -> Lucknow Motors | AC36: 2013 | AD36: 3000 | AE36: 4.4 | AF36: S020 | AG36: =VLOOKUP($AF36,SalesPerson[],2,FALSE) -> Tarun Patel | AH36: =_xlfn.XLOOKUP(AG36,Salespersons!$B:$B,Salespersons!$G:$G,,0) -> 4 | AI36: =_xlfn.XLOOKUP(AG36,Salespersons!$B:$B,Salespersons!$I:$I,,0) -> True | AJ36: Red | AK36: =AL36/W36 -> 0.032222222 | AL36: 29000 | AM36: =W36-AL36 -> 871000 | AN36: =AM36/100000 -> 8.71 | AO36: Cash | AP36: N/A | AQ36: Auto Expo/Event | AR36: No | AS36: No Feedback | AT36: No Feedback | AU36: No Feedback | AV36: No Feedback | AW36: No Feedback
A37: ORD00036 | B37: 45335 | C37: =TEXT(B37,"mmm") -> Feb | D37: =TEXT(B37,"yyyy") -> 2024 | E37: 45362 | F37: Delivered | G37: =IF(E37=0,"",E37-B37) -> 27 | H37: CU0657 | I37: =VLOOKUP($H37,Customers!$A$1:$I$721,2,FALSE) -> Suresh Agarwal | J37: =VLOOKUP($H37,Customers!$A$1:$I$721,3,FALSE) -> Male | K37: =VLOOKUP($H37,Customers!$A$1:$I$721,4,FALSE) -> 28 | L37: =VLOOKUP($H37,Customers!$A$1:$I$721,5,FALSE) -> Ludhiana | M37: =VLOOKUP($H37,Customers!$A$1:$I$721,6,FALSE) -> Punjab | N37: =VLOOKUP($H37,Customers!$A$1:$I$721,7,FALSE) -> Salaried - Private | O37: =VLOOKUP($H37,Customers!$A$1:$I$721,8,FALSE) -> 1370000 | P37: =VLOOKUP($H37,Customers!$A$1:$I$721,9,FALSE) -> Individual | Q37: C018 | R37: {=VLOOKUP($Q37,Cars[],{2,3,4,5,6,7,8,9},FALSE)} -> Tata | S37: Nexon EV | T37: SUV | U37: Electric | V37: Automatic | W37: 1450000 | X37: 2023 | Y37: 3 | Z37: D005 | AA37: =VLOOKUP(Z37,Dealers[],5,FALSE) -> North | AB37: {=VLOOKUP($Z37,Dealers[],{2,7,8,9},FALSE)} -> Ludhiana Wheels | AC37: 2010 | AD37: 12000 | AE37: 4 | AF37: S015 | AG37: =VLOOKUP($AF37,SalesPerson[],2,FALSE) -> Akash Verma | AH37: =_xlfn.XLOOKUP(AG37,Salespersons!$B:$B,Salespersons!$G:$G,,0) -> 8 | AI37: =_xlfn.XLOOKUP(AG37,Salespersons!$B:$B,Salespersons!$I:$I,,0) -> True | AJ37: Grey | AK37: =AL37/W37 -> 0.034482759 | AL37: 50000 | AM37: =W37-AL37 -> 1400000 | AN37: =AM37/100000 -> 14 | AO37: Loan/Finance | AP37: Bajaj Finserv | AQ37: Online Website | AR37: No | AS37: No Feedback | AT37: No Feedback | AU37: No Feedback | AV37: No Feedback | AW37: No Feedback
A38: ORD00037 | B38: 45338 | C38: =TEXT(B38,"mmm") -> Feb | D38: =TEXT(B38,"yyyy") -> 2024 | F38: Cancelled | G38: =IF(E38=0,"",E38-B38) | H38: CU0245 | I38: =VLOOKUP($H38,Customers!$A$1:$I$721,2,FALSE) -> Shweta Nair | J38: =VLOOKUP($H38,Customers!$A$1:$I$721,3,FALSE) -> Female | K38: =VLOOKUP($H38,Customers!$A$1:$I$721,4,FALSE) -> 57 | L38: =VLOOKUP($H38,Customers!$A$1:$I$721,5,FALSE) -> Guwahati | M38: =VLOOKUP($H38,Customers!$A$1:$I$721,6,FALSE) -> Assam | N38: =VLOOKUP($H38,Customers!$A$1:$I$721,7,FALSE) -> Salaried - Government | O38: =VLOOKUP($H38,Customers!$A$1:$I$721,8,FALSE) -> 1390000 | P38: =VLOOKUP($H38,Customers!$A$1:$I$721,9,FALSE) -> Individual | Q38: C004 | R38: {=VLOOKUP($Q38,Cars[],{2,3,4,5,6,7,8,9},FALSE)} -> Maruti Suzuki | S38: Dzire | T38: Sedan | U38: Petrol | V38: Manual | W38: 690000 | X38: 2024 | Y38: 3 | Z38: D023 | AA38: =VLOOKUP(Z38,Dealers[],5,FALSE) -> East | AB38: {=VLOOKUP($Z38,Dealers[],{2,7,8,9},FALSE)} -> Guwahati Automobiles | AC38: 2005 | AD38: 12000 | AE38: 4.4 | AF38: S069 | AG38: =VLOOKUP($AF38,SalesPerson[],2,FALSE) -> Varun Yadav | AH38: =_xlfn.XLOOKUP(AG38,Salespersons!$B:$B,Salespersons!$G:$G,,0) -> 6 | AI38: =_xlfn.XLOOKUP(AG38,Salespersons!$B:$B,Salespersons!$I:$I,,0) -> True | AJ38: White | AK38: =AL38/W38 -> 0.010144928 | AL38: 7000 | AM38: =W38-AL38 -> 683000 | AN38: =AM38/100000 -> 6.83 | AO38: Loan/Finance | AP38: SBI | AQ38: Auto Expo/Event | AR38: No | AS38: No Feedback | AT38: No Feedback | AU38: No Feedback | AV38: No Feedback | AW38: No Feedback
A39: ORD00038 | B39: 45338 | C39: =TEXT(B39,"mmm") -> Feb | D39: =TEXT(B39,"yyyy") -> 2024 | E39: 45354 | F39: Delivered | G39: =IF(E39=0,"",E39-B39) -> 16 | H39: CU0681 | I39: =VLOOKUP($H39,Customers!$A$1:$I$721,2,FALSE) -> Pradeep Mishra | J39: =VLOOKUP($H39,Customers!$A$1:$I$721,3,FALSE) -> Male | K39: =VLOOKUP($H39,Customers!$A$1:$I$721,4,FALSE) -> 38 | L39: =VLOOKUP($H39,Customers!$A$1:$I$721,5,FALSE) -> Coimbatore | M39: =VLOOKUP($H39,Customers!$A$1:$I$721,6,FALSE) -> Tamil Nadu | N39: =VLOOKUP($H39,Customers!$A$1:$I$721,7,FALSE) -> Doctor | O39: =VLOOKUP($H39,Customers!$A$1:$I$721,8,FALSE) -> 1400000 | P39: =VLOOKUP($H39,Customers!$A$1:$I$721,9,FALSE) -> Individual | Q39: C004 | R39: {=VLOOKUP($Q39,Cars[],{2,3,4,5,6,7,8,9},FALSE)} -> Maruti Suzuki | S39: Dzire | T39: Sedan | U39: Petrol | V39: Manual | W39: 690000 | X39: 2024 | Y39: 3 | Z39: D017 | AA39: =VLOOKUP(Z39,Dealers[],5,FALSE) -> South | AB39: {=VLOOKUP($Z39,Dealers[],{2,7,8,9},FALSE)} -> Coimbatore Car World | AC39: 2015 | AD39: 4500 | AE39: 4.3 | AF39: S051 | AG39: =VLOOKUP($AF39,SalesPerson[],2,FALSE) -> Arjun Verma | AH39: =_xlfn.XLOOKUP(AG39,Salespersons!$B:$B,Salespersons!$G:$G,,0) -> 4 | AI39: =_xlfn.XLOOKUP(AG39,Salespersons!$B:$B,Salespersons!$I:$I,,0) -> True | AJ39: Blue | AK39: =AL39/W39 -> 0.043478261 | AL39: 30000 | AM39: =W39-AL39 -> 660000 | AN39: =AM39/100000 -> 6.6 | AO39: Cash | AP39: N/A | AQ39: Social Media | AR39: No | AS39: No Feedback | AT39: No Feedback | AU39: No Feedback | AV39: No Feedback | AW39: No Feedback
A40: ORD00039 | B40: 45338 | C40: =TEXT(B40,"mmm") -> Feb | D40: =TEXT(B40,"yyyy") -> 2024 | E40: 45370 | F40: Delivered | G40: =IF(E40=0,"",E40-B40) -> 32 | H40: CU0124 | I40: =VLOOKUP($H40,Customers!$A$1:$I$721,2,FALSE) -> Gaurav Singh | J40: =VLOOKUP($H40,Customers!$A$1:$I$721,3,FALSE) -> Male | K40: =VLOOKUP($H40,Customers!$A$1:$I$721,4,FALSE) -> 35 | L40: =VLOOKUP($H40,Customers!$A$1:$I$721,5,FALSE) -> Pune | M40: =VLOOKUP($H40,Customers!$A$1:$I$721,6,FALSE) -> Maharashtra | N40: =VLOOKUP($H40,Customers!$A$1:$I$721,7,FALSE) -> Salaried - Government | O40: =VLOOKUP($H40,Customers!$A$1:$I$721,8,FALSE) -> 1230000 | P40: =VLOOKUP($H40,Customers!$A$1:$I$721,9,FALSE) -> Individual | Q40: C005 | R40: {=VLOOKUP($Q40,Cars[],{2,3,4,5,6,7,8,9},FALSE)} -> Maruti Suzuki | S40: Brezza | T40: SUV | U40: Petrol | V40: Automatic | W40: 900000 | X40: 2022 | Y40: 3 | Z40: D010 | AA40: =VLOOKUP(Z40,Dealers[],5,FALSE) -> West | AB40: {=VLOOKUP($Z40,Dealers[],{2,7,8,9},FALSE)} -> Pune Autoplex | AC40: 2014 | AD40: 3000 | AE40: 4.6 | AF40: S031 | AG40: =VLOOKUP($AF40,SalesPerson[],2,FALSE) -> Ankit Verma | AH40: =_xlfn.XLOOKUP(AG40,Salespersons!$B:$B,Salespersons!$G:$G,,0) -> 4 | AI40: =_xlfn.XLOOKUP(AG40,Salespersons!$B:$B,Salespersons!$I:$I,,0) -> True | AJ40: White | AK40: =AL40/W40 -> 0 | AL40: 0 | AM40: =W40-AL40 -> 900000 | AN40: =AM40/100000 -> 9 | AO40: Loan/Finance | AP40: HDFC Bank | AQ40: Corporate Tie-up | AR40: No | AS40: No Feedback | AT40: No Feedback | AU40: No Feedback | AV40: No Feedback | AW40: No Feedback
A41: ORD00040 | B41: 45343 | C41: =TEXT(B41,"mmm") -> Feb | D41: =TEXT(B41,"yyyy") -> 2024 | E41: 45356 | F41: Delivered | G41: =IF(E41=0,"",E41-B41) -> 13 | H41: CU0666 | I41: =VLOOKUP($H41,Customers!$A$1:$I$721,2,FALSE) -> Divya Reddy | J41: =VLOOKUP($H41,Customers!$A$1:$I$721,3,FALSE) -> Female | K41: =VLOOKUP($H41,Customers!$A$1:$I$721,4,FALSE) -> 62 | L41: =VLOOKUP($H41,Customers!$A$1:$I$721,5,FALSE) -> Bhopal | M41: =VLOOKUP($H41,Customers!$A$1:$I$721,6,FALSE) -> Madhya Pradesh | N41: =VLOOKUP($H41,Customers!$A$1:$I$721,7,FALSE) -> Retired | O41: =VLOOKUP($H41,Customers!$A$1:$I$721,8,FALSE) -> 580000 | P41: =VLOOKUP($H41,Customers!$A$1:$I$721,9,FALSE) -> Individual | Q41: C016 | R41: {=VLOOKUP($Q41,Cars[],{2,3,4,5,6,7,8,9},FALSE)} -> Tata | S41: Nexon | T41: SUV | U41: Diesel | V41: Manual | W41: 950000 | X41: 2023 | Y41: 3 | Z41: D024 | AA41: =VLOOKUP(Z41,Dealers[],5,FALSE) -> Central | AB41: {=VLOOKUP($Z41,Dealers[],{2,7,8,9},FALSE)} -> Bhopal Autoplex | AC41: 2013 | AD41: 12000 | AE41: 3.9 | AF41: S072 | AG41: =VLOOKUP($AF41,SalesPerson[],2,FALSE) -> Priya Saini | AH41: =_xlfn.XLOOKUP(AG41,Salespersons!$B:$B,Salespersons!$G:$G,,0) -> 4 | AI41: =_xlfn.XLOOKUP(AG41,Salespersons!$B:$B,Salespersons!$I:$I,,0) -> True | AJ41: White | AK41: =AL41/W41 -> 0.0094736842 | AL41: 9000 | AM41: =W41-AL41 -> 941000 | AN41: =AM41/100000 -> 9.41 | AO41: Exchange + Loan | AP41: HDFC Bank | AQ41: Walk-in | AR41: No | AS41: {=VLOOKUP($A41,Feedback[],{2,4,5,6,7},FALSE)} -> FB0024 | AT41: 4 | AU41: 9 | AV41: Dealer Visit | AW41: None
A42: ORD00041 | B42: 45344 | C42: =TEXT(B42,"mmm") -> Feb | D42: =TEXT(B42,"yyyy") -> 2024 | E42: 45351 | F42: Delivered | G42: =IF(E42=0,"",E42-B42) -> 7 | H42: CU0333 | I42: =VLOOKUP($H42,Customers!$A$1:$I$721,2,FALSE) -> Faisal Mehta | J42: =VLOOKUP($H42,Customers!$A$1:$I$721,3,FALSE) -> Male | K42: =VLOOKUP($H42,Customers!$A$1:$I$721,4,FALSE) -> 23 | L42: =VLOOKUP($H42,Customers!$A$1:$I$721,5,FALSE) -> Bengaluru | M42: =VLOOKUP($H42,Customers!$A$1:$I$721,6,FALSE) -> Karnataka | N42: =VLOOKUP($H42,Customers!$A$1:$I$721,7,FALSE) -> Business Owner | O42: =VLOOKUP($H42,Customers!$A$1:$I$721,8,FALSE) -> 3410000 | P42: =VLOOKUP($H42,Customers!$A$1:$I$721,9,FALSE) -> Individual | Q42: C037 | R42: {=VLOOKUP($Q42,Cars[],{2,3,4,5,6,7,8,9},FALSE)} -> Renault | S42: Kiger | T42: SUV | U42: Petrol | V42: Manual | W42: 700000 | X42: 2021 | Y42: 4 | Z42: D014 | AA42: =VLOOKUP(Z42,Dealers[],5,FALSE) -> South | AB42: {=VLOOKUP($Z42,Dealers[],{2,7,8,9},FALSE)} -> Bengaluru Auto Hub | AC42: 2013 | AD42: 12000 | AE42: 4.4 | AF42: S043 | AG42: =VLOOKUP($AF42,SalesPerson[],2,FALSE) -> Yash Singh | AH42: =_xlfn.XLOOKUP(AG42,Salespersons!$B:$B,Salespersons!$G:$G,,0) -> 4 | AI42: =_xlfn.XLOOKUP(AG42,Salespersons!$B:$B,Salespersons!$I:$I,,0) -> True | AJ42: Black | AK42: =AL42/W42 -> 0 | AL42: 0 | AM42: =W42-AL42 -> 700000 | AN42: =AM42/100000 -> 7 | AO42: Loan/Finance | AP42: Tata Capital | AQ42: Test Drive Campaign | AR42: No | AS42: No Feedback | AT42: No Feedback | AU42: No Feedback | AV42: No Feedback | AW42: No Feedback
A43: ORD00042 | B43: 45346 | C43: =TEXT(B43,"mmm") -> Feb | D43: =TEXT(B43,"yyyy") -> 2024 | E43: 45376 | F43: Delivered | G43: =IF(E43=0,"",E43-B43) -> 30 | H43: CU0460 | I43: =VLOOKUP($H43,Customers!$A$1:$I$721,2,FALSE) -> Anjali Singh | J43: =VLOOKUP($H43,Customers!$A$1:$I$721,3,FALSE) -> Female | K43: =VLOOKUP($H43,Customers!$A$1:$I$721,4,FALSE) -> 32 | L43: =VLOOKUP($H43,Customers!$A$1:$I$721,5,FALSE) -> Jaipur | M43: =VLOOKUP($H43,Customers!$A$1:$I$721,6,FALSE) -> Rajasthan | N43: =VLOOKUP($H43,Customers!$A$1:$I$721,7,FALSE) -> Salaried - Government | O43: =VLOOKUP($H43,Customers!$A$1:$I$721,8,FALSE) -> 810000 | P43: =VLOOKUP($H43,Customers!$A$1:$I$721,9,FALSE) -> Individual | Q43: C009 | R43: {=VLOOKUP($Q43,Cars[],{2,3,4,5,6,7,8,9},FALSE)} -> Hyundai | S43: i20 | T43: Hatchback | U43: Petrol | V43: Automatic | W43: 780000 | X43: 2023 | Y43: 2 | Z43: D006 | AA43: =VLOOKUP(Z43,Dealers[],5,FALSE) -> North | AB43: {=VLOOKUP($Z43,Dealers[],{2,7,8,9},FALSE)} -> Jaipur Wheels | AC43: 2015 | AD43: 3000 | AE43: 3.5 | AF43: S016 | AG43: =VLOOKUP($AF43,SalesPerson[],2,FALSE) -> Rahul Kapoor | AH43: =_xlfn.XLOOKUP(AG43,Salespersons!$B:$B,Salespersons!$G:$G,,0) -> 8 | AI43: =_xlfn.XLOOKUP(AG43,Salespersons!$B:$B,Salespersons!$I:$I,,0) -> True | AJ43: Grey | AK43: =AL43/W43 -> 0 | AL43: 0 | AM43: =W43-AL43 -> 780000 | AN43: =AM43/100000 -> 7.8 | AO43: Loan/Finance | AP43: ICICI Bank | AQ43: Test Drive Campaign | AR43: Yes | AS43: No Feedback | AT43: No Feedback | AU43: No Feedback | AV43: No Feedback | AW43: No Feedback
A44: ORD00043 | B44: 45347 | C44: =TEXT(B44,"mmm") -> Feb | D44: =TEXT(B44,"yyyy") -> 2024 | E44: 45378 | F44: Delivered | G44: =IF(E44=0,"",E44-B44) -> 31 | H44: CU0062 | I44: =VLOOKUP($H44,Customers!$A$1:$I$721,2,FALSE) -> Ayesha Kapoor | J44: =VLOOKUP($H44,Customers!$A$1:$I$721,3,FALSE) -> Female | K44: =VLOOKUP($H44,Customers!$A$1:$I$721,4,FALSE) -> 25 | L44: =VLOOKUP($H44,Customers!$A$1:$I$721,5,FALSE) -> Pune | M44: =VLOOKUP($H44,Customers!$A$1:$I$721,6,FALSE) -> Maharashtra | N44: =VLOOKUP($H44,Customers!$A$1:$I$721,7,FALSE) -> Business Owner | O44: =VLOOKUP($H44,Customers!$A$1:$I$721,8,FALSE) -> 3340000 | P44: =VLOOKUP($H44,Customers!$A$1:$I$721,9,FALSE) -> Corporate | Q44: C003 | R44: {=VLOOKUP($Q44,Cars[],{2,3,4,5,6,7,8,9},FALSE)} -> Maruti Suzuki | S44: Baleno | T44: Hatchback | U44: Petrol | V44: Automatic | W44: 760000 | X44: 2022 | Y44: 2 | Z44: D009 | AA44: =VLOOKUP(Z44,Dealers[],5,FALSE) -> West | AB44: {=VLOOKUP($Z44,Dealers[],{2,7,8,9},FALSE)} -> Mumbai Autoplex | AC44: 2011 | AD44: 12000 | AE44: 3.5 | AF44: S027 | AG44: =VLOOKUP($AF44,SalesPerson[],2,FALSE) -> Karan Rao | AH44: =_xlfn.XLOOKUP(AG44,Salespersons!$B:$B,Salespersons!$G:$G,,0) -> 4 | AI44: =_xlfn.XLOOKUP(AG44,Salespersons!$B:$B,Salespersons!$I:$I,,0) -> True | AJ44: Grey | AK44: =AL44/W44 -> 0.017105263 | AL44: 13000 | AM44: =W44-AL44 -> 747000 | AN44: =AM44/100000 -> 7.47 | AO44: Lease (Corporate) | AP44: SBI | AQ44: Referral | AR44: Yes | AS44: {=VLOOKUP($A44,Feedback[],{2,4,5,6,7},FALSE)} -> FB0025 | AT44: 5 | AU44: 10 | AV44: Email | AW44: None
A45: ORD00044 | B45: 45348 | C45: =TEXT(B45,"mmm") -> Feb | D45: =TEXT(B45,"yyyy") -> 2024 | E45: 45372 | F45: Delivered | G45: =IF(E45=0,"",E45-B45) -> 24 | H45: CU0285 | I45: =VLOOKUP($H45,Customers!$A$1:$I$721,2,FALSE) -> Divya Mehta | J45: =VLOOKUP($H45,Customers!$A$1:$I$721,3,FALSE) -> Female | K45: =VLOOKUP($H45,Customers!$A$1:$I$721,4,FALSE) -> 40 | L45: =VLOOKUP($H45,Customers!$A$1:$I$721,5,FALSE) -> Mysuru | M45: =VLOOKUP($H45,Customers!$A$1:$I$721,6,FALSE) -> Karnataka | N45: =VLOOKUP($H45,Customers!$A$1:$I$721,7,FALSE) -> Self-Employed Professional | O45: =VLOOKUP($H45,Customers!$A$1:$I$721,8,FALSE) -> 1380000 | P45: =VLOOKUP($H45,Customers!$A$1:$I$721,9,FALSE) -> Individual | Q45: C007 | R45: {=VLOOKUP($Q45,Cars[],{2,3,4,5,6,7,8,9},FALSE)} -> Maruti Suzuki | S45: Grand Vitara | T45: SUV | U45: Hybrid | V45: Automatic | W45: 1150000 | X45: 2022 | Y45: 3 | Z45: D014 | AA45: =VLOOKUP(Z45,Dealers[],5,FALSE) -> South | AB45: {=VLOOKUP($Z45,Dealers[],{2,7,8,9},FALSE)} -> Bengaluru Auto Hub | AC45: 2013 | AD45: 12000 | AE45: 4.4 | AF45: S044 | AG45: =VLOOKUP($AF45,SalesPerson[],2,FALSE) -> Divya Kapoor | AH45: =_xlfn.XLOOKUP(AG45,Salespersons!$B:$B,Salespersons!$G:$G,,0) -> 6 | AI45: =_xlfn.XLOOKUP(AG45,Salespersons!$B:$B,Salespersons!$I:$I,,0) -> True | AJ45: Black | AK45: =AL45/W45 -> 0.049565217 | AL45: 57000 | AM45: =W45-AL45 -> 1093000 | AN45: =AM45/100000 -> 10.93 | AO45: Loan/Finance | AP45: Tata Capital | AQ45: Online Website | AR45: No | AS45: No Feedback | AT45: No Feedback | AU45: No Feedback | AV45: No Feedback | AW45: No Feedback
A46: ORD00045 | B46: 45349 | C46: =TEXT(B46,"mmm") -> Feb | D46: =TEXT(B46,"yyyy") -> 2024 | E46: 45372 | F46: Delivered | G46: =IF(E46=0,"",E46-B46) -> 23 | H46: CU0056 | I46: =VLOOKUP($H46,Customers!$A$1:$I$721,2,FALSE) -> Dinesh Verma | J46: =VLOOKUP($H46,Customers!$A$1:$I$721,3,FALSE) -> Male | K46: =VLOOKUP($H46,Customers!$A$1:$I$721,4,FALSE) -> 40 | L46: =VLOOKUP($H46,Customers!$A$1:$I$721,5,FALSE) -> Surat | M46: =VLOOKUP($H46,Customers!$A$1:$I$721,6,FALSE) -> Gujarat | N46: =VLOOKUP($H46,Customers!$A$1:$I$721,7,FALSE) -> Salaried - Private | O46: =VLOOKUP($H46,Customers!$A$1:$I$721,8,FALSE) -> 1670000 | P46: =VLOOKUP($H46,Customers!$A$1:$I$721,9,FALSE) -> Individual | Q46: C032 | R46: {=VLOOKUP($Q46,Cars[],{2,3,4,5,6,7,8,9},FALSE)} -> Kia | S46: Carens | T46: MPV | U46: Diesel | V46: Manual | W46: 1200000 | X46: 2022 | Y46: 3 | Z46: D012 | AA46: =VLOOKUP(Z46,Dealers[],5,FALSE) -> West | AB46: {=VLOOKUP($Z46,Dealers[],{2,7,8,9},FALSE)} -> Ahmedabad Auto Hub | AC46: 2011 | AD46: 12000 | AE46: 3.8 | AF46: S038 | AG46: =VLOOKUP($AF46,SalesPerson[],2,FALSE) -> Varun Malhotra | AH46: =_xlfn.XLOOKUP(AG46,Salespersons!$B:$B,Salespersons!$G:$G,,0) -> 8 | AI46: =_xlfn.XLOOKUP(AG46,Salespersons!$B:$B,Salespersons!$I:$I,,0) -> True | AJ46: White | AK46: =AL46/W46 -> 0.0375 | AL46: 45000 | AM46: =W46-AL46 -> 1155000 | AN46: =AM46/100000 -> 11.55 | AO46: Cash | AP46: N/A | AQ46: Corporate Tie-up | AR46: Yes | AS46: {=VLOOKUP($A46,Feedback[],{2,4,5,6,7},FALSE)} -> FB0026 | AT46: 3 | AU46: 5 | AV46: Online Survey | AW46: Vehicle Quality
A47: ORD00046 | B47: 45349 | C47: =TEXT(B47,"mmm") -> Feb | D47: =TEXT(B47,"yyyy") -> 2024 | E47: 45363 | F47: Delivered | G47: =IF(E47=0,"",E47-B47) -> 14 | H47: CU0067 | I47: =VLOOKUP($H47,Customers!$A$1:$I$721,2,FALSE) -> Gaurav Singh | J47: =VLOOKUP($H47,Customers!$A$1:$I$721,3,FALSE) -> Male | K47: =VLOOKUP($H47,Customers!$A$1:$I$721,4,FALSE) -> 52 | L47: =VLOOKUP($H47,Customers!$A$1:$I$721,5,FALSE) -> Bengaluru | M47: =VLOOKUP($H47,Customers!$A$1:$I$721,6,FALSE) -> Karnataka | N47: =VLOOKUP($H47,Customers!$A$1:$I$721,7,FALSE) -> Engineer | O47: =VLOOKUP($H47,Customers!$A$1:$I$721,8,FALSE) -> 1590000 | P47: =VLOOKUP($H47,Customers!$A$1:$I$721,9,FALSE) -> Individual | Q47: C031 | R47: {=VLOOKUP($Q47,Cars[],{2,3,4,5,6,7,8,9},FALSE)} -> Kia | S47: Sonet | T47: SUV | U47: Diesel | V47: Manual | W47: 950000 | X47: 2024 | Y47: 4 | Z47: D014 | AA47: =VLOOKUP(Z47,Dealers[],5,FALSE) -> South | AB47: {=VLOOKUP($Z47,Dealers[],{2,7,8,9},FALSE)} -> Bengaluru Auto Hub | AC47: 2013 | AD47: 12000 | AE47: 4.4 | AF47: S042 | AG47: =VLOOKUP($AF47,SalesPerson[],2,FALSE) -> Yash Sharma | AH47: =_xlfn.XLOOKUP(AG47,Salespersons!$B:$B,Salespersons!$G:$G,,0) -> 5 | AI47: =_xlfn.XLOOKUP(AG47,Salespersons!$B:$B,Salespersons!$I:$I,,0) -> True | AJ47: Silver | AK47: =AL47/W47 -> 0.04 | AL47: 38000 | AM47: =W47-AL47 -> 912000 | AN47: =AM47/100000 -> 9.12 | AO47: Cash | AP47: N/A | AQ47: Auto Expo/Event | AR47: Yes | AS47: No Feedback | AT47: No Feedback | AU47: No Feedback | AV47: No Feedback | AW47: No Feedback
A48: ORD00047 | B48: 45351 | C48: =TEXT(B48,"mmm") -> Feb | D48: =TEXT(B48,"yyyy") -> 2024 | E48: 45369 | F48: Delivered | G48: =IF(E48=0,"",E48-B48) -> 18 | H48: CU0242 | I48: =VLOOKUP($H48,Customers!$A$1:$I$721,2,FALSE) -> Nisha Yadav | J48: =VLOOKUP($H48,Customers!$A$1:$I$721,3,FALSE) -> Female | K48: =VLOOKUP($H48,Customers!$A$1:$I$721,4,FALSE) -> 38 | L48: =VLOOKUP($H48,Customers!$A$1:$I$721,5,FALSE) -> Lucknow | M48: =VLOOKUP($H48,Customers!$A$1:$I$721,6,FALSE) -> Uttar Pradesh | N48: =VLOOKUP($H48,Customers!$A$1:$I$721,7,FALSE) -> Retired | O48: =VLOOKUP($H48,Customers!$A$1:$I$721,8,FALSE) -> 840000 | P48: =VLOOKUP($H48,Customers!$A$1:$I$721,9,FALSE) -> Individual | Q48: C013 | R48: {=VLOOKUP($Q48,Cars[],{2,3,4,5,6,7,8,9},FALSE)} -> Hyundai | S48: Alcazar | T48: SUV | U48: Diesel | V48: Automatic | W48: 1700000 | X48: 2024 | Y48: 2 | Z48: D008 | AA48: =VLOOKUP(Z48,Dealers[],5,FALSE) -> North | AB48: {=VLOOKUP($Z48,Dealers[],{2,7,8,9},FALSE)} -> Noida Car World | AC48: 2007 | AD48: 10000 | AE48: 3.8 | AF48: S024 | AG48: =VLOOKUP($AF48,SalesPerson[],2,FALSE) -> Imran Joshi | AH48: =_xlfn.XLOOKUP(AG48,Salespersons!$B:$B,Salespersons!$G:$G,,0) -> 4 | AI48: =_xlfn.XLOOKUP(AG48,Salespersons!$B:$B,Salespersons!$I:$I,,0) -> True | AJ48: Black | AK48: =AL48/W48 -> 0 | AL48: 0 | AM48: =W48-AL48 -> 1700000 | AN48: =AM48/100000 -> 17 | AO48: Cash | AP48: N/A | AQ48: Test Drive Campaign | AR48: No | AS48: No Feedback | AT48: No Feedback | AU48: No Feedback | AV48: No Feedback | AW48: No Feedback
A49: ORD00048 | B49: 45354 | C49: =TEXT(B49,"mmm") -> Mar | D49: =TEXT(B49,"yyyy") -> 2024 | E49: 45384 | F49: Delivered | G49: =IF(E49=0,"",E49-B49) -> 30 | H49: CU0651 | I49: =VLOOKUP($H49,Customers!$A$1:$I$721,2,FALSE) -> Mohit Shah | J49: =VLOOKUP($H49,Customers!$A$1:$I$721,3,FALSE) -> Male | K49: =VLOOKUP($H49,Customers!$A$1:$I$721,4,FALSE) -> 21 | L49: =VLOOKUP($H49,Customers!$A$1:$I$721,5,FALSE) -> Ludhiana | M49: =VLOOKUP($H49,Customers!$A$1:$I$721,6,FALSE) -> Punjab | N49: =VLOOKUP($H49,Customers!$A$1:$I$721,7,FALSE) -> Business Owner | O49: =VLOOKUP($H49,Customers!$A$1:$I$721,8,FALSE) -> 2550000 | P49: =VLOOKUP($H49,Customers!$A$1:$I$721,9,FALSE) -> Individual | Q49: C004 | R49: {=VLOOKUP($Q49,Cars[],{2,3,4,5,6,7,8,9},FALSE)} -> Maruti Suzuki | S49: Dzire | T49: Sedan | U49: Petrol | V49: Manual | W49: 690000 | X49: 2024 | Y49: 3 | Z49: D016 | AA49: =VLOOKUP(Z49,Dealers[],5,FALSE) -> South | AB49: {=VLOOKUP($Z49,Dealers[],{2,7,8,9},FALSE)} -> Chennai Wheels | AC49: 2007 | AD49: 4500 | AE49: 4.7 | AF49: S048 | AG49: =VLOOKUP($AF49,SalesPerson[],2,FALSE) -> Kunal Pillai | AH49: =_xlfn.XLOOKUP(AG49,Salespersons!$B:$B,Salespersons!$G:$G,,0) -> 5 | AI49: =_xlfn.XLOOKUP(AG49,Salespersons!$B:$B,Salespersons!$I:$I,,0) -> True | AJ49: Silver | AK49: =AL49/W49 -> 0.0086956522 | AL49: 6000 | AM49: =W49-AL49 -> 684000 | AN49: =AM49/100000 -> 6.84 | AO49: Cash | AP49: N/A | AQ49: Corporate Tie-up | AR49: No | AS49: No Feedback | AT49: No Feedback | AU49: No Feedback | AV49: No Feedback | AW49: No Feedback
A50: ORD00049 | B50: 45354 | C50: =TEXT(B50,"mmm") -> Mar | D50: =TEXT(B50,"yyyy") -> 2024 | E50: 45368 | F50: Delivered | G50: =IF(E50=0,"",E50-B50) -> 14 | H50: CU0160 | I50: =VLOOKUP($H50,Customers!$A$1:$I$721,2,FALSE) -> Nitin Reddy | J50: =VLOOKUP($H50,Customers!$A$1:$I$721,3,FALSE) -> Male | K50: =VLOOKUP($H50,Customers!$A$1:$I$721,4,FALSE) -> 31 | L50: =VLOOKUP($H50,Customers!$A$1:$I$721,5,FALSE) -> Ludhiana | M50: =VLOOKUP($H50,Customers!$A$1:$I$721,6,FALSE) -> Punjab | N50: =VLOOKUP($H50,Customers!$A$1:$I$721,7,FALSE) -> Business Owner | O50: =VLOOKUP($H50,Customers!$A$1:$I$721,8,FALSE) -> 3270000 | P50: =VLOOKUP($H50,Customers!$A$1:$I$721,9,FALSE) -> Corporate | Q50: C028 | R50: {=VLOOKUP($Q50,Cars[],{2,3,4,5,6,7,8,9},FALSE)} -> Honda | S50: City | T50: Sedan | U50: Petrol | V50: Automatic | W50: 1250000 | X50: 2023 | Y50: 4 | Z50: D005 | AA50: =VLOOKUP(Z50,Dealers[],5,FALSE) -> North | AB50: {=VLOOKUP($Z50,Dealers[],{2,7,8,9},FALSE)} -> Ludhiana Wheels | AC50: 2010 | AD50: 12000 | AE50: 4 | AF50: S015 | AG50: =VLOOKUP($AF50,SalesPerson[],2,FALSE) -> Akash Verma | AH50: =_xlfn.XLOOKUP(AG50,Salespersons!$B:$B,Salespersons!$G:$G,,0) -> 8 | AI50: =_xlfn.XLOOKUP(AG50,Salespersons!$B:$B,Salespersons!$I:$I,,0) -> True | AJ50: White | AK50: =AL50/W50 -> 0.0192 | AL50: 24000 | AM50: =W50-AL50 -> 1226000 | AN50: =AM50/100000 -> 12.26 | AO50: Lease (Corporate) | AP50: Bajaj Finserv | AQ50: Social Media | AR50: No | AS50: No Feedback | AT50: No Feedback | AU50: No Feedback | AV50: No Feedback | AW50: No Feedback
A51: ORD00050 | B51: 45356 | C51: =TEXT(B51,"mmm") -> Mar | D51: =TEXT(B51,"yyyy") -> 2024 | E51: 45371 | F51: Delivered | G51: =IF(E51=0,"",E51-B51) -> 15 | H51: CU0465 | I51: =VLOOKUP($H51,Customers!$A$1:$I$721,2,FALSE) -> Komal Rao | J51: =VLOOKUP($H51,Customers!$A$1:$I$721,3,FALSE) -> Female | K51: =VLOOKUP($H51,Customers!$A$1:$I$721,4,FALSE) -> 52 | L51: =VLOOKUP($H51,Customers!$A$1:$I$721,5,FALSE) -> Ludhiana | M51: =VLOOKUP($H51,Customers!$A$1:$I$721,6,FALSE) -> Punjab | N51: =VLOOKUP($H51,Customers!$A$1:$I$721,7,FALSE) -> Salaried - Private | O51: =VLOOKUP($H51,Customers!$A$1:$I$721,8,FALSE) -> 1320000 | P51: =VLOOKUP($H51,Customers!$A$1:$I$721,9,FALSE) -> Individual | Q51: C006 | R51: {=VLOOKUP($Q51,Cars[],{2,3,4,5,6,7,8,9},FALSE)} -> Maruti Suzuki | S51: Ertiga | T51: MPV | U51: CNG | V51: Manual | W51: 900000 | X51: 2022 | Y51: 3 | Z51: D005 | AA51: =VLOOKUP(Z51,Dealers[],5,FALSE) -> North | AB51: {=VLOOKUP($Z51,Dealers[],{2,7,8,9},FALSE)} -> Ludhiana Wheels | AC51: 2010 | AD51: 12000 | AE51: 4 | AF51: S014 | AG51: =VLOOKUP($AF51,SalesPerson[],2,FALSE) -> Harsh Nair | AH51: =_xlfn.XLOOKUP(AG51,Salespersons!$B:$B,Salespersons!$G:$G,,0) -> 8 | AI51: =_xlfn.XLOOKUP(AG51,Salespersons!$B:$B,Salespersons!$I:$I,,0) -> True | AJ51: White | AK51: =AL51/W51 -> 0.0077777778 | AL51: 7000 | AM51: =W51-AL51 -> 893000 | AN51: =AM51/100000 -> 8.93 | AO51: Exchange + Loan | AP51: SBI | AQ51: Auto Expo/Event | AR51: No | AS51: No Feedback | AT51: No Feedback | AU51: No Feedback | AV51: No Feedback | AW51: No Feedback
A52: ORD00051 | B52: 45356 | C52: =TEXT(B52,"mmm") -> Mar | D52: =TEXT(B52,"yyyy") -> 2024 | F52: Cancelled | G52: =IF(E52=0,"",E52-B52) | H52: CU0384 | I52: =VLOOKUP($H52,Customers!$A$1:$I$721,2,FALSE) -> Ritu Joshi | J52: =VLOOKUP($H52,Customers!$A$1:$I$721,3,FALSE) -> Female | K52: =VLOOKUP($H52,Customers!$A$1:$I$721,4,FALSE) -> 22 | L52: =VLOOKUP($H52,Customers!$A$1:$I$721,5,FALSE) -> Mysuru | M52: =VLOOKUP($H52,Customers!$A$1:$I$721,6,FALSE) -> Karnataka | N52: =VLOOKUP($H52,Customers!$A$1:$I$721,7,FALSE) -> Salaried - Private | O52: =VLOOKUP($H52,Customers!$A$1:$I$721,8,FALSE) -> 1340000 | P52: =VLOOKUP($H52,Customers!$A$1:$I$721,9,FALSE) -> Individual | Q52: C012 | R52: {=VLOOKUP($Q52,Cars[],{2,3,4,5,6,7,8,9},FALSE)} -> Hyundai | S52: Verna | T52: Sedan | U52: Petrol | V52: Automatic | W52: 1100000 | X52: 2023 | Y52: 2 | Z52: D013 | AA52: =VLOOKUP(Z52,Dealers[],5,FALSE) -> West | AB52: {=VLOOKUP($Z52,Dealers[],{2,7,8,9},FALSE)} -> Surat Autoplex | AC52: 2010 | AD52: 10000 | AE52: 4.4 | AF52: S041 | AG52: =VLOOKUP($AF52,SalesPerson[],2,FALSE) -> Jatin Kapoor | AH52: =_xlfn.XLOOKUP(AG52,Salespersons!$B:$B,Salespersons!$G:$G,,0) -> 5 | AI52: =_xlfn.XLOOKUP(AG52,Salespersons!$B:$B,Salespersons!$I:$I,,0) -> True | AJ52: White | AK52: =AL52/W52 -> 0.0090909091 | AL52: 10000 | AM52: =W52-AL52 -> 1090000 | AN52: =AM52/100000 -> 10.9 | AO52: Loan/Finance | AP52: Mahindra Finance | AQ52: Walk-in | AR52: No | AS52: No Feedback | AT52: No Feedback | AU52: No Feedback | AV52: No Feedback | AW52: No Feedback
A53: ORD00052 | B53: 45356 | C53: =TEXT(B53,"mmm") -> Mar | D53: =TEXT(B53,"yyyy") -> 2024 | E53: 45382 | F53: Delivered | G53: =IF(E53=0,"",E53-B53) -> 26 | H53: CU0128 | I53: =VLOOKUP($H53,Customers!$A$1:$I$721,2,FALSE) -> Jatin Mishra | J53: =VLOOKUP($H53,Customers!$A$1:$I$721,3,FALSE) -> Male | K53: =VLOOKUP($H53,Customers!$A$1:$I$721,4,FALSE) -> 64 | L53: =VLOOKUP($H53,Customers!$A$1:$I$721,5,FALSE) -> Hyderabad | M53: =VLOOKUP($H53,Customers!$A$1:$I$721,6,FALSE) -> Telangana | N53: =VLOOKUP($H53,Customers!$A$1:$I$721,7,FALSE) -> Salaried - Private | O53: =VLOOKUP($H53,Customers!$A$1:$I$721,8,FALSE) -> 1290000 | P53: =VLOOKUP($H53,Customers!$A$1:$I$721,9,FALSE) -> Individual | Q53: C009 | R53: {=VLOOKUP($Q53,Cars[],{2,3,4,5,6,7,8,9},FALSE)} -> Hyundai | S53: i20 | T53: Hatchback | U53: Petrol | V53: Automatic | W53: 780000 | X53: 2023 | Y53: 2 | Z53: D018 | AA53: =VLOOKUP(Z53,Dealers[],5,FALSE) -> South | AB53: {=VLOOKUP($Z53,Dealers[],{2,7,8,9},FALSE)} -> Hyderabad Automobiles | AC53: 2019 | AD53: 4500 | AE53: 3.8 | AF53: S054 | AG53: =VLOOKUP($AF53,SalesPerson[],2,FALSE) -> Gaurav Shah | AH53: =_xlfn.XLOOKUP(AG53,Salespersons!$B:$B,Salespersons!$G:$G,,0) -> 4 | AI53: =_xlfn.XLOOKUP(AG53,Salespersons!$B:$B,Salespersons!$I:$I,,0) -> True | AJ53: Grey | AK53: =AL53/W53 -> 0.008974359 | AL53: 7000 | AM53: =W53-AL53 -> 773000 | AN53: =AM53/100000 -> 7.73 | AO53: Loan/Finance | AP53: Bajaj Finserv | AQ53: Corporate Tie-up | AR53: No | AS53: No Feedback | AT53: No Feedback | AU53: No Feedback | AV53: No Feedback | AW53: No Feedback
A54: ORD00053 | B54: 45358 | C54: =TEXT(B54,"mmm") -> Mar | D54: =TEXT(B54,"yyyy") -> 2024 | E54: 45370 | F54: Delivered | G54: =IF(E54=0,"",E54-B54) -> 12 | H54: CU0435 | I54: =VLOOKUP($H54,Customers!$A$1:$I$721,2,FALSE) -> Sneha Rao | J54: =VLOOKUP($H54,Customers!$A$1:$I$721,3,FALSE) -> Female | K54: =VLOOKUP($H54,Customers!$A$1:$I$721,4,FALSE) -> 31 | L54: =VLOOKUP($H54,Customers!$A$1:$I$721,5,FALSE) -> Chennai | M54: =VLOOKUP($H54,Customers!$A$1:$I$721,6,FALSE) -> Tamil Nadu | N54: =VLOOKUP($H54,Customers!$A$1:$I$721,7,FALSE) -> Self-Employed Professional | O54: =VLOOKUP($H54,Customers!$A$1:$I$721,8,FALSE) -> 2470000 | P54: =VLOOKUP($H54,Customers!$A$1:$I$721,9,FALSE) -> Individual | Q54: C023 | R54: {=VLOOKUP($Q54,Cars[],{2,3,4,5,6,7,8,9},FALSE)} -> Mahindra | S54: XUV 3XO | T54: SUV | U54: Petrol | V54: Manual | W54: 900000 | X54: 2024 | Y54: 3 | Z54: D016 | AA54: =VLOOKUP(Z54,Dealers[],5,FALSE) -> South | AB54: {=VLOOKUP($Z54,Dealers[],{2,7,8,9},FALSE)} -> Chennai Wheels | AC54: 2007 | AD54: 4500 | AE54: 4.7 | AF54: S049 | AG54: =VLOOKUP($AF54,SalesPerson[],2,FALSE) -> Anjali Joshi | AH54: =_xlfn.XLOOKUP(AG54,Salespersons!$B:$B,Salespersons!$G:$G,,0) -> 8 | AI54: =_xlfn.XLOOKUP(AG54,Salespersons!$B:$B,Salespersons!$I:$I,,0) -> True | AJ54: White | AK54: =AL54/W54 -> 0.037777778 | AL54: 34000 | AM54: =W54-AL54 -> 866000 | AN54: =AM54/100000 -> 8.66 | AO54: Loan/Finance | AP54: Mahindra Finance | AQ54: Social Media | AR54: No | AS54: {=VLOOKUP($A54,Feedback[],{2,4,5,6,7},FALSE)} -> FB0027 | AT54: 4 | AU54: 6 | AV54: Email | AW54: None
A55: ORD00054 | B55: 45358 | C55: =TEXT(B55,"mmm") -> Mar | D55: =TEXT(B55,"yyyy") -> 2024 | E55: 45366 | F55: Delivered | G55: =IF(E55=0,"",E55-B55) -> 8 | H55: CU0151 | I55: =VLOOKUP($H55,Customers!$A$1:$I$721,2,FALSE) -> Gaurav Malhotra | J55: =VLOOKUP($H55,Customers!$A$1:$I$721,3,FALSE) -> Male | K55: =VLOOKUP($H55,Customers!$A$1:$I$721,4,FALSE) -> 27 | L55: =VLOOKUP($H55,Customers!$A$1:$I$721,5,FALSE) -> Mysuru | M55: =VLOOKUP($H55,Customers!$A$1:$I$721,6,FALSE) -> Karnataka | N55: =VLOOKUP($H55,Customers!$A$1:$I$721,7,FALSE) -> Salaried - Private | O55: =VLOOKUP($H55,Customers!$A$1:$I$721,8,FALSE) -> 1510000 | P55: =VLOOKUP($H55,Customers!$A$1:$I$721,9,FALSE) -> Individual | Q55: C005 | R55: {=VLOOKUP($Q55,Cars[],{2,3,4,5,6,7,8,9},FALSE)} -> Maruti Suzuki | S55: Brezza | T55: SUV | U55: Petrol | V55: Automatic | W55: 900000 | X55: 2022 | Y55: 3 | Z55: D014 | AA55: =VLOOKUP(Z55,Dealers[],5,FALSE) -> South | AB55: {=VLOOKUP($Z55,Dealers[],{2,7,8,9},FALSE)} -> Bengaluru Auto Hub | AC55: 2013 | AD55: 12000 | AE55: 4.4 | AF55: S042 | AG55: =VLOOKUP($AF55,SalesPerson[],2,FALSE) -> Yash Sharma | AH55: =_xlfn.XLOOKUP(AG55,Salespersons!$B:$B,Salespersons!$G:$G,,0) -> 5 | AI55: =_xlfn.XLOOKUP(AG55,Salespersons!$B:$B,Salespersons!$I:$I,,0) -> True | AJ55: Silver | AK55: =AL55/W55 -> 0 | AL55: 0 | AM55: =W55-AL55 -> 900000 | AN55: =AM55/100000 -> 9 | AO55: Exchange + Loan | AP55: Axis Bank | AQ55: Online Website | AR55: No | AS55: {=VLOOKUP($A55,Feedback[],{2,4,5,6,7},FALSE)} -> FB0028 | AT55: 5 | AU55: 9 | AV55: Dealer Visit | AW55: None
A56: ORD00055 | B56: 45358 | C56: =TEXT(B56,"mmm") -> Mar | D56: =TEXT(B56,"yyyy") -> 2024 | E56: 45387 | F56: Delivered | G56: =IF(E56=0,"",E56-B56) -> 29 | H56: CU0170 | I56: =VLOOKUP($H56,Customers!$A$1:$I$721,2,FALSE) -> Sandeep Das | J56: =VLOOKUP($H56,Customers!$A$1:$I$721,3,FALSE) -> Male | K56: =VLOOKUP($H56,Customers!$A$1:$I$721,4,FALSE) -> 44 | L56: =VLOOKUP($H56,Customers!$A$1:$I$721,5,FALSE) -> Surat | M56: =VLOOKUP($H56,Customers!$A$1:$I$721,6,FALSE) -> Gujarat | N56: =VLOOKUP($H56,Customers!$A$1:$I$721,7,FALSE) -> Salaried - Government | O56: =VLOOKUP($H56,Customers!$A$1:$I$721,8,FALSE) -> 1190000 | P56: =VLOOKUP($H56,Customers!$A$1:$I$721,9,FALSE) -> Individual | Q56: C029 | R56: {=VLOOKUP($Q56,Cars[],{2,3,4,5,6,7,8,9},FALSE)} -> Honda | S56: Amaze | T56: Sedan | U56: Petrol | V56: Manual | W56: 800000 | X56: 2024 | Y56: 3 | Z56: D013 | AA56: =VLOOKUP(Z56,Dealers[],5,FALSE) -> West | AB56: {=VLOOKUP($Z56,Dealers[],{2,7,8,9},FALSE)} -> Surat Autoplex | AC56: 2010 | AD56: 10000 | AE56: 4.4 | AF56: S041 | AG56: =VLOOKUP($AF56,SalesPerson[],2,FALSE) -> Jatin Kapoor | AH56: =_xlfn.XLOOKUP(AG56,Salespersons!$B:$B,Salespersons!$G:$G,,0) -> 5 | AI56: =_xlfn.XLOOKUP(AG56,Salespersons!$B:$B,Salespersons!$I:$I,,0) -> True | AJ56: Grey | AK56: =AL56/W56 -> 0.0275 | AL56: 22000 | AM56: =W56-AL56 -> 778000 | AN56: =AM56/100000 -> 7.78 | AO56: Exchange + Loan | AP56: Bajaj Finserv | AQ56: Corporate Tie-up | AR56: Yes | AS56: No Feedback | AT56: No Feedback | AU56: No Feedback | AV56: No Feedback | AW56: No Feedback
A57: ORD00056 | B57: 45359 | C57: =TEXT(B57,"mmm") -> Mar | D57: =TEXT(B57,"yyyy") -> 2024 | E57: 45372 | F57: Delivered | G57: =IF(E57=0,"",E57-B57) -> 13 | H57: CU0112 | I57: =VLOOKUP($H57,Customers!$A$1:$I$721,2,FALSE) -> Ramesh Chauhan | J57: =VLOOKUP($H57,Customers!$A$1:$I$721,3,FALSE) -> Male | K57: =VLOOKUP($H57,Customers!$A$1:$I$721,4,FALSE) -> 41 | L57: =VLOOKUP($H57,Customers!$A$1:$I$721,5,FALSE) -> Surat | M57: =VLOOKUP($H57,Customers!$A$1:$I$721,6,FALSE) -> Gujarat | N57: =VLOOKUP($H57,Customers!$A$1:$I$721,7,FALSE) -> Doctor | O57: =VLOOKUP($H57,Customers!$A$1:$I$721,8,FALSE) -> 3880000 | P57: =VLOOKUP($H57,Customers!$A$1:$I$721,9,FALSE) -> Individual | Q57: C016 | R57: {=VLOOKUP($Q57,Cars[],{2,3,4,5,6,7,8,9},FALSE)} -> Tata | S57: Nexon | T57: SUV | U57: Diesel | V57: Manual | W57: 950000 | X57: 2023 | Y57: 3 | Z57: D013 | AA57: =VLOOKUP(Z57,Dealers[],5,FALSE) -> West | AB57: {=VLOOKUP($Z57,Dealers[],{2,7,8,9},FALSE)} -> Surat Autoplex | AC57: 2010 | AD57: 10000 | AE57: 4.4 | AF57: S039 | AG57: =VLOOKUP($AF57,SalesPerson[],2,FALSE) -> Vivek Mehta | AH57: =_xlfn.XLOOKUP(AG57,Salespersons!$B:$B,Salespersons!$G:$G,,0) -> 4 | AI57: =_xlfn.XLOOKUP(AG57,Salespersons!$B:$B,Salespersons!$I:$I,,0) -> True | AJ57: Red | AK57: =AL57/W57 -> 0.0094736842 | AL57: 9000 | AM57: =W57-AL57 -> 941000 | AN57: =AM57/100000 -> 9.41 | AO57: Exchange + Loan | AP57: Mahindra Finance | AQ57: Walk-in | AR57: Yes | AS57: {=VLOOKUP($A57,Feedback[],{2,4,5,6,7},FALSE)} -> FB0029 | AT57: 4 | AU57: 8 | AV57: Phone | AW57: None
A58: ORD00057 | B58: 45359 | C58: =TEXT(B58,"mmm") -> Mar | D58: =TEXT(B58,"yyyy") -> 2024 | E58: 45370 | F58: Delivered | G58: =IF(E58=0,"",E58-B58) -> 11 | H58: CU0072 | I58: =VLOOKUP($H58,Customers!$A$1:$I$721,2,FALSE) -> Ashok Singh | J58: =VLOOKUP($H58,Customers!$A$1:$I$721,3,FALSE) -> Male | K58: =VLOOKUP($H58,Customers!$A$1:$I$721,4,FALSE) -> 56 | L58: =VLOOKUP($H58,Customers!$A$1:$I$721,5,FALSE) -> Ludhiana | M58: =VLOOKUP($H58,Customers!$A$1:$I$721,6,FALSE) -> Punjab | N58: =VLOOKUP($H58,Customers!$A$1:$I$721,7,FALSE) -> Doctor | O58: =VLOOKUP($H58,Customers!$A$1:$I$721,8,FALSE) -> 4100000 | P58: =VLOOKUP($H58,Customers!$A$1:$I$721,9,FALSE) -> Individual | Q58: C024 | R58: {=VLOOKUP($Q58,Cars[],{2,3,4,5,6,7,8,9},FALSE)} -> Mahindra | S58: Bolero | T58: SUV | U58: Diesel | V58: Manual | W58: 1000000 | X58: 2019 | Y58: 3 | Z58: D005 | AA58: =VLOOKUP(Z58,Dealers[],5,FALSE) -> North | AB58: {=VLOOKUP($Z58,Dealers[],{2,7,8,9},FALSE)} -> Ludhiana Wheels | AC58: 2010 | AD58: 12000 | AE58: 4 | AF58: S015 | AG58: =VLOOKUP($AF58,SalesPerson[],2,FALSE) -> Akash Verma | AH58: =_xlfn.XLOOKUP(AG58,Salespersons!$B:$B,Salespersons!$G:$G,,0) -> 8 | AI58: =_xlfn.XLOOKUP(AG58,Salespersons!$B:$B,Salespersons!$I:$I,,0) -> True | AJ58: White | AK58: =AL58/W58 -> 0.035 | AL58: 35000 | AM58: =W58-AL58 -> 965000 | AN58: =AM58/100000 -> 9.65 | AO58: Cash | AP58: N/A | AQ58: Online Website | AR58: No | AS58: {=VLOOKUP($A58,Feedback[],{2,4,5,6,7},FALSE)} -> FB0030 | AT58: 5 | AU58: 8 | AV58: Online Survey | AW58: None
A59: ORD00058 | B59: 45362 | C59: =TEXT(B59,"mmm") -> Mar | D59: =TEXT(B59,"yyyy") -> 2024 | E59: 45391 | F59: Delivered | G59: =IF(E59=0,"",E59-B59) -> 29 | H59: CU0113 | I59: =VLOOKUP($H59,Customers!$A$1:$I$721,2,FALSE) -> Komal Shah | J59: =VLOOKUP($H59,Customers!$A$1:$I$721,3,FALSE) -> Female | K59: =VLOOKUP($H59,Customers!$A$1:$I$721,4,FALSE) -> 24 | L59: =VLOOKUP($H59,Customers!$A$1:$I$721,5,FALSE) -> Chennai | M59: =VLOOKUP($H59,Customers!$A$1:$I$721,6,FALSE) -> Tamil Nadu | N59: =VLOOKUP($H59,Customers!$A$1:$I$721,7,FALSE) -> Salaried - Private | O59: =VLOOKUP($H59,Customers!$A$1:$I$721,8,FALSE) -> 640000 | P59: =VLOOKUP($H59,Customers!$A$1:$I$721,9,FALSE) -> Individual | Q59: C011 | R59: {=VLOOKUP($Q59,Cars[],{2,3,4,5,6,7,8,9},FALSE)} -> Hyundai | S59: Creta | T59: SUV | U59: Diesel | V59: Automatic | W59: 1250000 | X59: 2024 | Y59: 4 | Z59: D016 | AA59: =VLOOKUP(Z59,Dealers[],5,FALSE) -> South | AB59: {=VLOOKUP($Z59,Dealers[],{2,7,8,9},FALSE)} -> Chennai Wheels | AC59: 2007 | AD59: 4500 | AE59: 4.7 | AF59: S048 | AG59: =VLOOKUP($AF59,SalesPerson[],2,FALSE) -> Kunal Pillai | AH59: =_xlfn.XLOOKUP(AG59,Salespersons!$B:$B,Salespersons!$G:$G,,0) -> 5 | AI59: =_xlfn.XLOOKUP(AG59,Salespersons!$B:$B,Salespersons!$I:$I,,0) -> True | AJ59: Black | AK59: =AL59/W59 -> 0 | AL59: 0 | AM59: =W59-AL59 -> 1250000 | AN59: =AM59/100000 -> 12.5 | AO59: Cash | AP59: N/A | AQ59: Test Drive Campaign | AR59: Yes | AS59: No Feedback | AT59: No Feedback | AU59: No Feedback | AV59: No Feedback | AW59: No Feedback
A60: ORD00059 | B60: 45363 | C60: =TEXT(B60,"mmm") -> Mar | D60: =TEXT(B60,"yyyy") -> 2024 | E60: 45397 | F60: Delivered | G60: =IF(E60=0,"",E60-B60) -> 34 | H60: CU0652 | I60: =VLOOKUP($H60,Customers!$A$1:$I$721,2,FALSE) -> Vinod Das | J60: =VLOOKUP($H60,Customers!$A$1:$I$721,3,FALSE) -> Male | K60: =VLOOKUP($H60,Customers!$A$1:$I$721,4,FALSE) -> 38 | L60: =VLOOKUP($H60,Customers!$A$1:$I$721,5,FALSE) -> Bhopal | M60: =VLOOKUP($H60,Customers!$A$1:$I$721,6,FALSE) -> Madhya Pradesh | N60: =VLOOKUP($H60,Customers!$A$1:$I$721,7,FALSE) -> Self-Employed Professional | O60: =VLOOKUP($H60,Customers!$A$1:$I$721,8,FALSE) -> 1470000 | P60: =VLOOKUP($H60,Customers!$A$1:$I$721,9,FALSE) -> Individual | Q60: C004 | R60: {=VLOOKUP($Q60,Cars[],{2,3,4,5,6,7,8,9},FALSE)} -> Maruti Suzuki | S60: Dzire | T60: Sedan | U60: Petrol | V60: Manual | W60: 690000 | X60: 2024 | Y60: 3 | Z60: D025 | AA60: =VLOOKUP(Z60,Dealers[],5,FALSE) -> Central | AB60: {=VLOOKUP($Z60,Dealers[],{2,7,8,9},FALSE)} -> Indore Wheels | AC60: 2019 | AD60: 3000 | AE60: 4.7 | AF60: S074 | AG60: =VLOOKUP($AF60,SalesPerson[],2,FALSE) -> Kunal Shah | AH60: =_xlfn.XLOOKUP(AG60,Salespersons!$B:$B,Salespersons!$G:$G,,0) -> 8 | AI60: =_xlfn.XLOOKUP(AG60,Salespersons!$B:$B,Salespersons!$I:$I,,0) -> True | AJ60: Grey | AK60: =AL60/W60 -> 0.0086956522 | AL60: 6000 | AM60: =W60-AL60 -> 684000 | AN60: =AM60/100000 -> 6.84 | AO60: Loan/Finance | AP60: Bajaj Finserv | AQ60: Walk-in | AR60: Yes | AS60: {=VLOOKUP($A60,Feedback[],{2,4,5,6,7},FALSE)} -> FB0031 | AT60: 3 | AU60: 7 | AV60: Dealer Visit | AW60: Pricing
A61: ORD00060 | B61: 45364 | C61: =TEXT(B61,"mmm") -> Mar | D61: =TEXT(B61,"yyyy") -> 2024 | E61: 45384 | F61: Delivered | G61: =IF(E61=0,"",E61-B61) -> 20 | H61: CU0063 | I61: =VLOOKUP($H61,Customers!$A$1:$I$721,2,FALSE) -> Nitin Bose | J61: =VLOOKUP($H61,Customers!$A$1:$I$721,3,FALSE) -> Male | K61: =VLOOKUP($H61,Customers!$A$1:$I$721,4,FALSE) -> 41 | L61: =VLOOKUP($H61,Customers!$A$1:$I$721,5,FALSE) -> Guwahati | M61: =VLOOKUP($H61,Customers!$A$1:$I$721,6,FALSE) -> Assam | N61: =VLOOKUP($H61,Customers!$A$1:$I$721,7,FALSE) -> Salaried - Private | O61: =VLOOKUP($H61,Customers!$A$1:$I$721,8,FALSE) -> 1250000 | P61: =VLOOKUP($H61,Customers!$A$1:$I$721,9,FALSE) -> Individual | Q61: C006 | R61: {=VLOOKUP($Q61,Cars[],{2,3,4,5,6,7,8,9},FALSE)} -> Maruti Suzuki | S61: Ertiga | T61: MPV | U61: CNG | V61: Manual | W61: 900000 | X61: 2022 | Y61: 3 | Z61: D022 | AA61: =VLOOKUP(Z61,Dealers[],5,FALSE) -> East | AB61: {=VLOOKUP($Z61,Dealers[],{2,7,8,9},FALSE)} -> Patna Autoplex | AC61: 2007 | AD61: 8000 | AE61: 3.9 | AF61: S065 | AG61: =VLOOKUP($AF61,SalesPerson[],2,FALSE) -> Lokesh Iyer | AH61: =_xlfn.XLOOKUP(AG61,Salespersons!$B:$B,Salespersons!$G:$G,,0) -> 4 | AI61: =_xlfn.XLOOKUP(AG61,Salespersons!$B:$B,Salespersons!$I:$I,,0) -> True | AJ61: Blue | AK61: =AL61/W61 -> 0 | AL61: 0 | AM61: =W61-AL61 -> 900000 | AN61: =AM61/100000 -> 9 | AO61: Loan/Finance | AP61: Axis Bank | AQ61: Social Media | AR61: No | AS61: No Feedback | AT61: No Feedback | AU61: No Feedback | AV61: No Feedback | AW61: No Feedback
A62: ORD00061 | B62: 45365 | C62: =TEXT(B62,"mmm") -> Mar | D62: =TEXT(B62,"yyyy") -> 2024 | E62: 45371 | F62: Delivered | G62: =IF(E62=0,"",E62-B62) -> 6 | H62: CU0619 | I62: =VLOOKUP($H62,Customers!$A$1:$I$721,2,FALSE) -> Aman Mishra | J62: =VLOOKUP($H62,Customers!$A$1:$I$721,3,FALSE) -> Male | K62: =VLOOKUP($H62,Customers!$A$1:$I$721,4,FALSE) -> 38 | L62: =VLOOKUP($H62,Customers!$A$1:$I$721,5,FALSE) -> Gurugram | M62: =VLOOKUP($H62,Customers!$A$1:$I$721,6,FALSE) -> Haryana | N62: =VLOOKUP($H62,Customers!$A$1:$I$721,7,FALSE) -> Salaried - Private | O62: =VLOOKUP($H62,Customers!$A$1:$I$721,8,FALSE) -> 1280000 | P62: =VLOOKUP($H62,Customers!$A$1:$I$721,9,FALSE) -> Individual | Q62: C011 | R62: {=VLOOKUP($Q62,Cars[],{2,3,4,5,6,7,8,9},FALSE)} -> Hyundai | S62: Creta | T62: SUV | U62: Diesel | V62: Automatic | W62: 1250000 | X62: 2024 | Y62: 4 | Z62: D003 | AA62: =VLOOKUP(Z62,Dealers[],5,FALSE) -> North | AB62: {=VLOOKUP($Z62,Dealers[],{2,7,8,9},FALSE)} -> Panipat Motors | AC62: 2012 | AD62: 10000 | AE62: 4.2 | AF62: S010 | AG62: =VLOOKUP($AF62,SalesPerson[],2,FALSE) -> Rahul Rao | AH62: =_xlfn.XLOOKUP(AG62,Salespersons!$B:$B,Salespersons!$G:$G,,0) -> 5 | AI62: =_xlfn.XLOOKUP(AG62,Salespersons!$B:$B,Salespersons!$I:$I,,0) -> True | AJ62: Brown | AK62: =AL62/W62 -> 0.0424 | AL62: 53000 | AM62: =W62-AL62 -> 1197000 | AN62: =AM62/100000 -> 11.97 | AO62: Loan/Finance | AP62: Mahindra Finance | AQ62: Auto Expo/Event | AR62: No | AS62: No Feedback | AT62: No Feedback | AU62: No Feedback | AV62: No Feedback | AW62: No Feedback
A63: ORD00062 | B63: 45366 | C63: =TEXT(B63,"mmm") -> Mar | D63: =TEXT(B63,"yyyy") -> 2024 | E63: 45376 | F63: Delivered | G63: =IF(E63=0,"",E63-B63) -> 10 | H63: CU0103 | I63: =VLOOKUP($H63,Customers!$A$1:$I$721,2,FALSE) -> Nisha Bansal | J63: =VLOOKUP($H63,Customers!$A$1:$I$721,3,FALSE) -> Female | K63: =VLOOKUP($H63,Customers!$A$1:$I$721,4,FALSE) -> 32 | L63: =VLOOKUP($H63,Customers!$A$1:$I$721,5,FALSE) -> Kolkata | M63: =VLOOKUP($H63,Customers!$A$1:$I$721,6,FALSE) -> West Bengal | N63: =VLOOKUP($H63,Customers!$A$1:$I$721,7,FALSE) -> Salaried - Private | O63: =VLOOKUP($H63,Customers!$A$1:$I$721,8,FALSE) -> 890000 | P63: =VLOOKUP($H63,Customers!$A$1:$I$721,9,FALSE) -> Individual | Q63: C001 | R63: {=VLOOKUP($Q63,Cars[],{2,3,4,5,6,7,8,9},FALSE)} -> Maruti Suzuki | S63: Alto K10 | T63: Hatchback | U63: Petrol | V63: Manual | W63: 425000 | X63: 2022 | Y63: 3 | Z63: D013 | AA63: =VLOOKUP(Z63,Dealers[],5,FALSE) -> West | AB63: {=VLOOKUP($Z63,Dealers[],{2,7,8,9},FALSE)} -> Surat Autoplex | AC63: 2010 | AD63: 10000 | AE63: 4.4 | AF63: S041 | AG63: =VLOOKUP($AF63,SalesPerson[],2,FALSE) -> Jatin Kapoor | AH63: =_xlfn.XLOOKUP(AG63,Salespersons!$B:$B,Salespersons!$G:$G,,0) -> 5 | AI63: =_xlfn.XLOOKUP(AG63,Salespersons!$B:$B,Salespersons!$I:$I,,0) -> True | AJ63: Blue | AK63: =AL63/W63 -> 0.049411765 | AL63: 21000 | AM63: =W63-AL63 -> 404000 | AN63: =AM63/100000 -> 4.04 | AO63: Cash | AP63: N/A | AQ63: Referral | AR63: No | AS63: {=VLOOKUP($A63,Feedback[],{2,4,5,6,7},FALSE)} -> FB0032 | AT63: 2 | AU63: 4 | AV63: Online Survey | AW63: Pricing
A64: ORD00063 | B64: 45368 | C64: =TEXT(B64,"mmm") -> Mar | D64: =TEXT(B64,"yyyy") -> 2024 | F64: Cancelled | G64: =IF(E64=0,"",E64-B64) | H64: CU0255 | I64: =VLOOKUP($H64,Customers!$A$1:$I$721,2,FALSE) -> Lokesh Bose | J64: =VLOOKUP($H64,Customers!$A$1:$I$721,3,FALSE) -> Male | K64: =VLOOKUP($H64,Customers!$A$1:$I$721,4,FALSE) -> 26 | L64: =VLOOKUP($H64,Customers!$A$1:$I$721,5,FALSE) -> Bhubaneswar | M64: =VLOOKUP($H64,Customers!$A$1:$I$721,6,FALSE) -> Odisha | N64: =VLOOKUP($H64,Customers!$A$1:$I$721,7,FALSE) -> Retired | O64: =VLOOKUP($H64,Customers!$A$1:$I$721,8,FALSE) -> 940000 | P64: =VLOOKUP($H64,Customers!$A$1:$I$721,9,FALSE) -> Individual | Q64: C009 | R64: {=VLOOKUP($Q64,Cars[],{2,3,4,5,6,7,8,9},FALSE)} -> Hyundai | S64: i20 | T64: Hatchback | U64: Petrol | V64: Automatic | W64: 780000 | X64: 2023 | Y64: 2 | Z64: D021 | AA64: =VLOOKUP(Z64,Dealers[],5,FALSE) -> East | AB64: {=VLOOKUP($Z64,Dealers[],{2,7,8,9},FALSE)} -> Bhubaneswar Motors | AC64: 2008 | AD64: 4500 | AE64: 4.3 | AF64: S064 | AG64: =VLOOKUP($AF64,SalesPerson[],2,FALSE) -> Siddharth Joshi | AH64: =_xlfn.XLOOKUP(AG64,Salespersons!$B:$B,Salespersons!$G:$G,,0) -> 8 | AI64: =_xlfn.XLOOKUP(AG64,Salespersons!$B:$B,Salespersons!$I:$I,,0) -> True | AJ64: Red | AK64: =AL64/W64 -> 0.019230769 | AL64: 15000 | AM64: =W64-AL64 -> 765000 | AN64: =AM64/100000 -> 7.65 | AO64: Loan/Finance | AP64: Mahindra Finance | AQ64: Walk-in | AR64: No | AS64: No Feedback | AT64: No Feedback | AU64: No Feedback | AV64: No Feedback | AW64: No Feedback
A65: ORD00064 | B65: 45369 | C65: =TEXT(B65,"mmm") -> Mar | D65: =TEXT(B65,"yyyy") -> 2024 | E65: 45377 | F65: Delivered | G65: =IF(E65=0,"",E65-B65) -> 8 | H65: CU0649 | I65: =VLOOKUP($H65,Customers!$A$1:$I$721,2,FALSE) -> Mohit Bose | J65: =VLOOKUP($H65,Customers!$A$1:$I$721,3,FALSE) -> Male | K65: =VLOOKUP($H65,Customers!$A$1:$I$721,4,FALSE) -> 21 | L65: =VLOOKUP($H65,Customers!$A$1:$I$721,5,FALSE) -> Guwahati | M65: =VLOOKUP($H65,Customers!$A$1:$I$721,6,FALSE) -> Assam | N65: =VLOOKUP($H65,Customers!$A$1:$I$721,7,FALSE) -> Teacher | O65: =VLOOKUP($H65,Customers!$A$1:$I$721,8,FALSE) -> 650000 | P65: =VLOOKUP($H65,Customers!$A$1:$I$721,9,FALSE) -> Individual | Q65: C008 | R65: {=VLOOKUP($Q65,Cars[],{2,3,4,5,6,7,8,9},FALSE)} -> Hyundai | S65: i10 Nios | T65: Hatchback | U65: Petrol | V65: Manual | W65: 600000 | X65: 2023 | Y65: 3 | Z65: D023 | AA65: =VLOOKUP(Z65,Dealers[],5,FALSE) -> East | AB65: {=VLOOKUP($Z65,Dealers[],{2,7,8,9},FALSE)} -> Guwahati Automobiles | AC65: 2005 | AD65: 12000 | AE65: 4.4 | AF65: S070 | AG65: =VLOOKUP($AF65,SalesPerson[],2,FALSE) -> Tarun Mehta | AH65: =_xlfn.XLOOKUP(AG65,Salespersons!$B:$B,Salespersons!$G:$G,,0) -> 4 | AI65: =_xlfn.XLOOKUP(AG65,Salespersons!$B:$B,Salespersons!$I:$I,,0) -> True | AJ65: Black | AK65: =AL65/W65 -> 0 | AL65: 0 | AM65: =W65-AL65 -> 600000 | AN65: =AM65/100000 -> 6 | AO65: Exchange + Loan | AP65: Mahindra Finance | AQ65: Social Media | AR65: No | AS65: No Feedback | AT65: No Feedback | AU65: No Feedback | AV65: No Feedback | AW65: No Feedback
A66: ORD00065 | B66: 45370 | C66: =TEXT(B66,"mmm") -> Mar | D66: =TEXT(B66,"yyyy") -> 2024 | E66: 45405 | F66: Delivered | G66: =IF(E66=0,"",E66-B66) -> 35 | H66: CU0717 | I66: =VLOOKUP($H66,Customers!$A$1:$I$721,2,FALSE) -> Lokesh Yadav | J66: =VLOOKUP($H66,Customers!$A$1:$I$721,3,FALSE) -> Male | K66: =VLOOKUP($H66,Customers!$A$1:$I$721,4,FALSE) -> 43 | L66: =VLOOKUP($H66,Customers!$A$1:$I$721,5,FALSE) -> Noida | M66: =VLOOKUP($H66,Customers!$A$1:$I$721,6,FALSE) -> Uttar Pradesh | N66: =VLOOKUP($H66,Customers!$A$1:$I$721,7,FALSE) -> Salaried - Private | O66: =VLOOKUP($H66,Customers!$A$1:$I$721,8,FALSE) -> 1510000 | P66: =VLOOKUP($H66,Customers!$A$1:$I$721,9,FALSE) -> Individual | Q66: C032 | R66: {=VLOOKUP($Q66,Cars[],{2,3,4,5,6,7,8,9},FALSE)} -> Kia | S66: Carens | T66: MPV | U66: Diesel | V66: Manual | W66: 1200000 | X66: 2022 | Y66: 3 | Z66: D008 | AA66: =VLOOKUP(Z66,Dealers[],5,FALSE) -> North | AB66: {=VLOOKUP($Z66,Dealers[],{2,7,8,9},FALSE)} -> Noida Car World | AC66: 2007 | AD66: 10000 | AE66: 3.8 | AF66: S023 | AG66: =VLOOKUP($AF66,SalesPerson[],2,FALSE) -> Kunal Jain | AH66: =_xlfn.XLOOKUP(AG66,Salespersons!$B:$B,Salespersons!$G:$G,,0) -> 8 | AI66: =_xlfn.XLOOKUP(AG66,Salespersons!$B:$B,Salespersons!$I:$I,,0) -> True | AJ66: White | AK66: =AL66/W66 -> 0.033333333 | AL66: 40000 | AM66: =W66-AL66 -> 1160000 | AN66: =AM66/100000 -> 11.6 | AO66: Cash | AP66: N/A | AQ66: Social Media | AR66: Yes | AS66: {=VLOOKUP($A66,Feedback[],{2,4,5,6,7},FALSE)} -> FB0033 | AT66: 5 | AU66: 8 | AV66: Email | AW66: None
A67: ORD00066 | B67: 45372 | C67: =TEXT(B67,"mmm") -> Mar | D67: =TEXT(B67,"yyyy") -> 2024 | E67: 45390 | F67: Delivered | G67: =IF(E67=0,"",E67-B67) -> 18 | H67: CU0309 | I67: =VLOOKUP($H67,Customers!$A$1:$I$721,2,FALSE) -> Ravi Singh | J67: =VLOOKUP($H67,Customers!$A$1:$I$721,3,FALSE) -> Male | K67: =VLOOKUP($H67,Customers!$A$1:$I$721,4,FALSE) -> 31 | L67: =VLOOKUP($H67,Customers!$A$1:$I$721,5,FALSE) -> Bhubaneswar | M67: =VLOOKUP($H67,Customers!$A$1:$I$721,6,FALSE) -> Odisha | N67: =VLOOKUP($H67,Customers!$A$1:$I$721,7,FALSE) -> Teacher | O67: =VLOOKUP($H67,Customers!$A$1:$I$721,8,FALSE) -> 590000 | P67: =VLOOKUP($H67,Customers!$A$1:$I$721,9,FALSE) -> Individual | Q67: C029 | R67: {=VLOOKUP($Q67,Cars[],{2,3,4,5,6,7,8,9},FALSE)} -> Honda | S67: Amaze | T67: Sedan | U67: Petrol | V67: Manual | W67: 800000 | X67: 2024 | Y67: 3 | Z67: D015 | AA67: =VLOOKUP(Z67,Dealers[],5,FALSE) -> South | AB67: {=VLOOKUP($Z67,Dealers[],{2,7,8,9},FALSE)} -> Mysuru Auto Hub | AC67: 2006 | AD67: 4500 | AE67: 4.6 | AF67: S045 | AG67: =VLOOKUP($AF67,SalesPerson[],2,FALSE) -> Divya Jain | AH67: =_xlfn.XLOOKUP(AG67,Salespersons!$B:$B,Salespersons!$G:$G,,0) -> 7 | AI67: =_xlfn.XLOOKUP(AG67,Salespersons!$B:$B,Salespersons!$I:$I,,0) -> True | AJ67: White | AK67: =AL67/W67 -> 0.02 | AL67: 16000 | AM67: =W67-AL67 -> 784000 | AN67: =AM67/100000 -> 7.84 | AO67: Exchange + Loan | AP67: Mahindra Finance | AQ67: Auto Expo/Event | AR67: No | AS67: No Feedback | AT67: No Feedback | AU67: No Feedback | AV67: No Feedback | AW67: No Feedback
A68: ORD00067 | B68: 45372 | C68: =TEXT(B68,"mmm") -> Mar | D68: =TEXT(B68,"yyyy") -> 2024 | E68: 45405 | F68: Delivered | G68: =IF(E68=0,"",E68-B68) -> 33 | H68: CU0717 | I68: =VLOOKUP($H68,Customers!$A$1:$I$721,2,FALSE) -> Lokesh Yadav | J68: =VLOOKUP($H68,Customers!$A$1:$I$721,3,FALSE) -> Male | K68: =VLOOKUP($H68,Customers!$A$1:$I$721,4,FALSE) -> 43 | L68: =VLOOKUP($H68,Customers!$A$1:$I$721,5,FALSE) -> Noida | M68: =VLOOKUP($H68,Customers!$A$1:$I$721,6,FALSE) -> Uttar Pradesh | N68: =VLOOKUP($H68,Customers!$A$1:$I$721,7,FALSE) -> Salaried - Private | O68: =VLOOKUP($H68,Customers!$A$1:$I$721,8,FALSE) -> 1510000 | P68: =VLOOKUP($H68,Customers!$A$1:$I$721,9,FALSE) -> Individual | Q68: C002 | R68: {=VLOOKUP($Q68,Cars[],{2,3,4,5,6,7,8,9},FALSE)} -> Maruti Suzuki | S68: Swift | T68: Hatchback | U68: Petrol | V68: Manual | W68: 650000 | X68: 2024 | Y68: 3 | Z68: D007 | AA68: =VLOOKUP(Z68,Dealers[],5,FALSE) -> North | AB68: {=VLOOKUP($Z68,Dealers[],{2,7,8,9},FALSE)} -> Lucknow Motors | AC68: 2013 | AD68: 3000 | AE68: 4.4 | AF68: S020 | AG68: =VLOOKUP($AF68,SalesPerson[],2,FALSE) -> Tarun Patel | AH68: =_xlfn.XLOOKUP(AG68,Salespersons!$B:$B,Salespersons!$G:$G,,0) -> 4 | AI68: =_xlfn.XLOOKUP(AG68,Salespersons!$B:$B,Salespersons!$I:$I,,0) -> True | AJ68: Orange | AK68: =AL68/W68 -> 0.0092307692 | AL68: 6000 | AM68: =W68-AL68 -> 644000 | AN68: =AM68/100000 -> 6.44 | AO68: Loan/Finance | AP68: SBI | AQ68: Corporate Tie-up | AR68: Yes | AS68: No Feedback | AT68: No Feedback | AU68: No Feedback | AV68: No Feedback | AW68: No Feedback
A69: ORD00068 | B69: 45375 | C69: =TEXT(B69,"mmm") -> Mar | D69: =TEXT(B69,"yyyy") -> 2024 | E69: 45382 | F69: Delivered | G69: =IF(E69=0,"",E69-B69) -> 7 | H69: CU0682 | I69: =VLOOKUP($H69,Customers!$A$1:$I$721,2,FALSE) -> Harsh Shah | J69: =VLOOKUP($H69,Customers!$A$1:$I$721,3,FALSE) -> Male | K69: =VLOOKUP($H69,Customers!$A$1:$I$721,4,FALSE) -> 27 | L69: =VLOOKUP($H69,Customers!$A$1:$I$721,5,FALSE) -> Noida | M69: =VLOOKUP($H69,Customers!$A$1:$I$721,6,FALSE) -> Uttar Pradesh | N69: =VLOOKUP($H69,Customers!$A$1:$I$721,7,FALSE) -> Salaried - Government | O69: =VLOOKUP($H69,Customers!$A$1:$I$721,8,FALSE) -> 700000 | P69: =VLOOKUP($H69,Customers!$A$1:$I$721,9,FALSE) -> Individual | Q69: C003 | R69: {=VLOOKUP($Q69,Cars[],{2,3,4,5,6,7,8,9},FALSE)} -> Maruti Suzuki | S69: Baleno | T69: Hatchback | U69: Petrol | V69: Automatic | W69: 760000 | X69: 2022 | Y69: 2 | Z69: D008 | AA69: =VLOOKUP(Z69,Dealers[],5,FALSE) -> North | AB69: {=VLOOKUP($Z69,Dealers[],{2,7,8,9},FALSE)} -> Noida Car World | AC69: 2007 | AD69: 10000 | AE69: 3.8 | AF69: S022 | AG69: =VLOOKUP($AF69,SalesPerson[],2,FALSE) -> Ankit Malhotra | AH69: =_xlfn.XLOOKUP(AG69,Salespersons!$B:$B,Salespersons!$G:$G,,0) -> 6 | AI69: =_xlfn.XLOOKUP(AG69,Salespersons!$B:$B,Salespersons!$I:$I,,0) -> True | AJ69: Grey | AK69: =AL69/W69 -> 0.047368421 | AL69: 36000 | AM69: =W69-AL69 -> 724000 | AN69: =AM69/100000 -> 7.24 | AO69: Cash | AP69: N/A | AQ69: Social Media | AR69: No | AS69: No Feedback | AT69: No Feedback | AU69: No Feedback | AV69: No Feedback | AW69: No Feedback
A70: ORD00069 | B70: 45375 | C70: =TEXT(B70,"mmm") -> Mar | D70: =TEXT(B70,"yyyy") -> 2024 | E70: 45399 | F70: Delivered | G70: =IF(E70=0,"",E70-B70) -> 24 | H70: CU0391 | I70: =VLOOKUP($H70,Customers!$A$1:$I$721,2,FALSE) -> Mohit Yadav | J70: =VLOOKUP($H70,Customers!$A$1:$I$721,3,FALSE) -> Male | K70: =VLOOKUP($H70,Customers!$A$1:$I$721,4,FALSE) -> 29 | L70: =VLOOKUP($H70,Customers!$A$1:$I$721,5,FALSE) -> Mumbai | M70: =VLOOKUP($H70,Customers!$A$1:$I$721,6,FALSE) -> Maharashtra | N70: =VLOOKUP($H70,Customers!$A$1:$I$721,7,FALSE) -> Farmer | O70: =VLOOKUP($H70,Customers!$A$1:$I$721,8,FALSE) -> 750000 | P70: =VLOOKUP($H70,Customers!$A$1:$I$721,9,FALSE) -> Individual | Q70: C017 | R70: {=VLOOKUP($Q70,Cars[],{2,3,4,5,6,7,8,9},FALSE)} -> Tata | S70: Harrier | T70: SUV | U70: Diesel | V70: Automatic | W70: 1550000 | X70: 2023 | Y70: 2 | Z70: D010 | AA70: =VLOOKUP(Z70,Dealers[],5,FALSE) -> West | AB70: {=VLOOKUP($Z70,Dealers[],{2,7,8,9},FALSE)} -> Pune Autoplex | AC70: 2014 | AD70: 3000 | AE70: 4.6 | AF70: S031 | AG70: =VLOOKUP($AF70,SalesPerson[],2,FALSE) -> Ankit Verma | AH70: =_xlfn.XLOOKUP(AG70,Salespersons!$B:$B,Salespersons!$G:$G,,0) -> 4 | AI70: =_xlfn.XLOOKUP(AG70,Salespersons!$B:$B,Salespersons!$I:$I,,0) -> True | AJ70: Grey | AK70: =AL70/W70 -> 0 | AL70: 0 | AM70: =W70-AL70 -> 1550000 | AN70: =AM70/100000 -> 15.5 | AO70: Loan/Finance | AP70: HDFC Bank | AQ70: Online Website | AR70: No | AS70: No Feedback | AT70: No Feedback | AU70: No Feedback | AV70: No Feedback | AW70: No Feedback
A71: ORD00070 | B71: 45380 | C71: =TEXT(B71,"mmm") -> Mar | D71: =TEXT(B71,"yyyy") -> 2024 | E71: 45395 | F71: Delivered | G71: =IF(E71=0,"",E71-B71) -> 15 | H71: CU0119 | I71: =VLOOKUP($H71,Customers!$A$1:$I$721,2,FALSE) -> Imran Iyer | J71: =VLOOKUP($H71,Customers!$A$1:$I$721,3,FALSE) -> Male | K71: =VLOOKUP($H71,Customers!$A$1:$I$721,4,FALSE) -> 44 | L71: =VLOOKUP($H71,Customers!$A$1:$I$721,5,FALSE) -> Chandigarh | M71: =VLOOKUP($H71,Customers!$A$1:$I$721,6,FALSE) -> Chandigarh | N71: =VLOOKUP($H71,Customers!$A$1:$I$721,7,FALSE) -> Business Owner | O71: =VLOOKUP($H71,Customers!$A$1:$I$721,8,FALSE) -> 3220000 | P71: =VLOOKUP($H71,Customers!$A$1:$I$721,9,FALSE) -> Corporate | Q71: C015 | R71: {=VLOOKUP($Q71,Cars[],{2,3,4,5,6,7,8,9},FALSE)} -> Tata | S71: Punch | T71: SUV | U71: Petrol | V71: Manual | W71: 650000 | X71: 2021 | Y71: 3 | Z71: D004 | AA71: =VLOOKUP(Z71,Dealers[],5,FALSE) -> North | AB71: {=VLOOKUP($Z71,Dealers[],{2,7,8,9},FALSE)} -> Chandigarh Car World | AC71: 2018 | AD71: 4500 | AE71: 4 | AF71: S013 | AG71: =VLOOKUP($AF71,SalesPerson[],2,FALSE) -> Yash Shah | AH71: =_xlfn.XLOOKUP(AG71,Salespersons!$B:$B,Salespersons!$G:$G,,0) -> 7 | AI71: =_xlfn.XLOOKUP(AG71,Salespersons!$B:$B,Salespersons!$I:$I,,0) -> True | AJ71: Red | AK71: =AL71/W71 -> 0.027692308 | AL71: 18000 | AM71: =W71-AL71 -> 632000 | AN71: =AM71/100000 -> 6.32 | AO71: Lease (Corporate) | AP71: HDFC Bank | AQ71: Social Media | AR71: No | AS71: No Feedback | AT71: No Feedback | AU71: No Feedback | AV71: No Feedback | AW71: No Feedback
A72: ORD00071 | B72: 45380 | C72: =TEXT(B72,"mmm") -> Mar | D72: =TEXT(B72,"yyyy") -> 2024 | E72: 45403 | F72: Delivered | G72: =IF(E72=0,"",E72-B72) -> 23 | H72: CU0374 | I72: =VLOOKUP($H72,Customers!$A$1:$I$721,2,FALSE) -> Sandeep Chauhan | J72: =VLOOKUP($H72,Customers!$A$1:$I$721,3,FALSE) -> Male | K72: =VLOOKUP($H72,Customers!$A$1:$I$721,4,FALSE) -> 55 | L72: =VLOOKUP($H72,Customers!$A$1:$I$721,5,FALSE) -> Kolkata | M72: =VLOOKUP($H72,Customers!$A$1:$I$721,6,FALSE) -> West Bengal | N72: =VLOOKUP($H72,Customers!$A$1:$I$721,7,FALSE) -> Farmer | O72: =VLOOKUP($H72,Customers!$A$1:$I$721,8,FALSE) -> 720000 | P72: =VLOOKUP($H72,Customers!$A$1:$I$721,9,FALSE) -> Individual | Q72: C027 | R72: {=VLOOKUP($Q72,Cars[],{2,3,4,5,6,7,8,9},FALSE)} -> Toyota | S72: Urban Cruiser Hyryder | T72: SUV | U72: Hybrid | V72: Automatic | W72: 1350000 | X72: 2022 | Y72: 5 | Z72: D005 | AA72: =VLOOKUP(Z72,Dealers[],5,FALSE) -> North | AB72: {=VLOOKUP($Z72,Dealers[],{2,7,8,9},FALSE)} -> Ludhiana Wheels | AC72: 2010 | AD72: 12000 | AE72: 4 | AF72: S014 | AG72: =VLOOKUP($AF72,SalesPerson[],2,FALSE) -> Harsh Nair | AH72: =_xlfn.XLOOKUP(AG72,Salespersons!$B:$B,Salespersons!$G:$G,,0) -> 8 | AI72: =_xlfn.XLOOKUP(AG72,Salespersons!$B:$B,Salespersons!$I:$I,,0) -> True | AJ72: White | AK72: =AL72/W72 -> 0 | AL72: 0 | AM72: =W72-AL72 -> 1350000 | AN72: =AM72/100000 -> 13.5 | AO72: Cash | AP72: N/A | AQ72: Referral | AR72: Yes | AS72: No Feedback | AT72: No Feedback | AU72: No Feedback | AV72: No Feedback | AW72: No Feedback
A73: ORD00072 | B73: 45381 | C73: =TEXT(B73,"mmm") -> Mar | D73: =TEXT(B73,"yyyy") -> 2024 | E73: 45416 | F73: Delivered | G73: =IF(E73=0,"",E73-B73) -> 35 | H73: CU0512 | I73: =VLOOKUP($H73,Customers!$A$1:$I$721,2,FALSE) -> Pradeep Mishra | J73: =VLOOKUP($H73,Customers!$A$1:$I$721,3,FALSE) -> Male | K73: =VLOOKUP($H73,Customers!$A$1:$I$721,4,FALSE) -> 47 | L73: =VLOOKUP($H73,Customers!$A$1:$I$721,5,FALSE) -> Ludhiana | M73: =VLOOKUP($H73,Customers!$A$1:$I$721,6,FALSE) -> Punjab | N73: =VLOOKUP($H73,Customers!$A$1:$I$721,7,FALSE) -> Business Owner | O73: =VLOOKUP($H73,Customers!$A$1:$I$721,8,FALSE) -> 3240000 | P73: =VLOOKUP($H73,Customers!$A$1:$I$721,9,FALSE) -> Corporate | Q73: C020 | R73: {=VLOOKUP($Q73,Cars[],{2,3,4,5,6,7,8,9},FALSE)} -> Mahindra | S73: Thar | T73: SUV | U73: Diesel | V73: Manual | W73: 1250000 | X73: 2020 | Y73: 2 | Z73: D005 | AA73: =VLOOKUP(Z73,Dealers[],5,FALSE) -> North | AB73: {=VLOOKUP($Z73,Dealers[],{2,7,8,9},FALSE)} -> Ludhiana Wheels | AC73: 2010 | AD73: 12000 | AE73: 4 | AF73: S014 | AG73: =VLOOKUP($AF73,SalesPerson[],2,FALSE) -> Harsh Nair | AH73: =_xlfn.XLOOKUP(AG73,Salespersons!$B:$B,Salespersons!$G:$G,,0) -> 8 | AI73: =_xlfn.XLOOKUP(AG73,Salespersons!$B:$B,Salespersons!$I:$I,,0) -> True | AJ73: Brown | AK73: =AL73/W73 -> 0.0376 | AL73: 47000 | AM73: =W73-AL73 -> 1203000 | AN73: =AM73/100000 -> 12.03 | AO73: Lease (Corporate) | AP73: Bajaj Finserv | AQ73: Walk-in | AR73: No | AS73: {=VLOOKUP($A73,Feedback[],{2,4,5,6,7},FALSE)} -> FB0034 | AT73: 2 | AU73: 3 | AV73: Email | AW73: Vehicle Quality
A74: ORD00073 | B74: 45382 | C74: =TEXT(B74,"mmm") -> Mar | D74: =TEXT(B74,"yyyy") -> 2024 | E74: 45398 | F74: Delivered | G74: =IF(E74=0,"",E74-B74) -> 16 | H74: CU0588 | I74: =VLOOKUP($H74,Customers!$A$1:$I$721,2,FALSE) -> Aman Shah | J74: =VLOOKUP($H74,Customers!$A$1:$I$721,3,FALSE) -> Male | K74: =VLOOKUP($H74,Customers!$A$1:$I$721,4,FALSE) -> 62 | L74: =VLOOKUP($H74,Customers!$A$1:$I$721,5,FALSE) -> Panipat | M74: =VLOOKUP($H74,Customers!$A$1:$I$721,6,FALSE) -> Haryana | N74: =VLOOKUP($H74,Customers!$A$1:$I$721,7,FALSE) -> Salaried - Private | O74: =VLOOKUP($H74,Customers!$A$1:$I$721,8,FALSE) -> 1400000 | P74: =VLOOKUP($H74,Customers!$A$1:$I$721,9,FALSE) -> Individual | Q74: C012 | R74: {=VLOOKUP($Q74,Cars[],{2,3,4,5,6,7,8,9},FALSE)} -> Hyundai | S74: Verna | T74: Sedan | U74: Petrol | V74: Automatic | W74: 1100000 | X74: 2023 | Y74: 2 | Z74: D003 | AA74: =VLOOKUP(Z74,Dealers[],5,FALSE) -> North | AB74: {=VLOOKUP($Z74,Dealers[],{2,7,8,9},FALSE)} -> Panipat Motors | AC74: 2012 | AD74: 10000 | AE74: 4.2 | AF74: S010 | AG74: =VLOOKUP($AF74,SalesPerson[],2,FALSE) -> Rahul Rao | AH74: =_xlfn.XLOOKUP(AG74,Salespersons!$B:$B,Salespersons!$G:$G,,0) -> 5 | AI74: =_xlfn.XLOOKUP(AG74,Salespersons!$B:$B,Salespersons!$I:$I,,0) -> True | AJ74: Red | AK74: =AL74/W74 -> 0.04 | AL74: 44000 | AM74: =W74-AL74 -> 1056000 | AN74: =AM74/100000 -> 10.56 | AO74: Loan/Finance | AP74: Tata Capital | AQ74: Auto Expo/Event | AR74: Yes | AS74: {=VLOOKUP($A74,Feedback[],{2,4,5,6,7},FALSE)} -> FB0035 | AT74: 3 | AU74: 5 | AV74: Dealer Visit | AW74: Vehicle Quality
A75: ORD00074 | B75: 45383 | C75: =TEXT(B75,"mmm") -> Apr | D75: =TEXT(B75,"yyyy") -> 2024 | F75: Cancelled | G75: =IF(E75=0,"",E75-B75) | H75: CU0718 | I75: =VLOOKUP($H75,Customers!$A$1:$I$721,2,FALSE) -> Kamal Chauhan | J75: =VLOOKUP($H75,Customers!$A$1:$I$721,3,FALSE) -> Male | K75: =VLOOKUP($H75,Customers!$A$1:$I$721,4,FALSE) -> 42 | L75: =VLOOKUP($H75,Customers!$A$1:$I$721,5,FALSE) -> Bhubaneswar | M75: =VLOOKUP($H75,Customers!$A$1:$I$721,6,FALSE) -> Odisha | N75: =VLOOKUP($H75,Customers!$A$1:$I$721,7,FALSE) -> Farmer | O75: =VLOOKUP($H75,Customers!$A$1:$I$721,8,FALSE) -> 390000 | P75: =VLOOKUP($H75,Customers!$A$1:$I$721,9,FALSE) -> Individual | Q75: C016 | R75: {=VLOOKUP($Q75,Cars[],{2,3,4,5,6,7,8,9},FALSE)} -> Tata | S75: Nexon | T75: SUV | U75: Diesel | V75: Manual | W75: 950000 | X75: 2023 | Y75: 3 | Z75: D025 | AA75: =VLOOKUP(Z75,Dealers[],5,FALSE) -> Central | AB75: {=VLOOKUP($Z75,Dealers[],{2,7,8,9},FALSE)} -> Indore Wheels | AC75: 2019 | AD75: 3000 | AE75: 4.7 | AF75: S075 | AG75: =VLOOKUP($AF75,SalesPerson[],2,FALSE) -> Tanvi Shah | AH75: =_xlfn.XLOOKUP(AG75,Salespersons!$B:$B,Salespersons!$G:$G,,0) -> 4 | AI75: =_xlfn.XLOOKUP(AG75,Salespersons!$B:$B,Salespersons!$I:$I,,0) -> True | AJ75: Grey | AK75: =AL75/W75 -> 0.045263158 | AL75: 43000 | AM75: =W75-AL75 -> 907000 | AN75: =AM75/100000 -> 9.07 | AO75: Exchange + Loan | AP75: ICICI Bank | AQ75: Auto Expo/Event | AR75: No | AS75: No Feedback | AT75: No Feedback | AU75: No Feedback | AV75: No Feedback | AW75: No Feedback
A76: ORD00075 | B76: 45386 | C76: =TEXT(B76,"mmm") -> Apr | D76: =TEXT(B76,"yyyy") -> 2024 | E76: 45393 | F76: Delivered | G76: =IF(E76=0,"",E76-B76) -> 7 | H76: CU0164 | I76: =VLOOKUP($H76,Customers!$A$1:$I$721,2,FALSE) -> Komal Saini | J76: =VLOOKUP($H76,Customers!$A$1:$I$721,3,FALSE) -> Female | K76: =VLOOKUP($H76,Customers!$A$1:$I$721,4,FALSE) -> 65 | L76: =VLOOKUP($H76,Customers!$A$1:$I$721,5,FALSE) -> Hyderabad | M76: =VLOOKUP($H76,Customers!$A$1:$I$721,6,FALSE) -> Telangana | N76: =VLOOKUP($H76,Customers!$A$1:$I$721,7,FALSE) -> Engineer | O76: =VLOOKUP($H76,Customers!$A$1:$I$721,8,FALSE) -> 2010000 | P76: =VLOOKUP($H76,Customers!$A$1:$I$721,9,FALSE) -> Individual | Q76: C037 | R76: {=VLOOKUP($Q76,Cars[],{2,3,4,5,6,7,8,9},FALSE)} -> Renault | S76: Kiger | T76: SUV | U76: Petrol | V76: Manual | W76: 700000 | X76: 2021 | Y76: 4 | Z76: D018 | AA76: =VLOOKUP(Z76,Dealers[],5,FALSE) -> South | AB76: {=VLOOKUP($Z76,Dealers[],{2,7,8,9},FALSE)} -> Hyderabad Automobiles | AC76: 2019 | AD76: 4500 | AE76: 3.8 | AF76: S054 | AG76: =VLOOKUP($AF76,SalesPerson[],2,FALSE) -> Gaurav Shah | AH76: =_xlfn.XLOOKUP(AG76,Salespersons!$B:$B,Salespersons!$G:$G,,0) -> 4 | AI76: =_xlfn.XLOOKUP(AG76,Salespersons!$B:$B,Salespersons!$I:$I,,0) -> True | AJ76: Silver | AK76: =AL76/W76 -> 0.035714286 | AL76: 25000 | AM76: =W76-AL76 -> 675000 | AN76: =AM76/100000 -> 6.75 | AO76: Loan/Finance | AP76: Tata Capital | AQ76: Referral | AR76: No | AS76: {=VLOOKUP($A76,Feedback[],{2,4,5,6,7},FALSE)} -> FB0036 | AT76: 5 | AU76: 10 | AV76: Email | AW76: None
A77: ORD00076 | B77: 45387 | C77: =TEXT(B77,"mmm") -> Apr | D77: =TEXT(B77,"yyyy") -> 2024 | E77: 45393 | F77: Delivered | G77: =IF(E77=0,"",E77-B77) -> 6 | H77: CU0714 | I77: =VLOOKUP($H77,Customers!$A$1:$I$721,2,FALSE) -> Nisha Mishra | J77: =VLOOKUP($H77,Customers!$A$1:$I$721,3,FALSE) -> Female | K77: =VLOOKUP($H77,Customers!$A$1:$I$721,4,FALSE) -> 21 | L77: =VLOOKUP($H77,Customers!$A$1:$I$721,5,FALSE) -> Indore | M77: =VLOOKUP($H77,Customers!$A$1:$I$721,6,FALSE) -> Madhya Pradesh | N77: =VLOOKUP($H77,Customers!$A$1:$I$721,7,FALSE) -> Farmer | O77: =VLOOKUP($H77,Customers!$A$1:$I$721,8,FALSE) -> 820000 | P77: =VLOOKUP($H77,Customers!$A$1:$I$721,9,FALSE) -> Individual | Q77: C033 | R77: {=VLOOKUP($Q77,Cars[],{2,3,4,5,6,7,8,9},FALSE)} -> Skoda | S77: Slavia | T77: Sedan | U77: Petrol | V77: Automatic | W77: 1300000 | X77: 2022 | Y77: 3 | Z77: D025 | AA77: =VLOOKUP(Z77,Dealers[],5,FALSE) -> Central | AB77: {=VLOOKUP($Z77,Dealers[],{2,7,8,9},FALSE)} -> Indore Wheels | AC77: 2019 | AD77: 3000 | AE77: 4.7 | AF77: S074 | AG77: =VLOOKUP($AF77,SalesPerson[],2,FALSE) -> Kunal Shah | AH77: =_xlfn.XLOOKUP(AG77,Salespersons!$B:$B,Salespersons!$G:$G,,0) -> 8 | AI77: =_xlfn.XLOOKUP(AG77,Salespersons!$B:$B,Salespersons!$I:$I,,0) -> True | AJ77: Red | AK77: =AL77/W77 -> 0 | AL77: 0 | AM77: =W77-AL77 -> 1300000 | AN77: =AM77/100000 -> 13 | AO77: Cash | AP77: N/A | AQ77: Corporate Tie-up | AR77: No | AS77: No Feedback | AT77: No Feedback | AU77: No Feedback | AV77: No Feedback | AW77: No Feedback
A78: ORD00077 | B78: 45387 | C78: =TEXT(B78,"mmm") -> Apr | D78: =TEXT(B78,"yyyy") -> 2024 | E78: 45402 | F78: Delivered | G78: =IF(E78=0,"",E78-B78) -> 15 | H78: CU0469 | I78: =VLOOKUP($H78,Customers!$A$1:$I$721,2,FALSE) -> Varun Malhotra | J78: =VLOOKUP($H78,Customers!$A$1:$I$721,3,FALSE) -> Male | K78: =VLOOKUP($H78,Customers!$A$1:$I$721,4,FALSE) -> 36 | L78: =VLOOKUP($H78,Customers!$A$1:$I$721,5,FALSE) -> Pune | M78: =VLOOKUP($H78,Customers!$A$1:$I$721,6,FALSE) -> Maharashtra | N78: =VLOOKUP($H78,Customers!$A$1:$I$721,7,FALSE) -> Farmer | O78: =VLOOKUP($H78,Customers!$A$1:$I$721,8,FALSE) -> 820000 | P78: =VLOOKUP($H78,Customers!$A$1:$I$721,9,FALSE) -> Individual | Q78: C017 | R78: {=VLOOKUP($Q78,Cars[],{2,3,4,5,6,7,8,9},FALSE)} -> Tata | S78: Harrier | T78: SUV | U78: Diesel | V78: Automatic | W78: 1550000 | X78: 2023 | Y78: 2 | Z78: D010 | AA78: =VLOOKUP(Z78,Dealers[],5,FALSE) -> West | AB78: {=VLOOKUP($Z78,Dealers[],{2,7,8,9},FALSE)} -> Pune Autoplex | AC78: 2014 | AD78: 3000 | AE78: 4.6 | AF78: S033 | AG78: =VLOOKUP($AF78,SalesPerson[],2,FALSE) -> Shweta Mishra | AH78: =_xlfn.XLOOKUP(AG78,Salespersons!$B:$B,Salespersons!$G:$G,,0) -> 5 | AI78: =_xlfn.XLOOKUP(AG78,Salespersons!$B:$B,Salespersons!$I:$I,,0) -> True | AJ78: Grey | AK78: =AL78/W78 -> 0.0096774194 | AL78: 15000 | AM78: =W78-AL78 -> 1535000 | AN78: =AM78/100000 -> 15.35 | AO78: Cash | AP78: N/A | AQ78: Walk-in | AR78: No | AS78: {=VLOOKUP($A78,Feedback[],{2,4,5,6,7},FALSE)} -> FB0037 | AT78: 5 | AU78: 10 | AV78: Phone | AW78: None
A79: ORD00078 | B79: 45387 | C79: =TEXT(B79,"mmm") -> Apr | D79: =TEXT(B79,"yyyy") -> 2024 | E79: 45396 | F79: Delivered | G79: =IF(E79=0,"",E79-B79) -> 9 | H79: CU0590 | I79: =VLOOKUP($H79,Customers!$A$1:$I$721,2,FALSE) -> Mahesh Jain | J79: =VLOOKUP($H79,Customers!$A$1:$I$721,3,FALSE) -> Male | K79: =VLOOKUP($H79,Customers!$A$1:$I$721,4,FALSE) -> 26 | L79: =VLOOKUP($H79,Customers!$A$1:$I$721,5,FALSE) -> Indore | M79: =VLOOKUP($H79,Customers!$A$1:$I$721,6,FALSE) -> Madhya Pradesh | N79: =VLOOKUP($H79,Customers!$A$1:$I$721,7,FALSE) -> Salaried - Private | O79: =VLOOKUP($H79,Customers!$A$1:$I$721,8,FALSE) -> 1070000 | P79: =VLOOKUP($H79,Customers!$A$1:$I$721,9,FALSE) -> Individual | Q79: C003 | R79: {=VLOOKUP($Q79,Cars[],{2,3,4,5,6,7,8,9},FALSE)} -> Maruti Suzuki | S79: Baleno | T79: Hatchback | U79: Petrol | V79: Automatic | W79: 760000 | X79: 2022 | Y79: 2 | Z79: D024 | AA79: =VLOOKUP(Z79,Dealers[],5,FALSE) -> Central | AB79: {=VLOOKUP($Z79,Dealers[],{2,7,8,9},FALSE)} -> Bhopal Autoplex | AC79: 2013 | AD79: 12000 | AE79: 3.9 | AF79: S072 | AG79: =VLOOKUP($AF79,SalesPerson[],2,FALSE) -> Priya Saini | AH79: =_xlfn.XLOOKUP(AG79,Salespersons!$B:$B,Salespersons!$G:$G,,0) -> 4 | AI79: =_xlfn.XLOOKUP(AG79,Salespersons!$B:$B,Salespersons!$I:$I,,0) -> True | AJ79: Black | AK79: =AL79/W79 -> 0.018421053 | AL79: 14000 | AM79: =W79-AL79 -> 746000 | AN79: =AM79/100000 -> 7.46 | AO79: Cash | AP79: N/A | AQ79: Social Media | AR79: Yes | AS79: No Feedback | AT79: No Feedback | AU79: No Feedback | AV79: No Feedback | AW79: No Feedback
A80: ORD00079 | B80: 45388 | C80: =TEXT(B80,"mmm") -> Apr | D80: =TEXT(B80,"yyyy") -> 2024 | E80: 45406 | F80: Delivered | G80: =IF(E80=0,"",E80-B80) -> 18 | H80: CU0054 | I80: =VLOOKUP($H80,Customers!$A$1:$I$721,2,FALSE) -> Vinod Agarwal | J80: =VLOOKUP($H80,Customers!$A$1:$I$721,3,FALSE) -> Male | K80: =VLOOKUP($H80,Customers!$A$1:$I$721,4,FALSE) -> 37 | L80: =VLOOKUP($H80,Customers!$A$1:$I$721,5,FALSE) -> Bhopal | M80: =VLOOKUP($H80,Customers!$A$1:$I$721,6,FALSE) -> Madhya Pradesh | N80: =VLOOKUP($H80,Customers!$A$1:$I$721,7,FALSE) -> Doctor | O80: =VLOOKUP($H80,Customers!$A$1:$I$721,8,FALSE) -> 3850000 | P80: =VLOOKUP($H80,Customers!$A$1:$I$721,9,FALSE) -> Individual | Q80: C003 | R80: {=VLOOKUP($Q80,Cars[],{2,3,4,5,6,7,8,9},FALSE)} -> Maruti Suzuki | S80: Baleno | T80: Hatchback | U80: Petrol | V80: Automatic | W80: 760000 | X80: 2022 | Y80: 2 | Z80: D025 | AA80: =VLOOKUP(Z80,Dealers[],5,FALSE) -> Central | AB80: {=VLOOKUP($Z80,Dealers[],{2,7,8,9},FALSE)} -> Indore Wheels | AC80: 2019 | AD80: 3000 | AE80: 4.7 | AF80: S077 | AG80: =VLOOKUP($AF80,SalesPerson[],2,FALSE) -> Faisal Shah | AH80: =_xlfn.XLOOKUP(AG80,Salespersons!$B:$B,Salespersons!$G:$G,,0) -> 6 | AI80: =_xlfn.XLOOKUP(AG80,Salespersons!$B:$B,Salespersons!$I:$I,,0) -> True | AJ80: Black | AK80: =AL80/W80 -> 0 | AL80: 0 | AM80: =W80-AL80 -> 760000 | AN80: =AM80/100000 -> 7.6 | AO80: Exchange + Loan | AP80: SBI | AQ80: Referral | AR80: No | AS80: {=VLOOKUP($A80,Feedback[],{2,4,5,6,7},FALSE)} -> FB0038 | AT80: 5 | AU80: 9 | AV80: Phone | AW80: None
A81: ORD00080 | B81: 45388 | C81: =TEXT(B81,"mmm") -> Apr | D81: =TEXT(B81,"yyyy") -> 2024 | E81: 45419 | F81: Delivered | G81: =IF(E81=0,"",E81-B81) -> 31 | H81: CU0611 | I81: =VLOOKUP($H81,Customers!$A$1:$I$721,2,FALSE) -> Mahesh Yadav | J81: =VLOOKUP($H81,Customers!$A$1:$I$721,3,FALSE) -> Male | K81: =VLOOKUP($H81,Customers!$A$1:$I$721,4,FALSE) -> 55 | L81: =VLOOKUP($H81,Customers!$A$1:$I$721,5,FALSE) -> Kochi | M81: =VLOOKUP($H81,Customers!$A$1:$I$721,6,FALSE) -> Kerala | N81: =VLOOKUP($H81,Customers!$A$1:$I$721,7,FALSE) -> Engineer | O81: =VLOOKUP($H81,Customers!$A$1:$I$721,8,FALSE) -> 1470000 | P81: =VLOOKUP($H81,Customers!$A$1:$I$721,9,FALSE) -> Individual | Q81: C035 | R81: {=VLOOKUP($Q81,Cars[],{2,3,4,5,6,7,8,9},FALSE)} -> MG | S81: Hector | T81: SUV | U81: Petrol | V81: Automatic | W81: 1600000 | X81: 2019 | Y81: 4 | Z81: D019 | AA81: =VLOOKUP(Z81,Dealers[],5,FALSE) -> South | AB81: {=VLOOKUP($Z81,Dealers[],{2,7,8,9},FALSE)} -> Kochi Auto Hub | AC81: 2013 | AD81: 12000 | AE81: 4.2 | AF81: S056 | AG81: =VLOOKUP($AF81,SalesPerson[],2,FALSE) -> Meera Saini | AH81: =_xlfn.XLOOKUP(AG81,Salespersons!$B:$B,Salespersons!$G:$G,,0) -> 8 | AI81: =_xlfn.XLOOKUP(AG81,Salespersons!$B:$B,Salespersons!$I:$I,,0) -> True | AJ81: Black | AK81: =AL81/W81 -> 0.044375 | AL81: 71000 | AM81: =W81-AL81 -> 1529000 | AN81: =AM81/100000 -> 15.29 | AO81: Exchange + Loan | AP81: ICICI Bank | AQ81: Walk-in | AR81: Yes | AS81: No Feedback | AT81: No Feedback | AU81: No Feedback | AV81: No Feedback | AW81: No Feedback
A82: ORD00081 | B82: 45389 | C82: =TEXT(B82,"mmm") -> Apr | D82: =TEXT(B82,"yyyy") -> 2024 | E82: 45398 | F82: Delivered | G82: =IF(E82=0,"",E82-B82) -> 9 | H82: CU0085 | I82: =VLOOKUP($H82,Customers!$A$1:$I$721,2,FALSE) -> Ankit Joshi | J82: =VLOOKUP($H82,Customers!$A$1:$I$721,3,FALSE) -> Male | K82: =VLOOKUP($H82,Customers!$A$1:$I$721,4,FALSE) -> 34 | L82: =VLOOKUP($H82,Customers!$A$1:$I$721,5,FALSE) -> Mysuru | M82: =VLOOKUP($H82,Customers!$A$1:$I$721,6,FALSE) -> Karnataka | N82: =VLOOKUP($H82,Customers!$A$1:$I$721,7,FALSE) -> Engineer | O82: =VLOOKUP($H82,Customers!$A$1:$I$721,8,FALSE) -> 840000 | P82: =VLOOKUP($H82,Customers!$A$1:$I$721,9,FALSE) -> Individual | Q82: C003 | R82: {=VLOOKUP($Q82,Cars[],{2,3,4,5,6,7,8,9},FALSE)} -> Maruti Suzuki | S82: Baleno | T82: Hatchback | U82: Petrol | V82: Automatic | W82: 760000 | X82: 2022 | Y82: 2 | Z82: D014 | AA82: =VLOOKUP(Z82,Dealers[],5,FALSE) -> South | AB82: {=VLOOKUP($Z82,Dealers[],{2,7,8,9},FALSE)} -> Bengaluru Auto Hub | AC82: 2013 | AD82: 12000 | AE82: 4.4 | AF82: S042 | AG82: =VLOOKUP($AF82,SalesPerson[],2,FALSE) -> Yash Sharma | AH82: =_xlfn.XLOOKUP(AG82,Salespersons!$B:$B,Salespersons!$G:$G,,0) -> 5 | AI82: =_xlfn.XLOOKUP(AG82,Salespersons!$B:$B,Salespersons!$I:$I,,0) -> True | AJ82: Red | AK82: =AL82/W82 -> 0.027631579 | AL82: 21000 | AM82: =W82-AL82 -> 739000 | AN82: =AM82/100000 -> 7.39 | AO82: Cash | AP82: N/A | AQ82: Online Website | AR82: No | AS82: {=VLOOKUP($A82,Feedback[],{2,4,5,6,7},FALSE)} -> FB0039 | AT82: 3 | AU82: 8 | AV82: Dealer Visit | AW82: After-Sales Support
A83: ORD00082 | B83: 45389 | C83: =TEXT(B83,"mmm") -> Apr | D83: =TEXT(B83,"yyyy") -> 2024 | E83: 45393 | F83: Delivered | G83: =IF(E83=0,"",E83-B83) -> 4 | H83: CU0496 | I83: =VLOOKUP($H83,Customers!$A$1:$I$721,2,FALSE) -> Vinod Bansal | J83: =VLOOKUP($H83,Customers!$A$1:$I$721,3,FALSE) -> Male | K83: =VLOOKUP($H83,Customers!$A$1:$I$721,4,FALSE) -> 48 | L83: =VLOOKUP($H83,Customers!$A$1:$I$721,5,FALSE) -> Chandigarh | M83: =VLOOKUP($H83,Customers!$A$1:$I$721,6,FALSE) -> Chandigarh | N83: =VLOOKUP($H83,Customers!$A$1:$I$721,7,FALSE) -> Engineer | O83: =VLOOKUP($H83,Customers!$A$1:$I$721,8,FALSE) -> 1620000 | P83: =VLOOKUP($H83,Customers!$A$1:$I$721,9,FALSE) -> Individual | Q83: C040 | R83: {=VLOOKUP($Q83,Cars[],{2,3,4,5,6,7,8,9},FALSE)} -> Audi | S83: Q3 | T83: Luxury SUV | U83: Petrol | V83: Automatic | W83: 5400000 | X83: 2022 | Y83: 5 | Z83: D004 | AA83: =VLOOKUP(Z83,Dealers[],5,FALSE) -> North | AB83: {=VLOOKUP($Z83,Dealers[],{2,7,8,9},FALSE)} -> Chandigarh Car World | AC83: 2018 | AD83: 4500 | AE83: 4 | AF83: S012 | AG83: =VLOOKUP($AF83,SalesPerson[],2,FALSE) -> Tarun Sharma | AH83: =_xlfn.XLOOKUP(AG83,Salespersons!$B:$B,Salespersons!$G:$G,,0) -> 7 | AI83: =_xlfn.XLOOKUP(AG83,Salespersons!$B:$B,Salespersons!$I:$I,,0) -> True | AJ83: Black | AK83: =AL83/W83 -> 0 | AL83: 0 | AM83: =W83-AL83 -> 5400000 | AN83: =AM83/100000 -> 54 | AO83: Cash | AP83: N/A | AQ83: Auto Expo/Event | AR83: No | AS83: {=VLOOKUP($A83,Feedback[],{2,4,5,6,7},FALSE)} -> FB0040 | AT83: 5 | AU83: 8 | AV83: Email | AW83: None
A84: ORD00083 | B84: 45391 | C84: =TEXT(B84,"mmm") -> Apr | D84: =TEXT(B84,"yyyy") -> 2024 | E84: 45405 | F84: Delivered | G84: =IF(E84=0,"",E84-B84) -> 14 | H84: CU0543 | I84: =VLOOKUP($H84,Customers!$A$1:$I$721,2,FALSE) -> Imran Mishra | J84: =VLOOKUP($H84,Customers!$A$1:$I$721,3,FALSE) -> Male | K84: =VLOOKUP($H84,Customers!$A$1:$I$721,4,FALSE) -> 21 | L84: =VLOOKUP($H84,Customers!$A$1:$I$721,5,FALSE) -> Bhubaneswar | M84: =VLOOKUP($H84,Customers!$A$1:$I$721,6,FALSE) -> Odisha | N84: =VLOOKUP($H84,Customers!$A$1:$I$721,7,FALSE) -> Salaried - Private | O84: =VLOOKUP($H84,Customers!$A$1:$I$721,8,FALSE) -> 710000 | P84: =VLOOKUP($H84,Customers!$A$1:$I$721,9,FALSE) -> Individual | Q84: C012 | R84: {=VLOOKUP($Q84,Cars[],{2,3,4,5,6,7,8,9},FALSE)} -> Hyundai | S84: Verna | T84: Sedan | U84: Petrol | V84: Automatic | W84: 1100000 | X84: 2023 | Y84: 2 | Z84: D021 | AA84: =VLOOKUP(Z84,Dealers[],5,FALSE) -> East | AB84: {=VLOOKUP($Z84,Dealers[],{2,7,8,9},FALSE)} -> Bhubaneswar Motors | AC84: 2008 | AD84: 4500 | AE84: 4.3 | AF84: S062 | AG84: =VLOOKUP($AF84,SalesPerson[],2,FALSE) -> Akash Jain | AH84: =_xlfn.XLOOKUP(AG84,Salespersons!$B:$B,Salespersons!$G:$G,,0) -> 5 | AI84: =_xlfn.XLOOKUP(AG84,Salespersons!$B:$B,Salespersons!$I:$I,,0) -> True | AJ84: White | AK84: =AL84/W84 -> 0.039090909 | AL84: 43000 | AM84: =W84-AL84 -> 1057000 | AN84: =AM84/100000 -> 10.57 | AO84: Cash | AP84: N/A | AQ84: Social Media | AR84: No | AS84: {=VLOOKUP($A84,Feedback[],{2,4,5,6,7},FALSE)} -> FB0041 | AT84: 4 | AU84: 9 | AV84: Email | AW84: None
A85: ORD00084 | B85: 45392 | C85: =TEXT(B85,"mmm") -> Apr | D85: =TEXT(B85,"yyyy") -> 2024 | F85: Cancelled | G85: =IF(E85=0,"",E85-B85) | H85: CU0126 | I85: =VLOOKUP($H85,Customers!$A$1:$I$721,2,FALSE) -> Sneha Chauhan | J85: =VLOOKUP($H85,Customers!$A$1:$I$721,3,FALSE) -> Female | K85: =VLOOKUP($H85,Customers!$A$1:$I$721,4,FALSE) -> 35 | L85: =VLOOKUP($H85,Customers!$A$1:$I$721,5,FALSE) -> Coimbatore | M85: =VLOOKUP($H85,Customers!$A$1:$I$721,6,FALSE) -> Tamil Nadu | N85: =VLOOKUP($H85,Customers!$A$1:$I$721,7,FALSE) -> Farmer | O85: =VLOOKUP($H85,Customers!$A$1:$I$721,8,FALSE) -> 300000 | P85: =VLOOKUP($H85,Customers!$A$1:$I$721,9,FALSE) -> Individual | Q85: C001 | R85: {=VLOOKUP($Q85,Cars[],{2,3,4,5,6,7,8,9},FALSE)} -> Maruti Suzuki | S85: Alto K10 | T85: Hatchback | U85: Petrol | V85: Manual | W85: 425000 | X85: 2022 | Y85: 3 | Z85: D016 | AA85: =VLOOKUP(Z85,Dealers[],5,FALSE) -> South | AB85: {=VLOOKUP($Z85,Dealers[],{2,7,8,9},FALSE)} -> Chennai Wheels | AC85: 2007 | AD85: 4500 | AE85: 4.7 | AF85: S048 | AG85: =VLOOKUP($AF85,SalesPerson[],2,FALSE) -> Kunal Pillai | AH85: =_xlfn.XLOOKUP(AG85,Salespersons!$B:$B,Salespersons!$G:$G,,0) -> 5 | AI85: =_xlfn.XLOOKUP(AG85,Salespersons!$B:$B,Salespersons!$I:$I,,0) -> True | AJ85: Silver | AK85: =AL85/W85 -> 0.025882353 | AL85: 11000 | AM85: =W85-AL85 -> 414000 | AN85: =AM85/100000 -> 4.14 | AO85: Loan/Finance | AP85: HDFC Bank | AQ85: Referral | AR85: No | AS85: No Feedback | AT85: No Feedback | AU85: No Feedback | AV85: No Feedback | AW85: No Feedback
A86: ORD00085 | B86: 45392 | C86: =TEXT(B86,"mmm") -> Apr | D86: =TEXT(B86,"yyyy") -> 2024 | E86: 45413 | F86: Delivered | G86: =IF(E86=0,"",E86-B86) -> 21 | H86: CU0558 | I86: =VLOOKUP($H86,Customers!$A$1:$I$721,2,FALSE) -> Sandeep Reddy | J86: =VLOOKUP($H86,Customers!$A$1:$I$721,3,FALSE) -> Male | K86: =VLOOKUP($H86,Customers!$A$1:$I$721,4,FALSE) -> 36 | L86: =VLOOKUP($H86,Customers!$A$1:$I$721,5,FALSE) -> Kolkata | M86: =VLOOKUP($H86,Customers!$A$1:$I$721,6,FALSE) -> West Bengal | N86: =VLOOKUP($H86,Customers!$A$1:$I$721,7,FALSE) -> Salaried - Private | O86: =VLOOKUP($H86,Customers!$A$1:$I$721,8,FALSE) -> 1460000 | P86: =VLOOKUP($H86,Customers!$A$1:$I$721,9,FALSE) -> Individual | Q86: C004 | R86: {=VLOOKUP($Q86,Cars[],{2,3,4,5,6,7,8,9},FALSE)} -> Maruti Suzuki | S86: Dzire | T86: Sedan | U86: Petrol | V86: Manual | W86: 690000 | X86: 2024 | Y86: 3 | Z86: D022 | AA86: =VLOOKUP(Z86,Dealers[],5,FALSE) -> East | AB86: {=VLOOKUP($Z86,Dealers[],{2,7,8,9},FALSE)} -> Patna Autoplex | AC86: 2007 | AD86: 8000 | AE86: 3.9 | AF86: S065 | AG86: =VLOOKUP($AF86,SalesPerson[],2,FALSE) -> Lokesh Iyer | AH86: =_xlfn.XLOOKUP(AG86,Salespersons!$B:$B,Salespersons!$G:$G,,0) -> 4 | AI86: =_xlfn.XLOOKUP(AG86,Salespersons!$B:$B,Salespersons!$I:$I,,0) -> True | AJ86: Grey | AK86: =AL86/W86 -> 0 | AL86: 0 | AM86: =W86-AL86 -> 690000 | AN86: =AM86/100000 -> 6.9 | AO86: Cash | AP86: N/A | AQ86: Social Media | AR86: Yes | AS86: No Feedback | AT86: No Feedback | AU86: No Feedback | AV86: No Feedback | AW86: No Feedback
A87: ORD00086 | B87: 45393 | C87: =TEXT(B87,"mmm") -> Apr | D87: =TEXT(B87,"yyyy") -> 2024 | E87: 45405 | F87: Delivered | G87: =IF(E87=0,"",E87-B87) -> 12 | H87: CU0591 | I87: =VLOOKUP($H87,Customers!$A$1:$I$721,2,FALSE) -> Faisal Joshi | J87: =VLOOKUP($H87,Customers!$A$1:$I$721,3,FALSE) -> Male | K87: =VLOOKUP($H87,Customers!$A$1:$I$721,4,FALSE) -> 62 | L87: =VLOOKUP($H87,Customers!$A$1:$I$721,5,FALSE) -> Jaipur | M87: =VLOOKUP($H87,Customers!$A$1:$I$721,6,FALSE) -> Rajasthan | N87: =VLOOKUP($H87,Customers!$A$1:$I$721,7,FALSE) -> Doctor | O87: =VLOOKUP($H87,Customers!$A$1:$I$721,8,FALSE) -> 3400000 | P87: =VLOOKUP($H87,Customers!$A$1:$I$721,9,FALSE) -> Individual | Q87: C012 | R87: {=VLOOKUP($Q87,Cars[],{2,3,4,5,6,7,8,9},FALSE)} -> Hyundai | S87: Verna | T87: Sedan | U87: Petrol | V87: Automatic | W87: 1100000 | X87: 2023 | Y87: 2 | Z87: D006 | AA87: =VLOOKUP(Z87,Dealers[],5,FALSE) -> North | AB87: {=VLOOKUP($Z87,Dealers[],{2,7,8,9},FALSE)} -> Jaipur Wheels | AC87: 2015 | AD87: 3000 | AE87: 3.5 | AF87: S017 | AG87: =VLOOKUP($AF87,SalesPerson[],2,FALSE) -> Mohit Yadav | AH87: =_xlfn.XLOOKUP(AG87,Salespersons!$B:$B,Salespersons!$G:$G,,0) -> 8 | AI87: =_xlfn.XLOOKUP(AG87,Salespersons!$B:$B,Salespersons!$I:$I,,0) -> True | AJ87: Black | AK87: =AL87/W87 -> 0.032727273 | AL87: 36000 | AM87: =W87-AL87 -> 1064000 | AN87: =AM87/100000 -> 10.64 | AO87: Loan/Finance | AP87: SBI | AQ87: Auto Expo/Event | AR87: Yes | AS87: No Feedback | AT87: No Feedback | AU87: No Feedback | AV87: No Feedback | AW87: No Feedback
A88: ORD00087 | B88: 45393 | C88: =TEXT(B88,"mmm") -> Apr | D88: =TEXT(B88,"yyyy") -> 2024 | E88: 45412 | F88: Delivered | G88: =IF(E88=0,"",E88-B88) -> 19 | H88: CU0138 | I88: =VLOOKUP($H88,Customers!$A$1:$I$721,2,FALSE) -> Ashok Verma | J88: =VLOOKUP($H88,Customers!$A$1:$I$721,3,FALSE) -> Male | K88: =VLOOKUP($H88,Customers!$A$1:$I$721,4,FALSE) -> 38 | L88: =VLOOKUP($H88,Customers!$A$1:$I$721,5,FALSE) -> Kochi | M88: =VLOOKUP($H88,Customers!$A$1:$I$721,6,FALSE) -> Kerala | N88: =VLOOKUP($H88,Customers!$A$1:$I$721,7,FALSE) -> Business Owner | O88: =VLOOKUP($H88,Customers!$A$1:$I$721,8,FALSE) -> 1930000 | P88: =VLOOKUP($H88,Customers!$A$1:$I$721,9,FALSE) -> Individual | Q88: C016 | R88: {=VLOOKUP($Q88,Cars[],{2,3,4,5,6,7,8,9},FALSE)} -> Tata | S88: Nexon | T88: SUV | U88: Diesel | V88: Manual | W88: 950000 | X88: 2023 | Y88: 3 | Z88: D019 | AA88: =VLOOKUP(Z88,Dealers[],5,FALSE) -> South | AB88: {=VLOOKUP($Z88,Dealers[],{2,7,8,9},FALSE)} -> Kochi Auto Hub | AC88: 2013 | AD88: 12000 | AE88: 4.2 | AF88: S058 | AG88: =VLOOKUP($AF88,SalesPerson[],2,FALSE) -> Varun Saini | AH88: =_xlfn.XLOOKUP(AG88,Salespersons!$B:$B,Salespersons!$G:$G,,0) -> 8 | AI88: =_xlfn.XLOOKUP(AG88,Salespersons!$B:$B,Salespersons!$I:$I,,0) -> False | AJ88: Black | AK88: =AL88/W88 -> 0 | AL88: 0 | AM88: =W88-AL88 -> 950000 | AN88: =AM88/100000 -> 9.5 | AO88: Exchange + Loan | AP88: HDFC Bank | AQ88: Online Website | AR88: No | AS88: {=VLOOKUP($A88,Feedback[],{2,4,5,6,7},FALSE)} -> FB0042 | AT88: 4 | AU88: 8 | AV88: Phone | AW88: None
A89: ORD00088 | B89: 45393 | C89: =TEXT(B89,"mmm") -> Apr | D89: =TEXT(B89,"yyyy") -> 2024 | E89: 45408 | F89: Delivered | G89: =IF(E89=0,"",E89-B89) -> 15 | H89: CU0468 | I89: =VLOOKUP($H89,Customers!$A$1:$I$721,2,FALSE) -> Gaurav Das | J89: =VLOOKUP($H89,Customers!$A$1:$I$721,3,FALSE) -> Male | K89: =VLOOKUP($H89,Customers!$A$1:$I$721,4,FALSE) -> 27 | L89: =VLOOKUP($H89,Customers!$A$1:$I$721,5,FALSE) -> Pune | M89: =VLOOKUP($H89,Customers!$A$1:$I$721,6,FALSE) -> Maharashtra | N89: =VLOOKUP($H89,Customers!$A$1:$I$721,7,FALSE) -> Salaried - Government | O89: =VLOOKUP($H89,Customers!$A$1:$I$721,8,FALSE) -> 750000 | P89: =VLOOKUP($H89,Customers!$A$1:$I$721,9,FALSE) -> Individual | Q89: C002 | R89: {=VLOOKUP($Q89,Cars[],{2,3,4,5,6,7,8,9},FALSE)} -> Maruti Suzuki | S89: Swift | T89: Hatchback | U89: Petrol | V89: Manual | W89: 650000 | X89: 2024 | Y89: 3 | Z89: D010 | AA89: =VLOOKUP(Z89,Dealers[],5,FALSE) -> West | AB89: {=VLOOKUP($Z89,Dealers[],{2,7,8,9},FALSE)} -> Pune Autoplex | AC89: 2014 | AD89: 3000 | AE89: 4.6 | AF89: S031 | AG89: =VLOOKUP($AF89,SalesPerson[],2,FALSE) -> Ankit Verma | AH89: =_xlfn.XLOOKUP(AG89,Salespersons!$B:$B,Salespersons!$G:$G,,0) -> 4 | AI89: =_xlfn.XLOOKUP(AG89,Salespersons!$B:$B,Salespersons!$I:$I,,0) -> True | AJ89: Grey | AK89: =AL89/W89 -> 0.024615385 | AL89: 16000 | AM89: =W89-AL89 -> 634000 | AN89: =AM89/100000 -> 6.34 | AO89: Loan/Finance | AP89: Mahindra Finance | AQ89: Test Drive Campaign | AR89: No | AS89: {=VLOOKUP($A89,Feedback[],{2,4,5,6,7},FALSE)} -> FB0043 | AT89: 5 | AU89: 8 | AV89: Online Survey | AW89: None
A90: ORD00089 | B90: 45394 | C90: =TEXT(B90,"mmm") -> Apr | D90: =TEXT(B90,"yyyy") -> 2024 | E90: 45412 | F90: Delivered | G90: =IF(E90=0,"",E90-B90) -> 18 | H90: CU0664 | I90: =VLOOKUP($H90,Customers!$A$1:$I$721,2,FALSE) -> Vivek Pillai | J90: =VLOOKUP($H90,Customers!$A$1:$I$721,3,FALSE) -> Male | K90: =VLOOKUP($H90,Customers!$A$1:$I$721,4,FALSE) -> 21 | L90: =VLOOKUP($H90,Customers!$A$1:$I$721,5,FALSE) -> Ahmedabad | M90: =VLOOKUP($H90,Customers!$A$1:$I$721,6,FALSE) -> Gujarat | N90: =VLOOKUP($H90,Customers!$A$1:$I$721,7,FALSE) -> Salaried - Government | O90: =VLOOKUP($H90,Customers!$A$1:$I$721,8,FALSE) -> 1220000 | P90: =VLOOKUP($H90,Customers!$A$1:$I$721,9,FALSE) -> Individual | Q90: C028 | R90: {=VLOOKUP($Q90,Cars[],{2,3,4,5,6,7,8,9},FALSE)} -> Honda | S90: City | T90: Sedan | U90: Petrol | V90: Automatic | W90: 1250000 | X90: 2023 | Y90: 4 | Z90: D013 | AA90: =VLOOKUP(Z90,Dealers[],5,FALSE) -> West | AB90: {=VLOOKUP($Z90,Dealers[],{2,7,8,9},FALSE)} -> Surat Autoplex | AC90: 2010 | AD90: 10000 | AE90: 4.4 | AF90: S039 | AG90: =VLOOKUP($AF90,SalesPerson[],2,FALSE) -> Vivek Mehta | AH90: =_xlfn.XLOOKUP(AG90,Salespersons!$B:$B,Salespersons!$G:$G,,0) -> 4 | AI90: =_xlfn.XLOOKUP(AG90,Salespersons!$B:$B,Salespersons!$I:$I,,0) -> True | AJ90: White | AK90: =AL90/W90 -> 0.0096 | AL90: 12000 | AM90: =W90-AL90 -> 1238000 | AN90: =AM90/100000 -> 12.38 | AO90: Exchange + Loan | AP90: Axis Bank | AQ90: Walk-in | AR90: No | AS90: {=VLOOKUP($A90,Feedback[],{2,4,5,6,7},FALSE)} -> FB0044 | AT90: 5 | AU90: 10 | AV90: Online Survey | AW90: None
A91: ORD00090 | B91: 45394 | C91: =TEXT(B91,"mmm") -> Apr | D91: =TEXT(B91,"yyyy") -> 2024 | E91: 45411 | F91: Delivered | G91: =IF(E91=0,"",E91-B91) -> 17 | H91: CU0113 | I91: =VLOOKUP($H91,Customers!$A$1:$I$721,2,FALSE) -> Komal Shah | J91: =VLOOKUP($H91,Customers!$A$1:$I$721,3,FALSE) -> Female | K91: =VLOOKUP($H91,Customers!$A$1:$I$721,4,FALSE) -> 24 | L91: =VLOOKUP($H91,Customers!$A$1:$I$721,5,FALSE) -> Chennai | M91: =VLOOKUP($H91,Customers!$A$1:$I$721,6,FALSE) -> Tamil Nadu | N91: =VLOOKUP($H91,Customers!$A$1:$I$721,7,FALSE) -> Salaried - Private | O91: =VLOOKUP($H91,Customers!$A$1:$I$721,8,FALSE) -> 640000 | P91: =VLOOKUP($H91,Customers!$A$1:$I$721,9,FALSE) -> Individual | Q91: C019 | R91: {=VLOOKUP($Q91,Cars[],{2,3,4,5,6,7,8,9},FALSE)} -> Tata | S91: Tiago EV | T91: Hatchback | U91: Electric | V91: Automatic | W91: 800000 | X91: 2022 | Y91: 2 | Z91: D017 | AA91: =VLOOKUP(Z91,Dealers[],5,FALSE) -> South | AB91: {=VLOOKUP($Z91,Dealers[],{2,7,8,9},FALSE)} -> Coimbatore Car World | AC91: 2015 | AD91: 4500 | AE91: 4.3 | AF91: S051 | AG91: =VLOOKUP($AF91,SalesPerson[],2,FALSE) -> Arjun Verma | AH91: =_xlfn.XLOOKUP(AG91,Salespersons!$B:$B,Salespersons!$G:$G,,0) -> 4 | AI91: =_xlfn.XLOOKUP(AG91,Salespersons!$B:$B,Salespersons!$I:$I,,0) -> True | AJ91: White | AK91: =AL91/W91 -> 0.01 | AL91: 8000 | AM91: =W91-AL91 -> 792000 | AN91: =AM91/100000 -> 7.92 | AO91: Loan/Finance | AP91: SBI | AQ91: Walk-in | AR91: No | AS91: {=VLOOKUP($A91,Feedback[],{2,4,5,6,7},FALSE)} -> FB0045 | AT91: 5 | AU91: 10 | AV91: Phone | AW91: None
A92: ORD00091 | B92: 45395 | C92: =TEXT(B92,"mmm") -> Apr | D92: =TEXT(B92,"yyyy") -> 2024 | E92: 45429 | F92: Delivered | G92: =IF(E92=0,"",E92-B92) -> 34 | H92: CU0228 | I92: =VLOOKUP($H92,Customers!$A$1:$I$721,2,FALSE) -> Harsh Kapoor | J92: =VLOOKUP($H92,Customers!$A$1:$I$721,3,FALSE) -> Male | K92: =VLOOKUP($H92,Customers!$A$1:$I$721,4,FALSE) -> 29 | L92: =VLOOKUP($H92,Customers!$A$1:$I$721,5,FALSE) -> Surat | M92: =VLOOKUP($H92,Customers!$A$1:$I$721,6,FALSE) -> Gujarat | N92: =VLOOKUP($H92,Customers!$A$1:$I$721,7,FALSE) -> Salaried - Government | O92: =VLOOKUP($H92,Customers!$A$1:$I$721,8,FALSE) -> 620000 | P92: =VLOOKUP($H92,Customers!$A$1:$I$721,9,FALSE) -> Individual | Q92: C009 | R92: {=VLOOKUP($Q92,Cars[],{2,3,4,5,6,7,8,9},FALSE)} -> Hyundai | S92: i20 | T92: Hatchback | U92: Petrol | V92: Automatic | W92: 780000 | X92: 2023 | Y92: 2 | Z92: D012 | AA92: =VLOOKUP(Z92,Dealers[],5,FALSE) -> West | AB92: {=VLOOKUP($Z92,Dealers[],{2,7,8,9},FALSE)} -> Ahmedabad Auto Hub | AC92: 2011 | AD92: 12000 | AE92: 3.8 | AF92: S036 | AG92: =VLOOKUP($AF92,SalesPerson[],2,FALSE) -> Nitin Das | AH92: =_xlfn.XLOOKUP(AG92,Salespersons!$B:$B,Salespersons!$G:$G,,0) -> 5 | AI92: =_xlfn.XLOOKUP(AG92,Salespersons!$B:$B,Salespersons!$I:$I,,0) -> True | AJ92: White | AK92: =AL92/W92 -> 0.028205128 | AL92: 22000 | AM92: =W92-AL92 -> 758000 | AN92: =AM92/100000 -> 7.58 | AO92: Loan/Finance | AP92: Bajaj Finserv | AQ92: Referral | AR92: No | AS92: {=VLOOKUP($A92,Feedback[],{2,4,5,6,7},FALSE)} -> FB0046 | AT92: 3 | AU92: 5 | AV92: Email | AW92: After-Sales Support
A93: ORD00092 | B93: 45396 | C93: =TEXT(B93,"mmm") -> Apr | D93: =TEXT(B93,"yyyy") -> 2024 | E93: 45424 | F93: Delivered | G93: =IF(E93=0,"",E93-B93) -> 28 | H93: CU0586 | I93: =VLOOKUP($H93,Customers!$A$1:$I$721,2,FALSE) -> Kamal Jain | J93: =VLOOKUP($H93,Customers!$A$1:$I$721,3,FALSE) -> Male | K93: =VLOOKUP($H93,Customers!$A$1:$I$721,4,FALSE) -> 29 | L93: =VLOOKUP($H93,Customers!$A$1:$I$721,5,FALSE) -> Mysuru | M93: =VLOOKUP($H93,Customers!$A$1:$I$721,6,FALSE) -> Karnataka | N93: =VLOOKUP($H93,Customers!$A$1:$I$721,7,FALSE) -> Salaried - Government | O93: =VLOOKUP($H93,Customers!$A$1:$I$721,8,FALSE) -> 710000 | P93: =VLOOKUP($H93,Customers!$A$1:$I$721,9,FALSE) -> Individual | Q93: C030 | R93: {=VLOOKUP($Q93,Cars[],{2,3,4,5,6,7,8,9},FALSE)} -> Kia | S93: Seltos | T93: SUV | U93: Petrol | V93: Automatic | W93: 1350000 | X93: 2023 | Y93: 3 | Z93: D014 | AA93: =VLOOKUP(Z93,Dealers[],5,FALSE) -> South | AB93: {=VLOOKUP($Z93,Dealers[],{2,7,8,9},FALSE)} -> Bengaluru Auto Hub | AC93: 2013 | AD93: 12000 | AE93: 4.4 | AF93: S042 | AG93: =VLOOKUP($AF93,SalesPerson[],2,FALSE) -> Yash Sharma | AH93: =_xlfn.XLOOKUP(AG93,Salespersons!$B:$B,Salespersons!$G:$G,,0) -> 5 | AI93: =_xlfn.XLOOKUP(AG93,Salespersons!$B:$B,Salespersons!$I:$I,,0) -> True | AJ93: Silver | AK93: =AL93/W93 -> 0 | AL93: 0 | AM93: =W93-AL93 -> 1350000 | AN93: =AM93/100000 -> 13.5 | AO93: Exchange + Loan | AP93: SBI | AQ93: Online Website | AR93: No | AS93: No Feedback | AT93: No Feedback | AU93: No Feedback | AV93: No Feedback | AW93: No Feedback
A94: ORD00093 | B94: 45397 | C94: =TEXT(B94,"mmm") -> Apr | D94: =TEXT(B94,"yyyy") -> 2024 | E94: 45423 | F94: Delivered | G94: =IF(E94=0,"",E94-B94) -> 26 | H94: CU0010 | I94: =VLOOKUP($H94,Customers!$A$1:$I$721,2,FALSE) -> Nisha Mishra | J94: =VLOOKUP($H94,Customers!$A$1:$I$721,3,FALSE) -> Female | K94: =VLOOKUP($H94,Customers!$A$1:$I$721,4,FALSE) -> 21 | L94: =VLOOKUP($H94,Customers!$A$1:$I$721,5,FALSE) -> Pune | M94: =VLOOKUP($H94,Customers!$A$1:$I$721,6,FALSE) -> Maharashtra | N94: =VLOOKUP($H94,Customers!$A$1:$I$721,7,FALSE) -> Student/Other | O94: =VLOOKUP($H94,Customers!$A$1:$I$721,8,FALSE) -> 590000 | P94: =VLOOKUP($H94,Customers!$A$1:$I$721,9,FALSE) -> Individual | Q94: C019 | R94: {=VLOOKUP($Q94,Cars[],{2,3,4,5,6,7,8,9},FALSE)} -> Tata | S94: Tiago EV | T94: Hatchback | U94: Electric | V94: Automatic | W94: 800000 | X94: 2022 | Y94: 2 | Z94: D011 | AA94: =VLOOKUP(Z94,Dealers[],5,FALSE) -> West | AB94: {=VLOOKUP($Z94,Dealers[],{2,7,8,9},FALSE)} -> Nagpur Motors | AC94: 2019 | AD94: 12000 | AE94: 4.6 | AF94: S034 | AG94: =VLOOKUP($AF94,SalesPerson[],2,FALSE) -> Arjun Reddy | AH94: =_xlfn.XLOOKUP(AG94,Salespersons!$B:$B,Salespersons!$G:$G,,0) -> 5 | AI94: =_xlfn.XLOOKUP(AG94,Salespersons!$B:$B,Salespersons!$I:$I,,0) -> True | AJ94: Grey | AK94: =AL94/W94 -> 0 | AL94: 0 | AM94: =W94-AL94 -> 800000 | AN94: =AM94/100000 -> 8 | AO94: Loan/Finance | AP94: HDFC Bank | AQ94: Online Website | AR94: No | AS94: {=VLOOKUP($A94,Feedback[],{2,4,5,6,7},FALSE)} -> FB0047 | AT94: 5 | AU94: 10 | AV94: Dealer Visit | AW94: None
A95: ORD00094 | B95: 45397 | C95: =TEXT(B95,"mmm") -> Apr | D95: =TEXT(B95,"yyyy") -> 2024 | F95: Cancelled | G95: =IF(E95=0,"",E95-B95) | H95: CU0624 | I95: =VLOOKUP($H95,Customers!$A$1:$I$721,2,FALSE) -> Priya Bose | J95: =VLOOKUP($H95,Customers!$A$1:$I$721,3,FALSE) -> Female | K95: =VLOOKUP($H95,Customers!$A$1:$I$721,4,FALSE) -> 47 | L95: =VLOOKUP($H95,Customers!$A$1:$I$721,5,FALSE) -> Panipat | M95: =VLOOKUP($H95,Customers!$A$1:$I$721,6,FALSE) -> Haryana | N95: =VLOOKUP($H95,Customers!$A$1:$I$721,7,FALSE) -> Salaried - Private | O95: =VLOOKUP($H95,Customers!$A$1:$I$721,8,FALSE) -> 750000 | P95: =VLOOKUP($H95,Customers!$A$1:$I$721,9,FALSE) -> Individual | Q95: C010 | R95: {=VLOOKUP($Q95,Cars[],{2,3,4,5,6,7,8,9},FALSE)} -> Hyundai | S95: Venue | T95: SUV | U95: Petrol | V95: Manual | W95: 800000 | X95: 2022 | Y95: 3 | Z95: D003 | AA95: =VLOOKUP(Z95,Dealers[],5,FALSE) -> North | AB95: {=VLOOKUP($Z95,Dealers[],{2,7,8,9},FALSE)} -> Panipat Motors | AC95: 2012 | AD95: 10000 | AE95: 4.2 | AF95: S010 | AG95: =VLOOKUP($AF95,SalesPerson[],2,FALSE) -> Rahul Rao | AH95: =_xlfn.XLOOKUP(AG95,Salespersons!$B:$B,Salespersons!$G:$G,,0) -> 5 | AI95: =_xlfn.XLOOKUP(AG95,Salespersons!$B:$B,Salespersons!$I:$I,,0) -> True | AJ95: Silver | AK95: =AL95/W95 -> 0.045 | AL95: 36000 | AM95: =W95-AL95 -> 764000 | AN95: =AM95/100000 -> 7.64 | AO95: Loan/Finance | AP95: ICICI Bank | AQ95: Corporate Tie-up | AR95: No | AS95: No Feedback | AT95: No Feedback | AU95: No Feedback | AV95: No Feedback | AW95: No Feedback
A96: ORD00095 | B96: 45399 | C96: =TEXT(B96,"mmm") -> Apr | D96: =TEXT(B96,"yyyy") -> 2024 | E96: 45417 | F96: Delivered | G96: =IF(E96=0,"",E96-B96) -> 18 | H96: CU0235 | I96: =VLOOKUP($H96,Customers!$A$1:$I$721,2,FALSE) -> Gaurav Das | J96: =VLOOKUP($H96,Customers!$A$1:$I$721,3,FALSE) -> Male | K96: =VLOOKUP($H96,Customers!$A$1:$I$721,4,FALSE) -> 39 | L96: =VLOOKUP($H96,Customers!$A$1:$I$721,5,FALSE) -> Chandigarh | M96: =VLOOKUP($H96,Customers!$A$1:$I$721,6,FALSE) -> Chandigarh | N96: =VLOOKUP($H96,Customers!$A$1:$I$721,7,FALSE) -> Engineer | O96: =VLOOKUP($H96,Customers!$A$1:$I$721,8,FALSE) -> 1640000 | P96: =VLOOKUP($H96,Customers!$A$1:$I$721,9,FALSE) -> Individual | Q96: C007 | R96: {=VLOOKUP($Q96,Cars[],{2,3,4,5,6,7,8,9},FALSE)} -> Maruti Suzuki | S96: Grand Vitara | T96: SUV | U96: Hybrid | V96: Automatic | W96: 1150000 | X96: 2022 | Y96: 3 | Z96: D010 | AA96: =VLOOKUP(Z96,Dealers[],5,FALSE) -> West | AB96: {=VLOOKUP($Z96,Dealers[],{2,7,8,9},FALSE)} -> Pune Autoplex | AC96: 2014 | AD96: 3000 | AE96: 4.6 | AF96: S033 | AG96: =VLOOKUP($AF96,SalesPerson[],2,FALSE) -> Shweta Mishra | AH96: =_xlfn.XLOOKUP(AG96,Salespersons!$B:$B,Salespersons!$G:$G,,0) -> 5 | AI96: =_xlfn.XLOOKUP(AG96,Salespersons!$B:$B,Salespersons!$I:$I,,0) -> True | AJ96: Orange | AK96: =AL96/W96 -> 0.043478261 | AL96: 50000 | AM96: =W96-AL96 -> 1100000 | AN96: =AM96/100000 -> 11 | AO96: Loan/Finance | AP96: Mahindra Finance | AQ96: Online Website | AR96: No | AS96: No Feedback | AT96: No Feedback | AU96: No Feedback | AV96: No Feedback | AW96: No Feedback
A97: ORD00096 | B97: 45401 | C97: =TEXT(B97,"mmm") -> Apr | D97: =TEXT(B97,"yyyy") -> 2024 | E97: 45436 | F97: Delivered | G97: =IF(E97=0,"",E97-B97) -> 35 | H97: CU0059 | I97: =VLOOKUP($H97,Customers!$A$1:$I$721,2,FALSE) -> Sneha Patel | J97: =VLOOKUP($H97,Customers!$A$1:$I$721,3,FALSE) -> Female | K97: =VLOOKUP($H97,Customers!$A$1:$I$721,4,FALSE) -> 37 | L97: =VLOOKUP($H97,Customers!$A$1:$I$721,5,FALSE) -> Hyderabad | M97: =VLOOKUP($H97,Customers!$A$1:$I$721,6,FALSE) -> Telangana | N97: =VLOOKUP($H97,Customers!$A$1:$I$721,7,FALSE) -> Self-Employed Professional | O97: =VLOOKUP($H97,Customers!$A$1:$I$721,8,FALSE) -> 950000 | P97: =VLOOKUP($H97,Customers!$A$1:$I$721,9,FALSE) -> Individual | Q97: C002 | R97: {=VLOOKUP($Q97,Cars[],{2,3,4,5,6,7,8,9},FALSE)} -> Maruti Suzuki | S97: Swift | T97: Hatchback | U97: Petrol | V97: Manual | W97: 650000 | X97: 2024 | Y97: 3 | Z97: D018 | AA97: =VLOOKUP(Z97,Dealers[],5,FALSE) -> South | AB97: {=VLOOKUP($Z97,Dealers[],{2,7,8,9},FALSE)} -> Hyderabad Automobiles | AC97: 2019 | AD97: 4500 | AE97: 3.8 | AF97: S053 | AG97: =VLOOKUP($AF97,SalesPerson[],2,FALSE) -> Mohit Patel | AH97: =_xlfn.XLOOKUP(AG97,Salespersons!$B:$B,Salespersons!$G:$G,,0) -> 7 | AI97: =_xlfn.XLOOKUP(AG97,Salespersons!$B:$B,Salespersons!$I:$I,,0) -> True | AJ97: Grey | AK97: =AL97/W97 -> 0.018461538 | AL97: 12000 | AM97: =W97-AL97 -> 638000 | AN97: =AM97/100000 -> 6.38 | AO97: Cash | AP97: N/A | AQ97: Corporate Tie-up | AR97: No | AS97: {=VLOOKUP($A97,Feedback[],{2,4,5,6,7},FALSE)} -> FB0048 | AT97: 4 | AU97: 7 | AV97: Dealer Visit | AW97: None
A98: ORD00097 | B98: 45401 | C98: =TEXT(B98,"mmm") -> Apr | D98: =TEXT(B98,"yyyy") -> 2024 | E98: 45419 | F98: Delivered | G98: =IF(E98=0,"",E98-B98) -> 18 | H98: CU0715 | I98: =VLOOKUP($H98,Customers!$A$1:$I$721,2,FALSE) -> Ramesh Das | J98: =VLOOKUP($H98,Customers!$A$1:$I$721,3,FALSE) -> Male | K98: =VLOOKUP($H98,Customers!$A$1:$I$721,4,FALSE) -> 39 | L98: =VLOOKUP($H98,Customers!$A$1:$I$721,5,FALSE) -> Ludhiana | M98: =VLOOKUP($H98,Customers!$A$1:$I$721,6,FALSE) -> Punjab | N98: =VLOOKUP($H98,Customers!$A$1:$I$721,7,FALSE) -> Engineer | O98: =VLOOKUP($H98,Customers!$A$1:$I$721,8,FALSE) -> 2040000 | P98: =VLOOKUP($H98,Customers!$A$1:$I$721,9,FALSE) -> Individual | Q98: C003 | R98: {=VLOOKUP($Q98,Cars[],{2,3,4,5,6,7,8,9},FALSE)} -> Maruti Suzuki | S98: Baleno | T98: Hatchback | U98: Petrol | V98: Automatic | W98: 760000 | X98: 2022 | Y98: 2 | Z98: D005 | AA98: =VLOOKUP(Z98,Dealers[],5,FALSE) -> North | AB98: {=VLOOKUP($Z98,Dealers[],{2,7,8,9},FALSE)} -> Ludhiana Wheels | AC98: 2010 | AD98: 12000 | AE98: 4 | AF98: S014 | AG98: =VLOOKUP($AF98,SalesPerson[],2,FALSE) -> Harsh Nair | AH98: =_xlfn.XLOOKUP(AG98,Salespersons!$B:$B,Salespersons!$G:$G,,0) -> 8 | AI98: =_xlfn.XLOOKUP(AG98,Salespersons!$B:$B,Salespersons!$I:$I,,0) -> True | AJ98: Brown | AK98: =AL98/W98 -> 0.035526316 | AL98: 27000 | AM98: =W98-AL98 -> 733000 | AN98: =AM98/100000 -> 7.33 | AO98: Cash | AP98: N/A | AQ98: Corporate Tie-up | AR98: No | AS98: No Feedback | AT98: No Feedback | AU98: No Feedback | AV98: No Feedback | AW98: No Feedback
A99: ORD00098 | B99: 45404 | C99: =TEXT(B99,"mmm") -> Apr | D99: =TEXT(B99,"yyyy") -> 2024 | E99: 45410 | F99: Delivered | G99: =IF(E99=0,"",E99-B99) -> 6 | H99: CU0701 | I99: =VLOOKUP($H99,Customers!$A$1:$I$721,2,FALSE) -> Varun Joshi | J99: =VLOOKUP($H99,Customers!$A$1:$I$721,3,FALSE) -> Male | K99: =VLOOKUP($H99,Customers!$A$1:$I$721,4,FALSE) -> 23 | L99: =VLOOKUP($H99,Customers!$A$1:$I$721,5,FALSE) -> Guwahati | M99: =VLOOKUP($H99,Customers!$A$1:$I$721,6,FALSE) -> Assam | N99: =VLOOKUP($H99,Customers!$A$1:$I$721,7,FALSE) -> Business Owner | O99: =VLOOKUP($H99,Customers!$A$1:$I$721,8,FALSE) -> 2230000 | P99: =VLOOKUP($H99,Customers!$A$1:$I$721,9,FALSE) -> Individual | Q99: C016 | R99: {=VLOOKUP($Q99,Cars[],{2,3,4,5,6,7,8,9},FALSE)} -> Tata | S99: Nexon | T99: SUV | U99: Diesel | V99: Manual | W99: 950000 | X99: 2023 | Y99: 3 | Z99: D023 | AA99: =VLOOKUP(Z99,Dealers[],5,FALSE) -> East | AB99: {=VLOOKUP($Z99,Dealers[],{2,7,8,9},FALSE)} -> Guwahati Automobiles | AC99: 2005 | AD99: 12000 | AE99: 4.4 | AF99: S069 | AG99: =VLOOKUP($AF99,SalesPerson[],2,FALSE) -> Varun Yadav | AH99: =_xlfn.XLOOKUP(AG99,Salespersons!$B:$B,Salespersons!$G:$G,,0) -> 6 | AI99: =_xlfn.XLOOKUP(AG99,Salespersons!$B:$B,Salespersons!$I:$I,,0) -> True | AJ99: Black | AK99: =AL99/W99 -> 0 | AL99: 0 | AM99: =W99-AL99 -> 950000 | AN99: =AM99/100000 -> 9.5 | AO99: Cash | AP99: N/A | AQ99: Social Media | AR99: Yes | AS99: No Feedback | AT99: No Feedback | AU99: No Feedback | AV99: No Feedback | AW99: No Feedback
A100: ORD00099 | B100: 45406 | C100: =TEXT(B100,"mmm") -> Apr | D100: =TEXT(B100,"yyyy") -> 2024 | E100: 45427 | F100: Delivered | G100: =IF(E100=0,"",E100-B100) -> 21 | H100: CU0383 | I100: =VLOOKUP($H100,Customers!$A$1:$I$721,2,FALSE) -> Pradeep Iyer | J100: =VLOOKUP($H100,Customers!$A$1:$I$721,3,FALSE) -> Male | K100: =VLOOKUP($H100,Customers!$A$1:$I$721,4,FALSE) -> 33 | L100: =VLOOKUP($H100,Customers!$A$1:$I$721,5,FALSE) -> Bhubaneswar | M100: =VLOOKUP($H100,Customers!$A$1:$I$721,6,FALSE) -> Odisha | N100: =VLOOKUP($H100,Customers!$A$1:$I$721,7,FALSE) -> Engineer | O100: =VLOOKUP($H100,Customers!$A$1:$I$721,8,FALSE) -> 1570000 | P100: =VLOOKUP($H100,Customers!$A$1:$I$721,9,FALSE) -> Individual | Q100: C037 | R100: {=VLOOKUP($Q100,Cars[],{2,3,4,5,6,7,8,9},FALSE)} -> Renault | S100: Kiger | T100: SUV | U100: Petrol | V100: Manual | W100: 700000 | X100: 2021 | Y100: 4 | Z100: D021 | AA100: =VLOOKUP(Z100,Dealers[],5,FALSE) -> East | AB100: {=VLOOKUP($Z100,Dealers[],{2,7,8,9},FALSE)} -> Bhubaneswar Motors | AC100: 2008 | AD100: 4500 | AE100: 4.3 | AF100: S064 | AG100: =VLOOKUP($AF100,SalesPerson[],2,FALSE) -> Siddharth Joshi | AH100: =_xlfn.XLOOKUP(AG100,Salespersons!$B:$B,Salespersons!$G:$G,,0) -> 8 | AI100: =_xlfn.XLOOKUP(AG100,Salespersons!$B:$B,Salespersons!$I:$I,,0) -> True | AJ100: White | AK100: =AL100/W100 -> 0.047142857 | AL100: 33000 | AM100: =W100-AL100 -> 667000 | AN100: =AM100/100000 -> 6.67 | AO100: Loan/Finance | AP100: ICICI Bank | AQ100: Walk-in | AR100: No | AS100: {=VLOOKUP($A100,Feedback[],{2,4,5,6,7},FALSE)} -> FB0049 | AT100: 4 | AU100: 7 | AV100: Email | AW100: None
...

Sheet Customers
A1: Customer_ID | B1: Customer_Name | C1: Gender | D1: Age | E1: City | F1: State | G1: Occupation | H1: Annual_Income_INR | I1: Customer_Type | J1: Phone | K1: Marital_Status | L1: Email
A2: CU0001 | B2: Swati Gupta | C2: Female | D2: 40 | E2: Kochi | F2: Kerala | G2: Business Owner | H2: 1950000 | I2: Individual | J2: 9855799273 | K2: Married | L2: swati.gupta1@example.com
A3: CU0002 | B3: Komal Gupta | C3: Female | D3: 28 | E3: Bengaluru | F3: Karnataka | G3: Retired | H3: 710000 | I3: Individual | J3: 9871705170 | K3: Single | L3: komal.gupta2@example.com
A4: CU0003 | B4: Imran Mishra | C4: Male | D4: 39 | E4: Hyderabad | F4: Telangana | G4: Engineer | H4: 1640000 | I4: Individual | J4: 9853258988 | K4: Single | L4: imran.mishra3@example.com
A5: CU0004 | B5: Anjali Mehta | C5: Female | D5: 25 | E5: Mysuru | F5: Karnataka | G5: Salaried - Private | H5: 1080000 | I5: Individual | J5: 9891917334 | K5: Married | L5: anjali.mehta4@example.com
A6: CU0005 | B6: Sachin Khanna | C6: Male | D6: 27 | E6: Jaipur | F6: Rajasthan | G6: Salaried - Private | H6: 870000 | I6: Individual | J6: 9890014570 | K6: Married | L6: sachin.khanna5@example.com
A7: CU0006 | B7: Tarun Singh | C7: Male | D7: 38 | E7: Noida | F7: Uttar Pradesh | G7: Doctor | H7: 2720000 | I7: Individual | J7: 9842255732 | K7: Married | L7: tarun.singh6@example.com
A8: CU0007 | B8: Sachin Das | C8: Male | D8: 44 | E8: Delhi | F8: Delhi | G8: Self-Employed Professional | H8: 1500000 | I8: Individual | J8: 9888055069 | K8: Married | L8: sachin.das7@example.com
A9: CU0008 | B9: Dinesh Chauhan | C9: Male | D9: 42 | E9: Bhopal | F9: Madhya Pradesh | G9: Business Owner | H9: 1900000 | I9: Individual | J9: 9851154241 | K9: Married | L9: dinesh.chauhan8@example.com
A10: CU0009 | B10: Tarun Khanna | C10: Male | D10: 36 | E10: Chandigarh | F10: Chandigarh | G10: Self-Employed Professional | H10: 1270000 | I10: Individual | J10: 9874988034 | K10: Married | L10: tarun.khanna9@example.com
A11: CU0010 | B11: Nisha Mishra | C11: Female | D11: 21 | E11: Pune | F11: Maharashtra | G11: Student/Other | H11: 590000 | I11: Individual | J11: 9849761527 | K11: Single | L11: nisha.mishra10@example.com
A12: CU0011 | B12: Jatin Sharma | C12: Male | D12: 29 | E12: Guwahati | F12: Assam | G12: Retired | H12: 660000 | I12: Individual | J12: 9826948946 | K12: Married | L12: jatin.sharma11@example.com
A13: CU0012 | B13: Arjun Agarwal | C13: Male | D13: 36 | E13: Pune | F13: Maharashtra | G13: Business Owner | H13: 2110000 | I13: Corporate | J13: 9816895666 | K13: Married | L13: arjun.agarwal12@example.com
... A721: CU0720 | B721: Anjali Khanna | C721: Female | D721: 57 | E721: Kolkata | F721: West Bengal | G721: Salaried - Private | H721: 610000 | I721: Individual | J721: 9864627534 | K721: Married | L721: anjali.khanna720@example.com

Sheet Dealers
A1: Dealer_ID | B1: Dealer_Name | C1: City | D1: State | E1: Region | F1: Dealer_Manager | G1: Established_Year | H1: Showroom_Area_SqFt | I1: Dealer_Rating
A2: D001 | B2: Delhi Autoplex | C2: Delhi | D2: Delhi | E2: North | F2: Amit Sharma | G2: 2013 | H2: 4500 | I2: 3.7
A3: D002 | B3: Gurugram Autoplex | C3: Gurugram | D3: Haryana | E3: North | F3: Amit Pillai | G3: 2007 | H3: 10000 | I3: 4
A4: D003 | B4: Panipat Motors | C4: Panipat | D4: Haryana | E4: North | F4: Amit Nair | G4: 2012 | H4: 10000 | I4: 4.2
A5: D004 | B5: Chandigarh Car World | C5: Chandigarh | D5: Chandigarh | E5: North | F5: Vikram Shah | G5: 2018 | H5: 4500 | I5: 4
A6: D005 | B6: Ludhiana Wheels | C6: Ludhiana | D6: Punjab | E6: North | F6: Kavita Sharma | G6: 2010 | H6: 12000 | I6: 4
A7: D006 | B7: Jaipur Wheels | C7: Jaipur | D7: Rajasthan | E7: North | F7: Sunil Nair | G7: 2015 | H7: 3000 | I7: 3.5
A8: D007 | B8: Lucknow Motors | C8: Lucknow | D8: Uttar Pradesh | E8: North | F8: Manoj Malhotra | G8: 2013 | H8: 3000 | I8: 4.4
A9: D008 | B9: Noida Car World | C9: Noida | D9: Uttar Pradesh | E9: North | F9: Amit Yadav | G9: 2007 | H9: 10000 | I9: 3.8
A10: D009 | B10: Mumbai Autoplex | C10: Mumbai | D10: Maharashtra | E10: West | F10: Pankaj Malhotra | G10: 2011 | H10: 12000 | I10: 3.5
A11: D010 | B11: Pune Autoplex | C11: Pune | D11: Maharashtra | E11: West | F11: Vikram Saini | G11: 2014 | H11: 3000 | I11: 4.6
A12: D011 | B12: Nagpur Motors | C12: Nagpur | D12: Maharashtra | E12: West | F12: Deepak Mehta | G12: 2019 | H12: 12000 | I12: 4.6
A13: D012 | B13: Ahmedabad Auto Hub | C13: Ahmedabad | D13: Gujarat | E13: West | F13: Manoj Malhotra | G13: 2011 | H13: 12000 | I13: 3.8
... A26: D025 | B26: Indore Wheels | C26: Indore | D26: Madhya Pradesh | E26: Central | F26: Deepak Reddy | G26: 2019 | H26: 3000 | I26: 4.7

Sheet Cars
A1: Car_ID | B1: Brand | C1: Model | D1: Segment | E1: Fuel_Type | F1: Transmission | G1: Ex_Showroom_Price_INR | H1: Launch_Year | I1: Warranty_Years
A2: C001 | B2: Maruti Suzuki | C2: Alto K10 | D2: Hatchback | E2: Petrol | F2: Manual | G2: 425000 | H2: 2022 | I2: 3
A3: C002 | B3: Maruti Suzuki | C3: Swift | D3: Hatchback | E3: Petrol | F3: Manual | G3: 650000 | H3: 2024 | I3: 3
A4: C003 | B4: Maruti Suzuki | C4: Baleno | D4: Hatchback | E4: Petrol | F4: Automatic | G4: 760000 | H4: 2022 | I4: 2
A5: C004 | B5: Maruti Suzuki | C5: Dzire | D5: Sedan | E5: Petrol | F5: Manual | G5: 690000 | H5: 2024 | I5: 3
A6: C005 | B6: Maruti Suzuki | C6: Brezza | D6: SUV | E6: Petrol | F6: Automatic | G6: 900000 | H6: 2022 | I6: 3
A7: C006 | B7: Maruti Suzuki | C7: Ertiga | D7: MPV | E7: CNG | F7: Manual | G7: 900000 | H7: 2022 | I7: 3
A8: C007 | B8: Maruti Suzuki | C8: Grand Vitara | D8: SUV | E8: Hybrid | F8: Automatic | G8: 1150000 | H8: 2022 | I8: 3
A9: C008 | B9: Hyundai | C9: i10 Nios | D9: Hatchback | E9: Petrol | F9: Manual | G9: 600000 | H9: 2023 | I9: 3
A10: C009 | B10: Hyundai | C10: i20 | D10: Hatchback | E10: Petrol | F10: Automatic | G10: 780000 | H10: 2023 | I10: 2
A11: C010 | B11: Hyundai | C11: Venue | D11: SUV | E11: Petrol | F11: Manual | G11: 800000 | H11: 2022 | I11: 3
A12: C011 | B12: Hyundai | C12: Creta | D12: SUV | E12: Diesel | F12: Automatic | G12: 1250000 | H12: 2024 | I12: 4
A13: C012 | B13: Hyundai | C13: Verna | D13: Sedan | E13: Petrol | F13: Automatic | G13: 1100000 | H13: 2023 | I13: 2
... A41: C040 | B41: Audi | C41: Q3 | D41: Luxury SUV | E41: Petrol | F41: Automatic | G41: 5400000 | H41: 2022 | I41: 5

Sheet Salespersons
A1: Salesperson_ID | B1: Salesperson_Name | C1: Gender | D1: Region | E1: Dealer_ID | F1: Joining_Date | G1: Monthly_Target_Units | H1: Column1 | I1: Column2
A2: S001 | B2: Vivek Iyer | C2: Male | D2: =_xlfn.XLOOKUP(SalesPerson[[#This Row],[Salesperson_Name]],Sales!$AG:$AG,Sales!$AA:$AA,"NA",0) -> North | E2: D001 | F2: 43507 | G2: 4 | H2: =COUNTIFS(Sales!$AG:$AG,Salespersons!$B:$B,Sales!$F:$F,"Delivered") -> 10 | I2: =IF(SalesPerson[[#This Row],[Column1]]>=SalesPerson[[#This Row],[Monthly_Target_Units]],"True","False") -> True
A3: S002 | B3: Nisha Iyer | C3: Female | D3: =_xlfn.XLOOKUP(SalesPerson[[#This Row],[Salesperson_Name]],Sales!$AG:$AG,Sales!$AA:$AA,"NA",0) -> North | E3: D001 | F3: 43468 | G3: 4 | H3: =COUNTIFS(Sales!$AG:$AG,Salespersons!$B:$B,Sales!$F:$F,"Delivered") -> 12 | I3: =IF(SalesPerson[[#This Row],[Column1]]>=SalesPerson[[#This Row],[Monthly_Target_Units]],"True","False") -> True
A4: S003 | B4: Karan Verma | C4: Male | D4: =_xlfn.XLOOKUP(SalesPerson[[#This Row],[Salesperson_Name]],Sales!$AG:$AG,Sales!$AA:$AA,"NA",0) -> North | E4: D001 | F4: 44244 | G4: 5 | H4: =COUNTIFS(Sales!$AG:$AG,Salespersons!$B:$B,Sales!$F:$F,"Delivered") -> 5 | I4: =IF(SalesPerson[[#This Row],[Column1]]>=SalesPerson[[#This Row],[Monthly_Target_Units]],"True","False") -> True
A5: S004 | B5: Lokesh Nair | C5: Male | D5: =_xlfn.XLOOKUP(SalesPerson[[#This Row],[Salesperson_Name]],Sales!$AG:$AG,Sales!$AA:$AA,"NA",0) -> North | E5: D001 | F5: 45375 | G5: 8 | H5: =COUNTIFS(Sales!$AG:$AG,Salespersons!$B:$B,Sales!$F:$F,"Delivered") -> 4 | I5: =IF(SalesPerson[[#This Row],[Column1]]>=SalesPerson[[#This Row],[Monthly_Target_Units]],"True","False") -> False
A6: S005 | B6: Mohit Bose | C6: Male | D6: =_xlfn.XLOOKUP(SalesPerson[[#This Row],[Salesperson_Name]],Sales!$AG:$AG,Sales!$AA:$AA,"NA",0) -> North | E6: D002 | F6: 44655 | G6: 4 | H6: =COUNTIFS(Sales!$AG:$AG,Salespersons!$B:$B,Sales!$F:$F,"Delivered") -> 6 | I6: =IF(SalesPerson[[#This Row],[Column1]]>=SalesPerson[[#This Row],[Monthly_Target_Units]],"True","False") -> True
A7: S006 | B7: Shweta Malhotra | C7: Female | D7: =_xlfn.XLOOKUP(SalesPerson[[#This Row],[Salesperson_Name]],Sales!$AG:$AG,Sales!$AA:$AA,"NA",0) -> North | E7: D002 | F7: 44757 | G7: 4 | H7: =COUNTIFS(Sales!$AG:$AG,Salespersons!$B:$B,Sales!$F:$F,"Delivered") -> 7 | I7: =IF(SalesPerson[[#This Row],[Column1]]>=SalesPerson[[#This Row],[Monthly_Target_Units]],"True","False") -> True
A8: S007 | B8: Ayesha Rao | C8: Female | D8: =_xlfn.XLOOKUP(SalesPerson[[#This Row],[Salesperson_Name]],Sales!$AG:$AG,Sales!$AA:$AA,"NA",0) -> North | E8: D002 | F8: 42748 | G8: 6 | H8: =COUNTIFS(Sales!$AG:$AG,Salespersons!$B:$B,Sales!$F:$F,"Delivered") -> 5 | I8: =IF(SalesPerson[[#This Row],[Column1]]>=SalesPerson[[#This Row],[Monthly_Target_Units]],"True","False") -> False
A9: S008 | B9: Mohit Nair | C9: Male | D9: =_xlfn.XLOOKUP(SalesPerson[[#This Row],[Salesperson_Name]],Sales!$AG:$AG,Sales!$AA:$AA,"NA",0) -> North | E9: D002 | F9: 43723 | G9: 5 | H9: =COUNTIFS(Sales!$AG:$AG,Salespersons!$B:$B,Sales!$F:$F,"Delivered") -> 8 | I9: =IF(SalesPerson[[#This Row],[Column1]]>=SalesPerson[[#This Row],[Monthly_Target_Units]],"True","False") -> True
A10: S009 | B10: Varun Das | C10: Male | D10: =_xlfn.XLOOKUP(SalesPerson[[#This Row],[Salesperson_Name]],Sales!$AG:$AG,Sales!$AA:$AA,"NA",0) -> North | E10: D003 | F10: 43511 | G10: 8 | H10: =COUNTIFS(Sales!$AG:$AG,Salespersons!$B:$B,Sales!$F:$F,"Delivered") -> 10 | I10: =IF(SalesPerson[[#This Row],[Column1]]>=SalesPerson[[#This Row],[Monthly_Target_Units]],"True","False") -> True
A11: S010 | B11: Rahul Rao | C11: Male | D11: =_xlfn.XLOOKUP(SalesPerson[[#This Row],[Salesperson_Name]],Sales!$AG:$AG,Sales!$AA:$AA,"NA",0) -> North | E11: D003 | F11: 45294 | G11: 5 | H11: =COUNTIFS(Sales!$AG:$AG,Salespersons!$B:$B,Sales!$F:$F,"Delivered") -> 10 | I11: =IF(SalesPerson[[#This Row],[Column1]]>=SalesPerson[[#This Row],[Monthly_Target_Units]],"True","False") -> True
A12: S011 | B12: Yash Bose | C12: Male | D12: =_xlfn.XLOOKUP(SalesPerson[[#This Row],[Salesperson_Name]],Sales!$AG:$AG,Sales!$AA:$AA,"NA",0) -> North | E12: D003 | F12: 45044 | G12: 7 | H12: =COUNTIFS(Sales!$AG:$AG,Salespersons!$B:$B,Sales!$F:$F,"Delivered") -> 12 | I12: =IF(SalesPerson[[#This Row],[Column1]]>=SalesPerson[[#This Row],[Monthly_Target_Units]],"True","False") -> True
A13: S012 | B13: Tarun Sharma | C13: Male | D13: =_xlfn.XLOOKUP(SalesPerson[[#This Row],[Salesperson_Name]],Sales!$AG:$AG,Sales!$AA:$AA,"NA",0) -> North | E13: D004 | F13: 44707 | G13: 7 | H13: =COUNTIFS(Sales!$AG:$AG,Salespersons!$B:$B,Sales!$F:$F,"Delivered") -> 17 | I13: =IF(SalesPerson[[#This Row],[Column1]]>=SalesPerson[[#This Row],[Monthly_Target_Units]],"True","False") -> True
... A78: S077 | B78: Faisal Shah | C78: Male | D78: =_xlfn.XLOOKUP(SalesPerson[[#This Row],[Salesperson_Name]],Sales!$AG:$AG,Sales!$AA:$AA,"NA",0) -> Central | E78: D025 | F78: 43519 | G78: 6 | H78: =COUNTIFS(Sales!$AG:$AG,Salespersons!$B:$B,Sales!$F:$F,"Delivered") -> 11 | I78: =IF(SalesPerson[[#This Row],[Column1]]>=SalesPerson[[#This Row],[Monthly_Target_Units]],"True","False") -> True

Sheet Feedback
A1: Order_ID | B1: Feedback_ID | C1: Feedback_Date | D1: Rating_1_to_5 | E1: Recommend_Score_0_to_10 | F1: Feedback_Channel | G1: Complaint_Category
A2: ORD00002 | B2: FB0001 | C2: 45328 | D2: 4 | E2: 8 | F2: Dealer Visit | G2: None
A3: ORD00003 | B3: FB0002 | C3: 45320 | D3: 5 | E3: 10 | F3: Phone | G3: None
A4: ORD00004 | B4: FB0003 | C4: 45341 | D4: 3 | E4: 4 | F4: Dealer Visit | G4: Vehicle Quality
A5: ORD00005 | B5: FB0004 | C5: 45337 | D5: 5 | E5: 10 | F5: Email | G5: None
A6: ORD00006 | B6: FB0005 | C6: 45357 | D6: 4 | E6: 9 | F6: Dealer Visit | G6: None
A7: ORD00007 | B7: FB0006 | C7: 45310 | D7: 5 | E7: 10 | F7: Email | G7: None
A8: ORD00008 | B8: FB0007 | C8: 45338 | D8: 4 | E8: 9 | F8: Phone | G8: None
A9: ORD00009 | B9: FB0008 | C9: 45314 | D9: 5 | E9: 10 | F9: Phone | G9: None
A10: ORD00010 | B10: FB0009 | C10: 45329 | D10: 4 | E10: 9 | F10: Email | G10: None
A11: ORD00011 | B11: FB0010 | C11: 45348 | D11: 4 | E11: 8 | F11: Phone | G11: None
A12: ORD00014 | B12: FB0011 | C12: 45342 | D12: 3 | E12: 6 | F12: Online Survey | G12: After-Sales Support
A13: ORD00015 | B13: FB0012 | C13: 45341 | D13: 5 | E13: 10 | F13: Phone | G13: None
... A507: ORD00998 | B507: FB0506 | C507: 46326 | D507: 4 | E507: 10 | F507: Phone | G507: None

Sheet Data_Dictionary
A1: Sheet | B1: Column | C1: Description
A2: Sales | B2: Order_ID | C2: Unique order number (primary key)
A3: Sales | B3: Order_Date | C3: Date booking was placed
A4: Sales | B4: Customer_ID | C4: Look up in Customers
A5: Sales | B5: Car_ID | C5: Look up in Cars (price, brand, model, segment, fuel)
A6: Sales | B6: Dealer_ID | C6: Look up in Dealers (city, state, region)
A7: Sales | B7: Salesperson_ID | C7: Look up in Salespersons (name, target)
A8: Sales | B8: Discount_INR | C8: Discount given on the order
A9: Sales | B9: Order_Status | C9: Delivered / Pending Delivery / Cancelled
A10: Customers | B10: Customer_ID | C10: Primary key
A11: Dealers | B11: Dealer_ID | C11: Primary key
A12: Cars | B12: Car_ID | C12: Primary key; Ex_Showroom_Price_INR is the list price
... A15: TIP | B15: Calculated columns to build | C15: Final_Price = Ex_Showroom_Price - Discount | Revenue | Delivery_Days | Month/Year | Age_Group | Income_Band | Target achievement
A16: TIP | B16: Example XLOOKUP | C16: =_xludf.XLOOKUP(#REF!,#REF!,#REF!,"Not found") -> #NAME?
